Workbook
Name Calls_Scores: raw_calls!$T$2:$T$1000
Name Deals_Source: raw_deals!$J$2:$J$1000
Name Deals_Amount: raw_deals!$C$2:$C$1000
Name Payments_Amount: raw_payments!$E$2:$E$1000
Name USERS_ROLES_MAP: '⚙️ Настройки'!$J$10:$L$100
Name Marketing_Leads: raw_marketing!$H$2:$H$1000
Name SHEETS_LIST: '🔐 RBAC_Matrix'!$A$2:$A$46
Name Deals_ID: raw_deals!$A$2:$A$1000
Name Deals_Stage: raw_deals!$D$2:$D$1000
Name ROLES_LIST: '🔐 RBAC_Matrix'!$D$1:$J$1
Name Deals_Manager: raw_deals!$H$2:$H$1000
Name Payments_Type: raw_payments!$F$2:$F$1000
Name Marketing_Spend: raw_marketing!$E$2:$E$1000
Name Deals_IsWon: raw_deals!$O$2:$O$1000

Sheet ⚡ Экспресс_Калькулятор_3_Цифры
B1: ⚡ ЭКСПРЕСС-КАЛЬКУЛЯТОР УПУЩЕННОЙ ПРИБЫЛИ ОП (ДИАГНОСТИКА ЗА 30 СЕКУНД)
A2: =HYPERLINK("https://docs.google.com/spreadsheets/d/1QnjrrbpqhYssofchee7G06szWrFvBCcOqGIVokjqdVc/edit#gid=1377308911", "📄 1. One-Pager") -> 📄 1. One-Pager | B2: =HYPERLINK("https://docs.google.com/spreadsheets/d/1QnjrrbpqhYssofchee7G06szWrFvBCcOqGIVokjqdVc/edit#gid=1847360667", "⚡ 2. Пульс компании") -> ⚡ 2. Пульс компании | C2: =HYPERLINK("https://docs.google.com/spreadsheets/d/1QnjrrbpqhYssofchee7G06szWrFvBCcOqGIVokjqdVc/edit#gid=777000301", "📋 3. Пульт РОПа") -> 📋 3. Пульт РОПа | D2: =HYPERLINK("https://docs.google.com/spreadsheets/d/1QnjrrbpqhYssofchee7G06szWrFvBCcOqGIVokjqdVc/edit#gid=777000101", "💸 4. 7 Грехов ОП") -> 💸 4. 7 Грехов ОП | E2: =HYPERLINK("https://docs.google.com/spreadsheets/d/1QnjrrbpqhYssofchee7G06szWrFvBCcOqGIVokjqdVc/edit#gid=811060921", "🎯 5. Action Center") -> 🎯 5. Action Center | F2: =HYPERLINK("https://docs.google.com/spreadsheets/d/1QnjrrbpqhYssofchee7G06szWrFvBCcOqGIVokjqdVc/edit#gid=852624872", "🎙️ 6. ИИ-Аудит") -> 🎙️ 6. ИИ-Аудит | G2: =HYPERLINK("https://docs.google.com/spreadsheets/d/1QnjrrbpqhYssofchee7G06szWrFvBCcOqGIVokjqdVc/edit#gid=777000201", "⚡ 7. Экспресс 3 цифры") -> ⚡ 7. Экспресс 3 цифры | H2: =HYPERLINK("https://docs.google.com/spreadsheets/d/1QnjrrbpqhYssofchee7G06szWrFvBCcOqGIVokjqdVc/edit#gid=60692888", "🧪 8. QA Suite") -> 🧪 8. QA Suite | I2: =HYPERLINK("https://docs.google.com/spreadsheets/d/1QnjrrbpqhYssofchee7G06szWrFvBCcOqGIVokjqdVc/edit#gid=985355776", "⚙️ 9. Настройки") -> ⚙️ 9. Настройки
A4: 🎛️ ВВЕДИТЕ 3 ЦИФРЫ ВАШЕГО БИЗНЕСА: | C4: 📊 БАЗОВЫЕ ПОКАЗАТЕЛИ (AS-IS): | G4: Категория капитала | H4: Объем, ₽
A5: 1. Входящий поток лидов в месяц (шт): | B5: 150 | C5: Емкость базы (при 100% конверсии): | D5: =B5 * B6 -> 60000000 | G5: Факт выручки (As-Is) | H5: =D7 -> 1650000
A6: 2. Средний чек закрытой сделки (₽): | B6: 400000 | C6: Текущая конверсия в оплату (факт): | D6: =D7/MAX(B5*B6, 1) -> 0.0275 | G6: Упущенная прибыль ОП | H6: =A11 -> 1122000
A7: 3. Количество менеджеров в ОП (чел): | B7: 4 | C7: Текущая выручка месяца (факт): | D7: =calc_engine!B19 -> 1650000 | G7: Потенциал кассы (To-Be) | H7: =C11 -> 1986600
A8: Отраслевой сегмент компании: | B8: B2B Услуги / Производство | C8: Нагрузка на одного менеджера (лидов): | D8: =ROUND(B5 / MAX(B7,1), 0) & " лид/мес" -> 38 лид/мес
A10: 🔴 ВЫЯВЛЕННЫЙ РИСК ПОТЕРЬ | B10: 🟢 КОНСЕРВАТИВНЫЙ (+15%) | C10: 🚀 БАЗОВЫЙ ПЛАН (+30%) | D10: ⭐ ОПТИМИСТИЧНЫЙ (+50%)
A11: =SUM(D15:D18) -> 1122000 | B11: =D7 + A11*0.15 -> 1818300 | C11: =D7 + A11*0.3 -> 1986600 | D11: =D7 + A11*0.5 -> 2211000
A13: 📊 РАСШИФРОВКА ФИНАНСОВЫХ УТЕЧЕК ПО 4 УЗКИМ МЕСТАМ
A14: № | B14: Узкое место воронки продаж | C14: Отраслевой бенчмарк потерь | D14: Упущенная прибыль, ₽/мес | E14: Причина утечки | F14: Как закрываем за 14 дней
A15: 1 | B15: Слив лидов на звонках (нет Next Step) | C15: 28% выручки теряется из-за ошибок менеджеров на звонках (бенчмарк 2026) | D15: =ROUND(D7 * '⚙️ Настройки'!B43, 0) -> 462000 | E15: Менеджеры консультируют, но не закрывают на дату | F15: ИИ-аудит 100% звонков + чек-лист Next Step
A16: 2 | B16: Зависание сделок на этапе КП > 48ч | C16: 18% выручки теряется из-за просрочки follow-up | D16: =ROUND(D7 * '⚙️ Настройки'!B44, 0) -> 297000 | E16: Клиент остывает, пока менеджер ждет звонка | F16: Авторадар SLA 48ч + эскалация РОПу на 3-й день
A17: 3 | B17: Брошенные отказники без дожима (L1-L4) | C17: 12% — потенциал реактивации списанных отказников CRM | D17: =ROUND(D7 * '⚙️ Настройки'!B45, 0) -> 198000 | E17: Сделки списаны в архив без реактивации | F17: AI Recovery Engine: автодожим в WhatsApp/TG
A18: 4 | B18: Зависшая дебиторка и задержка оплат | C18: 10% выставленных счетов зависают на согласовании (DSO) | D18: =ROUND(D7 * '⚙️ Настройки'!B46, 0) -> 165000 | E18: Нет платежного календаря и контроля сроков | F18: Платежный календарь DSO + автонапоминания
B19: ИТОГО УПУЩЕННОЙ ПРИБЫЛИ В МЕСЯЦ: | D19: =SUM(D15:D18) -> 1122000 | E19: ПОТЕНЦИАЛ БЫСТРОГО ВОЗВРАТА: | F19: =ROUND(D19 * '⚙️ Настройки'!B48, 0) & " ₽ в первый месяц" -> 392700 ₽ в первый месяц
A21: 🎁 СЛЕДУЮЩИЙ ШАГ: БЕСПЛАТНЫЙ ТЕСТ-ДРАЙВ НА 3 ВАШИХ ЗВОНКАХ
A22: Хотите проверить эту математику на реальных данных вашей компании за 15 минут?
A23: 👉 Отправьте 3 аудиозаписи любых вчерашних звонков ваших менеджеров в Telegram.
A24: ИИ бесплатно разберет их по 13 критериям, покажет ошибки речи и рассчитает точную сумму под угрозой слива.
A25: =HYPERLINK("https://ai-rop.ru/?utm_source=sheets_calculator", "🚀 ЗАПУСТИТЬ БЕСПЛАТНЫЙ ТЕСТ-ДРАЙВ НА 3 ЗВОНКАХ (ПЕРЕЙТИ НА AI-ROP.RU)") -> 🚀 ЗАПУСТИТЬ БЕСПЛАТНЫЙ ТЕСТ-ДРАЙВ НА 3 ЗВОНКАХ (ПЕРЕЙТИ НА AI-ROP.RU)
A26: =HYPERLINK("#'💸 Диагностика_Утечек_ОП'!A18", "Нужен комплексный аудит отдела продаж? 👉 Экономика спринта оптимизации (450 000 ₽)") -> Нужен комплексный аудит отдела продаж? 👉 Экономика спринта оптимизации (450 000 ₽)
A27: 🔒 Конфиденциально • Без передачи персональных данных • Экспресс-разбор за 15 минут (152-ФЗ РФ)

Sheet 📋 Пульт_РОПа_15_Минут
A1: =IF(ISNUMBER(SEARCH("CEO", '⚙️ Настройки'!$B$10)), "📋 СТРАТЕГИЧЕСКИЙ ПУЛЬТ СОБСТВЕННИКА: «5 РЕШЕНИЙ МЕСЯЦА»", IF(ISNUMBER(SEARCH("KAM", '⚙️ Настройки'!$B$10)), "📋 ЛИЧНЫЙ ACTION-LIST МЕНЕДЖЕРА НА СЕГОДНЯ (ПЕТРОВ А.)", IF(ISNUMBER(SEARCH("SDR", '⚙️ Настройки'!$B$10)), "📞 ПУЛЬТ ТЕЛЕМАРКЕТОЛОГА: «СКРИПТЫ И ГОРЯЧИЕ ЗВОНКИ»", IF(ISNUMBER(SEARCH("CMO", '⚙️ Настройки'!$B$10)), "📋 ПУЛЬТ ОПТИМИЗАЦИИ ТРАФИКА: «ТОЧКИ СЛИВА БЮДЖЕТА»", IF(ISNUMBER(SEARCH("CFO", '⚙️ Настройки'!$B$10)), "📋 ПЛАТЕЖНЫЙ КАЛЕНДАРЬ И ДЕБИТОРКА: «СРОЧНЫЕ СЧЕТА»", IF(OR(ISNUMBER(SEARCH("Admin", '⚙️ Настройки'!$B$10)), ISNUMBER(SEARCH("Администр", '⚙️ Настройки'!$B$10))), "🔧 ПУЛЬТ АДМИНИСТРАТОРА: «МОНИТОРИНГ И НАСТРОЙКИ СИСТЕМЫ»", "📋 ОПЕРАТИВНЫЙ ПУЛЬТ РОПа: «15 МИНУТ В ДЕНЬ»")))))) -> 📋 СТРАТЕГИЧЕСКИЙ ПУЛЬТ СОБСТВЕННИКА: «5 РЕШЕНИЙ МЕСЯЦА»
A2: =HYPERLINK("https://docs.google.com/spreadsheets/d/1QnjrrbpqhYssofchee7G06szWrFvBCcOqGIVokjqdVc/edit#gid=1377308911", "📄 1. One-Pager") -> 📄 1. One-Pager | B2: =HYPERLINK("https://docs.google.com/spreadsheets/d/1QnjrrbpqhYssofchee7G06szWrFvBCcOqGIVokjqdVc/edit#gid=1847360667", "⚡ 2. Пульс компании") -> ⚡ 2. Пульс компании | C2: =HYPERLINK("https://docs.google.com/spreadsheets/d/1QnjrrbpqhYssofchee7G06szWrFvBCcOqGIVokjqdVc/edit#gid=777000301", "📋 3. Пульт РОПа") -> 📋 3. Пульт РОПа | D2: =HYPERLINK("https://docs.google.com/spreadsheets/d/1QnjrrbpqhYssofchee7G06szWrFvBCcOqGIVokjqdVc/edit#gid=777000101", "💸 4. 7 Грехов ОП") -> 💸 4. 7 Грехов ОП | E2: =HYPERLINK("https://docs.google.com/spreadsheets/d/1QnjrrbpqhYssofchee7G06szWrFvBCcOqGIVokjqdVc/edit#gid=811060921", "🎯 5. Action Center") -> 🎯 5. Action Center | F2: =HYPERLINK("https://docs.google.com/spreadsheets/d/1QnjrrbpqhYssofchee7G06szWrFvBCcOqGIVokjqdVc/edit#gid=852624872", "🎙️ 6. ИИ-Аудит") -> 🎙️ 6. ИИ-Аудит | G2: =HYPERLINK("https://docs.google.com/spreadsheets/d/1QnjrrbpqhYssofchee7G06szWrFvBCcOqGIVokjqdVc/edit#gid=777000201", "⚡ 7. Экспресс 3 цифры") -> ⚡ 7. Экспресс 3 цифры | H2: =HYPERLINK("https://docs.google.com/spreadsheets/d/1QnjrrbpqhYssofchee7G06szWrFvBCcOqGIVokjqdVc/edit#gid=60692888", "🧪 8. QA Suite") -> 🧪 8. QA Suite | I2: =HYPERLINK("https://docs.google.com/spreadsheets/d/1QnjrrbpqhYssofchee7G06szWrFvBCcOqGIVokjqdVc/edit#gid=985355776", "⚙️ 9. Настройки") -> ⚙️ 9. Настройки
A4: Звонков за вчера | B4: Диалогов с браком (<9) | C4: Сделок с угрозой срыва | D4: Сумма в зоне риска прямо сейчас | E4: Статус дня для РОПа
A5: =calc_engine!B41 -> 6 | B5: =COUNTIFS(raw_calls!$T$2:$T1000, "<9") -> 2 | C5: =COUNTIF(E9:E13, "*КРИТИЧЕСКИЙ*") -> 2 | D5: =SUM(D9:D13) -> 2730000 | E5: =IF(C5>0, "🚨 ТРЕБУЕТСЯ 15 МИНУТ КОНТРОЛЯ РОПа", "🟢 ВСЕ В РАБОЧЕМ ГРАФИКЕ") -> 🚨 ТРЕБУЕТСЯ 15 МИНУТ КОНТРОЛЯ РОПа
A7: ="🎯 " & IF(ISNUMBER(SEARCH("CEO", '⚙️ Настройки'!$B$10)), "ТОП-5 СТРАТЕГИЧЕСКИХ РЕШЕНИЙ ДЛЯ ЗАЩИТЫ КАПИТАЛА БИЗНЕСА", IF(ISNUMBER(SEARCH("KAM", '⚙️ Настройки'!$B$10)), "МОЙ ПЕРСОНАЛЬНЫЙ СПИСОК ГОРЯЩИХ СДЕЛОК НА СЕГОДНЯ", IF(ISNUMBER(SEARCH("SDR", '⚙️ Настройки'!$B$10)), "ТОП-5 ЗВОНКОВ В РИСКЕ И СРОЧНАЯ КВАЛИФИКАЦИЯ ЛИДОВ", IF(ISNUMBER(SEARCH("CMO", '⚙️ Настройки'!$B$10)), "ТОП-5 ДЕЙСТВИЙ ПО ОПТИМИЗАЦИИ РЕКЛАМНЫХ КАМПАНИЙ", IF(ISNUMBER(SEARCH("CFO", '⚙️ Настройки'!$B$10)), "ТОП-5 СРОЧНЫХ ДЕЙСТВИЙ ПО СБОРУ ДЕБИТОРКИ И ЗАЩИТЕ КАССЫ", IF(OR(ISNUMBER(SEARCH("Admin", '⚙️ Настройки'!$B$10)), ISNUMBER(SEARCH("Администр", '⚙️ Настройки'!$B$10))), "ТОП-5 СИСТЕМНЫХ АЛЕРТОВ И ПРОВЕРКА ЦЕЛОСТНОСТИ REVOPS", "ТОП-5 СРОЧНЫХ ДЕЙСТВИЙ ДЛЯ РОПа НА СЕГОДНЯ (DAILY ACTION LIST)")))))) -> 🎯 ТОП-5 СТРАТЕГИЧЕСКИХ РЕШЕНИЙ ДЛЯ ЗАЩИТЫ КАПИТАЛА БИЗНЕСА
A8: № | B8: Сделка / Контрагент | C8: Суть проблемы и симптом | D8: Сумма в риске | E8: Приоритет | F8: Срочное действие РОПа (Что сделать) | G8: Чекбокс | H8: 🤖 Сгенерированный оффер ИИ-дожима (WhatsApp / Скрипт РОПа)
A9: 1 | B9: Сделка D-104 (ООО «Вектор Плюс») | C9: Зависание на этапе КП: 12 дней без ответа (норма 48ч) | D9: =VLOOKUP("D-104", raw_deals!$A$2:$C$1000, 3, FALSE) -> 850000 | E9: 🔴 КРИТИЧЕСКИЙ | F9: Запросить статус у КАМа Петрова, согласовать скидку/рассрочку | G9: В РАБОТЕ | H9: ="Добрый день, Алексей! Вижу, наш расчет по договору согласован. Чтобы зафиксировать спецусловия октября со скидкой 7%, предлагаю сегодня подписать спецификацию. Слот для звонка: 14:30. Удобно?" -> Добрый день, Алексей! Вижу, наш расчет по договору согласован. Чтобы зафиксировать спецусловия октября со скидкой 7%, предлагаю сегодня подписать спецификацию. Слот для звонка: 14:30. Удобно?
A10: 2 | B10: Звонок C-505 / Сделка D-109 (ООО «ПромКомплект») | C10: Менеджер сорвал контакт (балл речи 2/13), клиент ушел в отказ | D10: =VLOOKUP("D-109", raw_deals!$A$2:$C$1000, 3, FALSE) -> 600000 | E10: 🔴 КРИТИЧЕСКИЙ | F10: Личный звонок РОПа ЛПР до 12:00: перехват сделки от лица руководства | G10: В РАБОТЕ | H10: ="Михаил Сергеевич, добрый день! Это Дмитрий Иванов, коммерческий директор. Прослушал вчерашний диалог с нашим менеджером — приношу извинения за неполную консультацию. Лично подготовил для вас проект с расширенной гарантией 24 мес. Уделите 5 минут?" -> Михаил Сергеевич, добрый день! Это Дмитрий Иванов, коммерческий директор. Прослушал вчерашний диалог с нашим менеджером — приношу извинения за неполную консультацию. Лично подготовил для вас проект с расширенной гарантией 24 мес. Уделите 5 минут?
A11: 3 | B11: Звонок C-503 / Сделка D-106 (ООО «СнабСервис») | C11: В диалоге не зафиксирована дата встречи (балл речи 6/13) | D11: =VLOOKUP("D-106", raw_deals!$A$2:$C$1000, 3, FALSE) -> 280000 | E11: 🟡 СРЕДНИЙ | F11: Поставить задачу менеджеру Петрову: перезвонить и назначить слот встречи | G11: В РАБОТЕ | H11: ="Игорь, приветствую! Направил вам 2 слота на онлайн-демо платформы: сегодня в 16:00 или завтра в 11:30. За 15 минут покажем связку с вашей CRM. Какой слот забронировать?" -> Игорь, приветствую! Направил вам 2 слота на онлайн-демо платформы: сегодня в 16:00 или завтра в 11:30. За 15 минут покажем связку с вашей CRM. Какой слот забронировать?
A12: 4 | B12: Сделка D-107 (ООО «ТехноПром») | C12: Счет просрочен на 9 дней (сумма 150 000 ₽) | D12: =VLOOKUP("INV-203", raw_invoices!$A$2:$G$1000, 7, FALSE) -> 150000 | E12: 🟡 СРЕДНИЙ | F12: Отправить триггерное напоминание в WhatsApp бухгалтеру клиента | G12: В РАБОТЕ | H12: ="Ольга, здравствуйте! Бухгалтерия напоминает: по счету INV-203 сегодня крайний день резерва оборудования по льготному курсу. Выставить ссылку на моментальную оплату через СБП?" -> Ольга, здравствуйте! Бухгалтерия напоминает: по счету INV-203 сегодня крайний день резерва оборудования по льготному курсу. Выставить ссылку на моментальную оплату через СБП?
A13: 5 | B13: Сделка D-103 (ООО «ИнвестХолдинг») | C13: Нагрузка 80%, 4 ключевые сделки висят на РОПе | D13: =calc_engine!E43 -> 850000 | E13: 🟡 СРЕДНИЙ | F13: Делегировать 2 входящие сделки на КАМа (у КАМа загрузка всего 4%) | G13: В РАБОТЕ | H13: ="Регламентное действие: передать права ответственного по сделке D-102 на КАМа Петрова (свободная емкость 75%). РОПу оставить контроль ключевых контрольных точек." -> Регламентное действие: передать права ответственного по сделке D-102 на КАМа Петрова (свободная емкость 75%). РОПу оставить контроль ключевых контрольных точек.
B14: ИТОГО ДЕНЕГ В ЗОНЕ РИСКА СЕГОДНЯ: | D14: =SUM(D9:D13) -> 2730000 | E14: СПАСЕННАЯ ВЫРУЧКА: | F14: При выполнении всех 5 действий | G14: 100% защита
E17: ⏱️ ЭКСПРЕСС-РЕГЛАМЕНТ РОПа (15 МИНУТ/ДЕНЬ)
E18: 09:00 - 09:05 | F18: Проверка ночного ИИ-аудита: 2 звонка с браком (<9 баллов)
E19: 09:05 - 09:10 | F19: Перехват сделки D-109 (600 т.р.) и звонок ЛПР до 12:00
E20: 09:10 - 09:13 | F20: Согласование спецусловий по D-104 (850 т.р.)
E21: 09:13 - 09:15 | F21: Делегирование 2 сделок с РОПа на свободного КАМа
E22: Результат: | F22: 2 730 000 ₽ защищено от слива за 15 минут

Sheet 🎙️ ИИ_Аудит
A1: 🎙️ ИИ-СУПЕРВАЙЗЕР ЗВОНКОВ: РЕЧЕВАЯ АНАЛИТИКА 100% ДИАЛОГОВ (WHISPER LARGE V3 + LLM)
A2: ⚡ Экспресс-Калькулятор | D2: 📋 Пульт РОПа | G2: 🎙️ ИИ-Аудит звонков | K2: 💸 7 Грехов ОП | N2: 📄 One-Pager | Q2: 🔐 152-ФЗ Контур Безопасности
A3: Проанализировано звонков | C3: Средний балл качества | E3: Фиксация жесткого Next Step | G3: Критический брак речи (<9) | J3: Выручка под угрозой слива | M3: Вердикт ИИ-супервайзера
A4: 25 звонков / сут | C4: 8.9 из 13 | E4: 60.0% (норма ≥85%) | G4: 6 диалогов | J4: 2,840,000 ₽ | M4: 🚨 ВЫСОКИЙ РИСК СЛИВА VIP-КЛИЕНТОВ (ТРЕБУЕТСЯ ВМЕШАТЕЛЬСТВО РОПа)
A6: 👥 РЕЙТИНГ МЕНЕДЖЕРОВ ОП ПО КАЧЕСТВУ РЕЧИ (ЛИДЕРБОРД РОПа)
A7: № | B7: Менеджер ОП | C7: Звонков | D7: Ср. балл /13 | E7: Next Step % | F7: Talk/Listen (норма ≥45%) | G7: Зависших сделок | H7: Сумма риска (₽) | I7: Грейд ИИ | J7: Статус и рекомендация РОПу
A8: 1 | B8: Алексей Мельников | C8: 6 | D8: 12.2 | E8: 100.0% | F8: 48% / 52% | G8: 0 | H8: 0 ₽ | I8: ⭐ А (Эталон) | J8: Эталонный скрипт, рекомендован в базу знаний компании
A9: 2 | B9: Елена Васильева | C9: 5 | D9: 10.8 | E9: 80.0% | F9: 51% / 49% | G9: 1 | H9: 160,000 ₽ | I9: 🟢 B (Норма) | J9: Высокая конверсия, мелкие замечания по регламенту встречи
A10: 3 | B10: Анна Соколова | C10: 5 | D10: 8.4 | E10: 60.0% | F10: 58% / 42% | G10: 2 | H10: 480,000 ₽ | I10: 🟡 C (Зона риска) | J10: Забывает фиксировать дату звонка, требуется тренинг
A11: 4 | B11: Дмитрий Ковалев | C11: 5 | D11: 6.2 | E11: 40.0% | F11: 72% / 28% | G11: 3 | H11: 1,100,000 ₽ | I11: 🔴 D (Брак речи) | J11: Срыв контакта, перебивание клиента, демпинг скидок
A12: 5 | B12: Иван Попов | C12: 4 | D12: 5.5 | E12: 25.0% | F12: 79% / 21% | G12: 3 | H12: 1,100,000 ₽ | I12: 🔴 D (Брак речи) | J12: Режим 'автоответчика', нет попыток закрытия на встречу
A13: ИТОГО ПО ОТДЕЛУ ПРОДАЖ: | C13: 25 | D13: 8.9 / 13 | E13: 60.0% | F13: 61% / 39% | G13: 9 | H13: 2,840,000 ₽ | I13: ⚠️ РИСК | J13: Требуется экспресс-коучинг по отработке возражений
A15: 🔍 ДЕТАЛИЗИРОВАННАЯ МАТРИЦА ОЦЕНКИ ЗВОНКОВ ПО ВСЕМ 13 КРИТЕРИЯМ (0 / 1)
A16: Call ID | B16: Сделка / Клиент | C16: Менеджер | D16: Сумма (₽) | E16: Длит. | F16: Этап CRM | G16: К1 NextStep | H16: К2 Иниц. | I16: К3 ЛПР | J16: К4 Боли | K16: К5 Дорого | L16: К6 Подумаю | M16: К7 Кейсы | N16: К8 Закрытие | O16: К9 Привет. | P16: К10 Речь | Q16: К11 Слушан. | R16: К12 Итог | S16: К13 Маржа | T16: Балл /13 | U16: Статус ИИ | V16: Сумма в риске, ₽
A17: C-501 | B17: D-101 (ООО Вектор Плюс) | C17: Мельников | D17: 850,000 ₽ | E17: 05:40 | F17: КП отправлено | G17: 1 | H17: 1 | I17: 1 | J17: 1 | K17: 1 | L17: 1 | M17: 1 | N17: 1 | O17: 1 | P17: 1 | Q17: 1 | R17: 1 | S17: 1 | T17: 13 | U17: ⭐ ЭТАЛОН | V17: 0 ₽
A18: C-502 | B18: D-104 (ООО Вектор Плюс) | C18: Васильева | D18: 850,000 ₽ | E18: 04:20 | F18: Переговоры | G18: 1 | H18: 1 | I18: 1 | J18: 1 | K18: 1 | L18: 0 | M18: 1 | N18: 1 | O18: 1 | P18: 1 | Q18: 1 | R18: 1 | S18: 1 | T18: 12 | U18: 🟢 В НОРМЕ | V18: 0 ₽
A19: C-503 | B19: D-106 (ООО СнабСервис) | C19: Соколова | D19: 280,000 ₽ | E19: 03:10 | F19: Встреча/Демо | G19: 0 | H19: 1 | I19: 1 | J19: 0 | K19: 1 | L19: 0 | M19: 1 | N19: 0 | O19: 1 | P19: 0 | Q19: 1 | R19: 0 | S19: 1 | T19: 7 | U19: ⚠️ РИСК | V19: 280,000 ₽
A20: C-504 | B20: D-107 (ООО ТехноПром) | C20: Соколова | D20: 150,000 ₽ | E20: 06:15 | F20: Квалификация | G20: 1 | H20: 1 | I20: 1 | J20: 0 | K20: 1 | L20: 1 | M20: 0 | N20: 0 | O20: 1 | P20: 1 | Q20: 0 | R20: 1 | S20: 1 | T20: 9 | U20: ⚠️ РИСК | V20: 150,000 ₽
A21: C-505 | B21: D-109 (ООО ПромКомплект) | C21: Ковалев | D21: 600,000 ₽ | E21: 03:30 | F21: КП отправлено | G21: 0 | H21: 0 | I21: 0 | J21: 0 | K21: 0 | L21: 0 | M21: 0 | N21: 0 | O21: 1 | P21: 0 | Q21: 0 | R21: 0 | S21: 1 | T21: 2 | U21: ❌ СЛИВ | V21: 600,000 ₽
A22: C-506 | B22: D-111 (ООО Глобал Инвест) | C22: Мельников | D22: 3,000,000 ₽ | E22: 07:15 | F22: Финальные условия | G22: 1 | H22: 1 | I22: 1 | J22: 1 | K22: 1 | L22: 1 | M22: 1 | N22: 1 | O22: 1 | P22: 1 | Q22: 1 | R22: 1 | S22: 1 | T22: 13 | U22: ⭐ ЭТАЛОН | V22: 0 ₽
A23: C-507 | B23: D-114 (ООО АльфаТрейд) | C23: Ковалев | D23: 500,000 ₽ | E23: 04:45 | F23: Дожим договора | G23: 0 | H23: 1 | I23: 1 | J23: 0 | K23: 0 | L23: 0 | M23: 1 | N23: 0 | O23: 1 | P23: 0 | Q23: 0 | R23: 1 | S23: 0 | T23: 5 | U23: ❌ СЛИВ | V23: 500,000 ₽
A24: C-508 | B24: D-118 (ООО СтройХолдинг) | C24: Попов | D24: 650,000 ₽ | E24: 02:50 | F24: Входящий лид | G24: 0 | H24: 0 | I24: 1 | J24: 0 | K24: 0 | L24: 0 | M24: 0 | N24: 0 | O24: 1 | P24: 1 | Q24: 0 | R24: 1 | S24: 0 | T24: 4 | U24: ❌ СЛИВ | V24: 650,000 ₽
A25: C-509 | B25: D-121 (ООО СпецМаш) | C25: Васильева | D25: 420,000 ₽ | E25: 05:10 | F25: Презентация КП | G25: 1 | H25: 1 | I25: 1 | J25: 1 | K25: 1 | L25: 1 | M25: 1 | N25: 0 | O25: 1 | P25: 1 | Q25: 1 | R25: 1 | S25: 1 | T25: 12 | U25: 🟢 В НОРМЕ | V25: 0 ₽
A26: C-510 | B26: D-125 (ООО МегаТранс) | C26: Попов | D26: 450,000 ₽ | E26: 03:40 | F26: Квалификация | G26: 0 | H26: 0 | I26: 0 | J26: 1 | K26: 1 | L26: 0 | M26: 1 | N26: 0 | O26: 1 | P26: 1 | Q26: 0 | R26: 1 | S26: 0 | T26: 6 | U26: ⚠️ РИСК | V26: 450,000 ₽
A27: ИТОГО ПОТЕРЬ И РИСКОВ ПО ЗВОНКАМ: | D27: 7,750,000 ₽ | T27: 8.9 ср. | U27: 6 сливов | V27: 2,840,000 ₽
A29: 🚨 РЕЕСТР ДЕФЕКТОВ РЕЧИ: РАСШИФРОВАННЫЕ ЦИТАТЫ ИЗ РАЗГОВОРОВ И РЕШЕНИЯ РОПа
A30: Call ID | B30: Сделка / Контрагент | C30: Менеджер | D30: Сумма в риске | E30: Критический дефект речи | G30: 💬 Цитата из диалога (Расшифровка Whisper Large V3) | N30: 🤖 Решение ИИ и Срочное действие РОПа
A31: C-505 | B31: D-109 (ООО «ПромКомплект») | C31: Дмитрий Ковалев | D31: 600,000 ₽ | E31: Срыв контакта / грубость при цене | G31: Клиент: «Почему у вас смета на 15% выше рынка?» → Менеджер: «Не знаю, везде всё дорожает. Не устраивает — берите у конкурентов без гарантии» | N31: 🚨 Экстренный звонок РОПа ЛПР до 12:00: принести извинения за консультацию, перехватить сделку, дать проект со спец-гарантией 24 мес.
A32: C-503 | B32: D-106 (ООО «СнабСервис») | C32: Анна Соколова | D32: 280,000 ₽ | E32: Слив жесткого Next Step (в никуда) | G32: Менеджер: «Я вам КП на почту сбросила, посмотрите когда время будет». Клиент: «Хорошо, если что наберу» | N32: Направить клиенту в WhatsApp 2 конкретных слота встречи (сегодня 16:00 / завтра 11:30) с демонстрацией интеграции с CRM.
A33: C-507 | B33: D-114 (ООО «АльфаТрейд») | C33: Дмитрий Ковалев | D33: 500,000 ₽ | E33: Необоснованная скидка вместо ценности | G33: Клиент: «У нас бюджет строго ограничен». Менеджер: «Ну ладно, согласую вам скидку 10% прямо сейчас» | N33: Заблокировать выставление счета со скидкой в CRM. РОПу пересогласовать условия: скидка 5% только в обмен на 100% предоплату за 24ч.
A34: C-508 | B34: D-118 (ООО «СтройХолдинг») | C34: Иван Попов | D34: 650,000 ₽ | E34: Слив возражения «Я подумаю» | G34: Клиент: «Нам нужно всё обдумать и посоветоваться с руководством». Менеджер: «Да, конечно, думайте» (повесил трубку) | N34: Передать лида старшему КАМу. Отправить в WhatsApp отраслевой кейс с аналогичным объектом и окупаемостью за 21 день.
A35: C-510 | B35: D-125 (ООО «МегаТранс») | C35: Иван Попов | D35: 450,000 ₽ | E35: Режим автоответчика, не выявлен ЛПР | G35: Менеджер 5 минут зачитывал прайс-лист секретарю, не спросив, кто принимает решение по закупкам | N35: Разбор на летучке: регламент квалификации BANT. Назначить повторный звонок с прямым выходом на генерального директора.
A37: 📋 ЭТАЛОННЫЙ СТАНДАРТ 13 КРИТЕРИЕВ ОЦЕНКИ B2B-ДИАЛОГОВ (WHISPER LARGE V3 + LLM SUPERVISOR)
A38: № | B38: Параметр оценки диалога | C38: Вес | D38: Приоритет | E38: Что проверяет алгоритм ИИ (Суть критерия) | H38: Маркеры дефекта в речи (Почему сделка срывается) | M38: Coaching Tip: как обучить менеджера и защитить выручку
A39: 1 | B39: Жёсткий Next Step | C39: 2.0x | D39: 🔴 P0 (Критический) | E39: Зафиксирована точная дата и время следующего контакта (календарный слот) | H39: «Я вам наберу на днях», «Подумайте, позвоните», отпускание без дедлайна | M39: Внедрить обязательный вопрос: «Во вторник в 14:30 или в среду в 11:00 удобно?»
A40: 2 | B40: Инициатива диалога | C40: 1.0x | D40: 🟡 P1 (Высокий) | E40: Менеджер ведёт диалог вопросами, держит сценарий, а не работает автоответчиком | H40: Клиент задает все вопросы сам, менеджер только пассивно отвечает | M40: Правило «Ответ + Встречный вопрос». Завершать каждую реплику вопросом.
A41: 3 | B41: Квалификация ЛПР / ЛВПР | C41: 1.5x | D41: 🔴 P0 (Критический) | E41: Установлен статус собеседника: принимает ли решения по бюджету и согласованию | H41: Трата 40 минут на презентацию секретарю или инженеру без полномочий | M41: «Кто кроме вас участвует в утверждении финансового бюджета проекта?»
A42: 4 | B42: Выявление болей и срочности | C42: 1.2x | D42: 🟡 P1 (Высокий) | E42: Понятна ли бизнес-задача клиента, текущие потери и дедлайн решения проблемы | H42: Менеджер презентует продукт 'в лоб', не узнав реальную боль клиента | M42: Сначала диагностика по методологии SPIN/BANT, затем презентация под боль.
A43: 5 | B43: Отработка возражения «Дорого» | C43: 1.5x | D43: 🔴 P0 (Критический) | E43: Обоснование ценности, расчет ROI/окупаемости, рассрочка (без моментальной скидки) | H43: Моментальная скидка при первом сомнении или согласие («Да, у нас недешево») | M43: Показать окупаемость: сколько клиент теряет каждый день без решения.
A44: 6 | B44: Отработка «Я подумаю» | C44: 1.0x | D44: 🟡 P1 (Высокий) | E44: Вскрытие истинного сомнения клиента, а не молчаливое отпускание в архив | H44: «Хорошо, думайте, ждем звонка», закрытие звонка на неопределенности | M44: «Алексей, обычно говорят 'подумаю', если смущает цена или функционал. Что именно?»
A45: 7 | B45: Презентация через кейсы и цифры | C45: 1.0x | D45: 🟡 P1 (Высокий) | E45: Приведение аналогичных проектов, оцифрованных результатов и сроков возврата | H45: Абстрактные фразы «мы надежные», «у нас качество» без реальных фактов | M45: Привести кейс: «Для компании X мы сократили цикл сделки на 14 дней».
A46: 8 | B46: Попытка закрытия сделки | C46: 1.5x | D46: 🔴 P0 (Критический) | E46: Прямое предложение заключить договор, забронировать слот аудита или оплатить счет | H46: Разговор прошел тепло, но менеджер не предложил сделать шаг к оплате | M46: «Если все параметры подходят, предлагаю запустить пилот. Куда направить договор?»
A47: 9 | B47: Регламент приветствия и повестка | C47: 0.8x | D47: 🟢 P2 (Стандарт) | E47: Представление имени, компании, уточнение времени и согласование цели звонка | H47: Невнятное приветствие, вопрос «Удобно говорить?» без обозначения повестки | M47: «Добрый день! Дмитрий, RevOps. Звоню по аудиту воронки. Уделите 5 минут?»
A48: 10 | B48: Чистота речи и уверенность | C48: 0.8x | D48: 🟢 P2 (Стандарт) | E48: Отсутствие слов-паразитов, пауз и извиняющихся интонаций при чеке | H48: Дрожащий голос при озвучивании цены, слова неуверенности («наверное», «может») | M48: Отработать блок цены на тренажере: уверенная пауза после суммы.
A49: 11 | B49: Слушание клиента (Talk/Listen) | C49: 1.2x | D49: 🟡 P1 (Высокий) | E49: Менеджер слушает клиента не менее 45–50% общего времени разговора | H49: Монолог менеджера > 70% времени: клиент молчит и теряет внимание | M49: Держать баланс 50/50. Задавать открытые вопросы и слушать клиента.
... A51: 13 | B51: Защита маржинальности | C51: 1.5x | D51: 🔴 P0 (Критический) | E51: Отсутствие необоснованных скидок без встречных уступок по объему или предоплате | H51: Раздача скидок из маржи без требования 100% оплаты или большего объема | M51: Скидка только в обмен: «Готовы дать 5% при оплате счета в течение 24 часов».
A53: 💰 ЭКОНОМИЧЕСКИЙ ЭФФЕКТ РЕЧЕВОЙ АНАЛИТИКИ (ROI ВНЕДРЕНИЯ И ОКУПАЕМОСТЬ)
A54: Параметр эффекта речевой аналитики | D54: Значение | F54: Комментарий и логика окупаемости
A55: Текущие потери от брака звонков в месяц (As-Is) | D55: 1,382,500 ₽ | F55: Сливы на этапе первичного звонка из-за отсутствия Next Step и слабой отработки возражений
A56: Ожидаемый возврат выручки в кассу (M1 To-Be) | D56: 414,750 ₽ | F56: Консервативный сценарий: устранение всего 30% выявленных дефектов речи
A57: Стоимость модуля речевого ИИ-супервайзера | D57: 150,000 ₽ | F57: В составе комплексного 4-недельного спринта оптимизации отдела продаж
A58: Чистая прибыль компании от внедрения в первый месяц | D58: 264,750 ₽ | F58: Чистый денежный плюс в кассе компании уже в первый месяц работы
A59: Чистый ROI речевой аналитики | D59: 276% | F59: Отдача на каждый вложенный рубль в первый месяц
A60: Срок полной окупаемости модуля | D60: 11 дней | F60: Количество рабочих дней до полной окупаемости внедрения речевого ИИ

Sheet 💸 Диагностика_Утечек_ОП
A1: 💸 ДИАГНОСТИЧЕСКИЙ АУДИТ УПУЩЕННОЙ ПРИБЫЛИ И УЗКИХ МЕСТ ОТДЕЛА ПРОДАЖ
A2: =HYPERLINK("https://docs.google.com/spreadsheets/d/1QnjrrbpqhYssofchee7G06szWrFvBCcOqGIVokjqdVc/edit#gid=1377308911", "📄 1. One-Pager") -> 📄 1. One-Pager | B2: =HYPERLINK("https://docs.google.com/spreadsheets/d/1QnjrrbpqhYssofchee7G06szWrFvBCcOqGIVokjqdVc/edit#gid=1847360667", "⚡ 2. Пульс компании") -> ⚡ 2. Пульс компании | C2: =HYPERLINK("https://docs.google.com/spreadsheets/d/1QnjrrbpqhYssofchee7G06szWrFvBCcOqGIVokjqdVc/edit#gid=777000301", "📋 3. Пульт РОПа") -> 📋 3. Пульт РОПа | D2: =HYPERLINK("https://docs.google.com/spreadsheets/d/1QnjrrbpqhYssofchee7G06szWrFvBCcOqGIVokjqdVc/edit#gid=777000101", "💸 4. 7 Грехов ОП") -> 💸 4. 7 Грехов ОП | E2: =HYPERLINK("https://docs.google.com/spreadsheets/d/1QnjrrbpqhYssofchee7G06szWrFvBCcOqGIVokjqdVc/edit#gid=811060921", "🎯 5. Action Center") -> 🎯 5. Action Center | F2: =HYPERLINK("https://docs.google.com/spreadsheets/d/1QnjrrbpqhYssofchee7G06szWrFvBCcOqGIVokjqdVc/edit#gid=852624872", "🎙️ 6. ИИ-Аудит") -> 🎙️ 6. ИИ-Аудит | G2: =HYPERLINK("https://docs.google.com/spreadsheets/d/1QnjrrbpqhYssofchee7G06szWrFvBCcOqGIVokjqdVc/edit#gid=777000201", "⚡ 7. Экспресс 3 цифры") -> ⚡ 7. Экспресс 3 цифры | H2: =HYPERLINK("https://docs.google.com/spreadsheets/d/1QnjrrbpqhYssofchee7G06szWrFvBCcOqGIVokjqdVc/edit#gid=60692888", "🧪 8. QA Suite") -> 🧪 8. QA Suite | I2: =HYPERLINK("https://docs.google.com/spreadsheets/d/1QnjrrbpqhYssofchee7G06szWrFvBCcOqGIVokjqdVc/edit#gid=985355776", "⚙️ 9. Настройки") -> ⚙️ 9. Настройки
A4: Фактическая выручка месяца | B4: Взвешенный пайплайн в работе | C4: Выявленная упущенная прибыль | D4: Потенциал выручки (To-Be) | E4: Ожидаемый чистый ROI | F4: Срок окупаемости проекта
A5: =calc_engine!B19 -> 1650000 | B5: =calc_engine!B18 -> 2754000 | C5: =E16 -> 7001000 | D5: =A5 + E16 -> 8651000 | E5: =B23 -> 367% | F5: =B24 -> 6 дн.
A7: 🔴 7 СМЕРТНЫХ ГРЕХОВ ОТДЕЛА ПРОДАЖ (АНАТОМИЯ СБОЕВ И ИХ УСТРАНЕНИЕ)
A8: № | B8: Смертный грех ОП (Системный сбой) | C8: Симптом и диагностика в компании | D8: Объем базы в риске | E8: Упущенная выгода / Риск, ₽ | F8: Приоритет | G8: Как закрывает наша платформа | H8: Ожидаемый эффект
A9: 1 | B9: «Черный ящик» CRM: иллюзорный пайплайн | C9: В CRM висит 5.3 млн ₽, но реальный взвешенный объем всего 2.6 млн ₽. Фаундер живет в иллюзии плана | D9: =calc_engine!B17 -> 5530000 | E9: =calc_engine!B17 - calc_engine!B18 -> 2776000 | F9: 🔴 P0 (Критический) | G9: Взвешенный прогноз воронки (SSOT) + исключение зомби-сделок | H9: 100% точность прогноза Run-Rate без иллюзий
A10: 2 | B10: «Кладбище сделок»: срыв регламентов SLA | C10: Сделки маринуются на этапе КП по 12–14 дней (норма 48ч). Вероятность закрытия падает на 45% | D10: =calc_engine!C5 -> 3850000 | E10: =ROUND(D10 * 0.45, 0) -> 1732500 | F10: 🔴 P0 (Критический) | G10: Авторадар зависания сделок + эскалация РОПу на 3-й день | H10: ="+45% к конверсии этапа КП в оплату" -> +45% к конверсии этапа КП в оплату
A11: 3 | B11: РОП — «играющий тренер» и узкое горлышко | C11: РОП ведет 80% сделок и перегружен (нагрузка 80%), а КАМы простаивают с 4% загрузки. Сделки тухнут без внимания | D11: =SUMIFS(raw_deals!$C$2:$C1000, raw_deals!$H$2:$H1000, 101, raw_deals!$D$2:$D1000, "<=5") -> 850000 | E11: =ROUND(D11 * 0.3, 0) -> 255000 | F11: 🔴 P0 (Критический) | G11: Матрица емкости (Capacity Planning) + автоперелив сделок на КАМов | H11: Разгрузка РОПа на 60% для управления и коучинга
A12: 4 | B12: Менеджеры-автоответчики и слив звонков | C12: В 33% звонков не зафиксирован Next Step. Средний балл речи < 9/13. Лиды уходят в «подумаю» | D12: =calc_engine!B17 -> 5530000 | E12: =ROUND(D12 * 0.25, 0) -> 1382500 | F12: 🔴 P0 (Критический) | G12: 13-факторная речевая аналитика + чек-листы BANT + мотивация от речи | H12: ="+30% к конверсии из первого звонка во встречу" -> +30% к конверсии из первого звонка во встречу
A13: 5 | B13: «Кладбище отказников» без реактивации | C13: 1 млн ₽ списан в отказ (L1 «дорого», L2 «подумаю»). База брошена в архиве без повторного прогрева | D13: =SUM(calc_engine!D52:D55) -> 1000000 | E13: =calc_engine!D56 -> 440000 | F13: 🟡 P1 (Высокий) | G13: Agentic AI Recovery Engine: сегментация отказников + офферы даунсейла | H13: Возврат до 20–30% списанной выручки из архива
A14: 6 | B14: Зависшая дебиторка и кассовые разрывы | C14: Счета выставлены, но не оплачены (DSO > 25 дней). 330к просрочки грозит кассовым разрывом | D14: =calc_engine!B146 -> 330000 | E14: =D14 -> 330000 | F14: 🟡 P1 (Высокий) | G14: Платежный календарь DSO + триггерные AI-уведомления бухгалтерии клиента | H14: Сокращение срока дебиторки DSO с 27 до 7 дней
A15: 7 | B15: Слив маркетинга и война с отделом продаж | C15: Google Ads слил 85 000 ₽ с ROMI -100% (0 оплат). Деньги сожжены без сквозного контроля окупаемости | D15: =SUMIF(raw_marketing!$B$2:$B1000, "Google Ads", raw_marketing!$E$2:$E1000) -> 85000 | E15: =D15 -> 85000 | F15: 🟡 P1 (Высокий) | G15: Сквозная RevOps-атрибуция W-Shaped: автоотключение убыточных связок | H15: Экономия рекламного бюджета + перелив в прибыльный Контур/Директ
B16: ИТОГО ВЫЯВЛЕННЫХ ПОТЕРЬ И РИСКОВ В МЕСЯЦ: | D16: =SUM(D9:D15) -> 17175000 | E16: =SUM(E9:E15) -> 7001000 | F16: ИТОГО ПОТЕРЬ | G16: Потенциал возврата в кассу | H16: Окупаемость за счет устранения узких мест
A18: 🚀 ЭКОНОМИКА ПРОЕКТА ОПТИМИЗАЦИИ И СРОК ОКУПАЕМОСТИ ДЛЯ КЛИЕНТА
A19: Параметр экономики проекта | B19: Значение | C19: Комментарий и логика расчета
A20: Стоимость проекта оптимизации ОП | B20: 450000 | C20: Фиксированная стоимость внедрения (4 недели спринтов)
A21: Ожидаемый возврат выручки (M1 факт) | B21: =ROUND(E16 * 0.3, 0) -> 2100300 | C21: Консервативный ориентир: устранение всего 30% найденных узких мест
A22: Чистая прибыль собственника за вычетом услуг | B22: =B21 - B20 -> 1650300 | C22: Чистый денежный плюс в кассе компании в первый же месяц
A23: Чистый ROI инвестиций в проект | B23: =ROUND((B21 - B20) / B20 * 100, 0) & "%" -> 367% | C23: Процент отдачи на каждый вложенный рубль
A24: Срок полной окупаемости проекта | B24: =ROUND(B20 / (B21 / 30), 0) & " дн." -> 6 дн. | C24: Количество дней работы ОП до полной окупаемости чека внедрения
A26: 👉 УТВЕРДИТЬ ПРОЕКТ ОПТИМИЗАЦИИ И СФОРМИРОВАТЬ ИНВОЙС (450 000 ₽)
A27: =HYPERLINK("#'⚡ Экспресс_Калькулятор_3_Цифры'!A1", "Не готовы к спринту? 👉 Бесплатный тест-драйв на 3 звонках в Экспресс-Калькуляторе") -> Не готовы к спринту? 👉 Бесплатный тест-драйв на 3 звонках в Экспресс-Калькуляторе
A28: 🔒 Безопасный B2B-расчет: безналичный платеж по счету (УПД / Диадок) • 152-ФЗ РФ • Старт спринта за 24 часа

Sheet 📄 Executive_OnePager
A1: 📄 REVOPS ENTERPRISE EXECUTIVE ONE-PAGER (УПРАВЛЕНЧЕСКИЙ ДАЙДЖЕСТ РУКОВОДСТВА)
A2: =HYPERLINK("https://docs.google.com/spreadsheets/d/1QnjrrbpqhYssofchee7G06szWrFvBCcOqGIVokjqdVc/edit#gid=1377308911", "📄 1. One-Pager") -> 📄 1. One-Pager | B2: =HYPERLINK("https://docs.google.com/spreadsheets/d/1QnjrrbpqhYssofchee7G06szWrFvBCcOqGIVokjqdVc/edit#gid=1847360667", "⚡ 2. Пульс компании") -> ⚡ 2. Пульс компании | C2: =HYPERLINK("https://docs.google.com/spreadsheets/d/1QnjrrbpqhYssofchee7G06szWrFvBCcOqGIVokjqdVc/edit#gid=777000301", "📋 3. Пульт РОПа") -> 📋 3. Пульт РОПа | D2: =HYPERLINK("https://docs.google.com/spreadsheets/d/1QnjrrbpqhYssofchee7G06szWrFvBCcOqGIVokjqdVc/edit#gid=777000101", "💸 4. 7 Грехов ОП") -> 💸 4. 7 Грехов ОП | E2: =HYPERLINK("https://docs.google.com/spreadsheets/d/1QnjrrbpqhYssofchee7G06szWrFvBCcOqGIVokjqdVc/edit#gid=811060921", "🎯 5. Action Center") -> 🎯 5. Action Center | F2: =HYPERLINK("https://docs.google.com/spreadsheets/d/1QnjrrbpqhYssofchee7G06szWrFvBCcOqGIVokjqdVc/edit#gid=852624872", "🎙️ 6. ИИ-Аудит") -> 🎙️ 6. ИИ-Аудит | G2: =HYPERLINK("https://docs.google.com/spreadsheets/d/1QnjrrbpqhYssofchee7G06szWrFvBCcOqGIVokjqdVc/edit#gid=777000201", "⚡ 7. Экспресс 3 цифры") -> ⚡ 7. Экспресс 3 цифры | H2: =HYPERLINK("https://docs.google.com/spreadsheets/d/1QnjrrbpqhYssofchee7G06szWrFvBCcOqGIVokjqdVc/edit#gid=60692888", "🧪 8. QA Suite") -> 🧪 8. QA Suite | I2: =HYPERLINK("https://docs.google.com/spreadsheets/d/1QnjrrbpqhYssofchee7G06szWrFvBCcOqGIVokjqdVc/edit#gid=985355776", "⚙️ 9. Настройки") -> ⚙️ 9. Настройки
A4: Выручка (Факт Closed-Won) | B4: % Выполнения плана | C4: Взвешенный прогноз (SSOT) | D4: Run-Rate касса (Прогноз) | E4: Активный пайплайн в работе | F4: Сделок под угрозой SLA | G4: Качество речи ОП (ИИ) | H4: Data Quality Index
A5: =calc_engine!B19 -> 1650000 | B5: =calc_engine!B20 -> 0.33 | C5: =calc_engine!B18 -> 2754000 | D5: =calc_engine!B29 -> 1706896.6 | E5: =calc_engine!B17 -> 5530000 | F5: =COUNTIF('🎯 Action_Center'!$E$2:$E$50, "*P0*") -> 4 | G5: =AVERAGE(raw_calls!$T$2:$T$1000)/13 -> 0.73076923 | H5: ='📊 Data_Quality'!$C$8 -> 1
A7: 📊 ВОРОНКА ПРОДАЖ & УЗКИЕ ГОРЛЫШКИ (AS-IS) | F7: 🚨 ТОП-5 КРИТИЧЕСКИХ РИСКОВ ВЫРУЧКИ (ACTION CENTER)
A8: Этап сделки | B8: Сделок | C8: Объем, ₽ | D8: SLA норматив (ч) | F8: Сделка / Клиент | G8: Проблема & Симптом | H8: Сумма в риске, ₽ | I8: Срочное действие РОПа
A9: 1. Новый лид | B9: ='⚡ Пульс_Компании'!B10 -> 1 | C9: ='⚡ Пульс_Компании'!C10 -> 950000 | D9: 24 | F9: D-104 | G9: ='🎯 Action_Center'!B2 -> КП без ответа > 48ч | H9: ='🎯 Action_Center'!D2 -> 850000 | I9: ='🎯 Action_Center'!F2 -> Повторный контакт с ЛПР + звонок РОПа
A10: 2. Квалификация / ЛПР | B10: ='⚡ Пульс_Компании'!B11 -> 1 | C10: ='⚡ Пульс_Компании'!C11 -> 120000 | D10: 48 | F10: D-103 | G10: ='🎯 Action_Center'!B3 -> Просрочен счёт | H10: ='🎯 Action_Center'!D3 -> 150000 | I10: ='🎯 Action_Center'!F3 -> Дожим счета через AI-бота + автозвонок РОПа
A11: 3. Встреча / Демо | B11: ='⚡ Пульс_Компании'!B12 -> 1 | C11: ='⚡ Пульс_Компании'!C12 -> 280000 | D11: 120 | F11: D-109 | G11: ='🎯 Action_Center'!B4 -> Критический брак речи | H11: ='🎯 Action_Center'!D4 -> 120000 | I11: ='🎯 Action_Center'!F4 -> Прослушать звонок C-504, отработать возражения
A12: 4. КП и согласование | B12: ='⚡ Пульс_Компании'!B13 -> 2 | C12: ='⚡ Пульс_Компании'!C13 -> 3850000 | D12: 48 | F12: D-106 | G12: ='🎯 Action_Center'!B5 -> Зависание на этапе счета | H12: ='🎯 Action_Center'!D5 -> 180000 | I12: ='🎯 Action_Center'!F5 -> Эскалация РОПу, согласование спец-условий
A13: 5. Счет выставлен | B13: ='⚡ Пульс_Компании'!B14 -> 2 | C13: ='⚡ Пульс_Компании'!C14 -> 330000 | D13: 72 | F13: D-107 | G13: ='🎯 Action_Center'!B6 -> Крупная сделка без движения | H13: ='🎯 Action_Center'!D6 -> 3000000 | I13: ='🎯 Action_Center'!F6 -> Подключение генерального директора к переговорам
A14: 6. Успешно реализовано | B14: ='⚡ Пульс_Компании'!B15 -> 2 | C14: ='⚡ Пульс_Компании'!C15 -> 1650000 | D14: 0
A16: 🎯 ГЛАВНЫЙ ФОКУС РУКОВОДСТВА ДО КОНЦА МЕСЯЦА: Перехват сделки D-104 (850 000 ₽) и перераспределение 3 лидов с перегруженного РОПа на КАМов.

Sheet ⚙️ Настройки
A1: ⚙️ СИСТЕМНЫЕ КОНФИГУРАЦИИ И РЕЕСТР ДОПУЩЕНИЙ REVOPS OS PRO V17.6 (GOLDEN MASTER)
A2: =HYPERLINK("https://docs.google.com/spreadsheets/d/1QnjrrbpqhYssofchee7G06szWrFvBCcOqGIVokjqdVc/edit#gid=1377308911", "📄 1. One-Pager") -> 📄 1. One-Pager | B2: =HYPERLINK("https://docs.google.com/spreadsheets/d/1QnjrrbpqhYssofchee7G06szWrFvBCcOqGIVokjqdVc/edit#gid=1847360667", "⚡ 2. Пульс компании") -> ⚡ 2. Пульс компании | C2: =HYPERLINK("https://docs.google.com/spreadsheets/d/1QnjrrbpqhYssofchee7G06szWrFvBCcOqGIVokjqdVc/edit#gid=777000301", "📋 3. Пульт РОПа") -> 📋 3. Пульт РОПа | D2: =HYPERLINK("https://docs.google.com/spreadsheets/d/1QnjrrbpqhYssofchee7G06szWrFvBCcOqGIVokjqdVc/edit#gid=777000101", "💸 4. 7 Грехов ОП") -> 💸 4. 7 Грехов ОП | E2: =HYPERLINK("https://docs.google.com/spreadsheets/d/1QnjrrbpqhYssofchee7G06szWrFvBCcOqGIVokjqdVc/edit#gid=811060921", "🎯 5. Action Center") -> 🎯 5. Action Center | F2: =HYPERLINK("https://docs.google.com/spreadsheets/d/1QnjrrbpqhYssofchee7G06szWrFvBCcOqGIVokjqdVc/edit#gid=852624872", "🎙️ 6. ИИ-Аудит") -> 🎙️ 6. ИИ-Аудит | G2: =HYPERLINK("https://docs.google.com/spreadsheets/d/1QnjrrbpqhYssofchee7G06szWrFvBCcOqGIVokjqdVc/edit#gid=777000201", "⚡ 7. Экспресс 3 цифры") -> ⚡ 7. Экспресс 3 цифры | H2: =HYPERLINK("https://docs.google.com/spreadsheets/d/1QnjrrbpqhYssofchee7G06szWrFvBCcOqGIVokjqdVc/edit#gid=60692888", "🧪 8. QA Suite") -> 🧪 8. QA Suite | I2: =HYPERLINK("https://docs.google.com/spreadsheets/d/1QnjrrbpqhYssofchee7G06szWrFvBCcOqGIVokjqdVc/edit#gid=985355776", "⚙️ 9. Настройки") -> ⚙️ 9. Настройки
A3: Организация | B3: RevOps Enterprise | D3: 🔑 TENANT UUID: | E3: TENANT-MASTER-001 | F3: (Мастер-шаблон)
A4: Валюта системы | B4: RUB (₽) | D4: 🏢 ТЕНАНТ / КОМПАНИЯ: | E4: Golden Master Template | F4: (Пространство вендора)
A5: Версия архитектуры | B5: RevOps Enterprise OS V17.6 Production Suite | C5: ⚡ БЫСТРЫЙ ВЫБОР ПЕРИОДА | D5: 🔒 СТАТУС RBAC: | E5: 🛡️ Hardware Enforcement (Protected Sheets) | F5: (Защищено через API)
A6: Период: начало | B6: 01.10.2026 | C6: Текущий месяц
A7: Период: конец | B7: 31.10.2026 | C7: (автозаполнение B6 и B7)
A8: Дата старта проекта | B8: 01.10.2026 | J8: 👥 ПЕРСОНАЛЬНЫЙ МАППИНГ РОЛЕЙ ПО EMAIL (MULTI-USER RBAC)
A9: План выручки на месяц | B9: 5000000 | C9: Enterprise Multi-Tenant V17.6 | D9: 🏢 Холдинг (Все филиалы) | E9: Статус контура: | F9: 🟢 152-ФЗ РФ Compliant (Аттестован) | G9: СЕССИЯ ПЛАНИРОВАНИЯ: | H9: 🟢 Готова к работе (Свободна) | J9: Корпоративный Email | K9: Назначенная роль | L9: Целевой Landing-дашборд
A10: 👤 РОЛЬ В СИСТЕМЕ: | B10: 👑 CEO | C10: 🎯 ВЫБОР ФОКУСА ДАННЫХ: | D10: Авто (По умолчанию роли) | E10: 👥 ФИЛЬТР СОТРУДНИКА: | F10: 👥 Весь отдел продаж (Сводно) | G10: РЕЖИМ ЭКСПЛУАТАЦИИ: | H10: 👥 Multi-User (Персональные фильтры) | J10: ceo@company.com | K10: 👑 CEO | L10: 📄 Executive_OnePager
A11: Stage ID | B11: Название этапа воронки | C11: SLA норматив (ч) | D11: Вероятность (Win %) | J11: rop@company.com | K11: 📋 РОП | L11: 📋 Пульт_РОПа_15_Минут
A12: 1 | B12: 1. Новый лид | C12: 24 | D12: 0.05 | J12: kam@company.com | K12: 💼 KAM | L12: ⚡ Пульс_Компании
A13: 2 | B13: 2. Квалификация / ЛПР | C13: 48 | D13: 0.15 | J13: sdr@company.com | K13: 📞 SDR | L13: ⚡ Пульс_Компании
A14: 3 | B14: 3. Встреча / Демо | C14: 120 | D14: 0.35 | J14: cmo@company.com | K14: 🌐 CMO | L14: 🌐 Маркетинг_и_Трафик
A15: 4 | B15: 4. КП и согласование | C15: 48 | D15: 0.6 | J15: cfo@company.com | K15: 💳 CFO | L15: 💳 Финансы_и_AI_Дожим
A16: 5 | B16: 5. Счет выставлен | C16: 72 | D16: 0.85 | J16: admin@company.com | K16: 🔧 Admin | L16: ⚙️ Настройки
A17: 6 | B17: 6. Успешно реализовано | C17: 0 | D17: 1
A18: 7 | B18: 7. Закрыто и не реализовано | C18: 0 | D18: 0
A20: ID | B20: Сотрудник | C20: Роль | D20: Лимит открытых сделок | E20: Статус емкости
A21: 101 | B21: Иванов Дмитрий (РОП) | C21: ROP | D21: 5 | E21: Жесткий лимит
A22: 102 | B22: Петров Александр (КАМ) | C22: KAM | D22: 25 | E22: Норма
A23: 103 | B23: Сидоров Роман (SDR) | C23: SDR | D23: 40 | E23: Норма
A24: 104 | B24: Козлов Алексей (SDR-2) | C24: SDR | D24: 40 | E24: Норма
A25: Код срыва | B25: Причина отказа | C25: Вероятность реактивации
A26: L1 | B26: Дорого / нет бюджета | C26: 0.5
A27: L2 | B27: Выбрали конкурента | C27: 0.35
A28: L3 | B28: Не формат / нет потребности | C28: 0.1
A29: L4 | B29: Потеря контакта / недозвон | C29: 0.2
A31: 📦 МОДУЛЬНЫЙ КОНСТРУКТОР ТАРИФОВ И РАСШИРЕНИЙ (FEATURE FLAGS)
A32: Код модуля | B32: Название модуля платформы RevOps | C32: Статус модуля | D32: Уровень тарифа | E32: Плата, ₽/мес
A33: MOD-01 | B33: 🎙️ Речевой ИИ-Супервайзер 100% звонков (Whisper + DeepSeek) | C33: ВКЛЮЧЕН | D33: Light | E33: 29,000 ₽
A34: MOD-02 | B34: ⚡ Мгновенные алерты в Telegram (30с со сценарием спасения) | C34: ВКЛЮЧЕН | D34: Pro | E34: 15,000 ₽
A35: MOD-03 | B35: 🤖 Автозаполнение CRM (Executive Summary + договоренности) | C35: ВКЛЮЧЕН | D35: Pro | E35: 19,000 ₽
A36: MOD-04 | B36: 🛡️ Пакет «Антисаботаж» и Режим «Адвокат менеджера» | C36: ВКЛЮЧЕН | D36: Pro | E36: 15,000 ₽
A37: MOD-05 | B37: 🎯 Контроль 13 B2B-стандартов речи и жесткого Next Step | C37: ВКЛЮЧЕН | D37: Pro | E37: 25,000 ₽
A38: MOD-06 | B38: 📊 Пульт РОПа 15 минут: утренний радар сливов и лидерборд | C38: ВКЛЮЧЕН | D38: Pro | E38: 35,000 ₽
A39: MOD-07 | B39: 🔐 Контур безопасности 152-ФЗ и токенизация биометрии | C39: ВКЛЮЧЕН | D39: Enterprise | E39: 25,000 ₽
A40: MOD-08 | B40: 📄 Executive OnePager генератор для Собственника и CFO | C40: ВКЛЮЧЕН | D40: Enterprise | E40: 20,000 ₽
A41: ⚡ БЕНЧМАРКИ И НОРМАТИВЫ ПОТЕРЬ (ФИНАНСОВЫЙ КАЛЬКУЛЯТОР) | D41: СУММАРНЫЙ MRR: | E41: 183,000 ₽
A42: Параметр бенчмарка | B42: Значение | C42: Комментарий
A43: Потери на браке речи (% от выручки) | B43: 0.28 | C43: 28% потенциальной выручки теряется из-за ошибок менеджеров на звонках
A44: Потери на зависание КП (% от выручки) | B44: 0.18 | C44: 18% выручки теряется при отправке КП на «кладбище почты» без Next Step
A45: Потери спящих отказников CRM (% от выручки) | B45: 0.12 | C45: 12% — потенциал реактивации списанных отказных сделок
A46: Просрочка оплат и счетов — DSO (% от выручки) | B46: 0.1 | C46: 10% выставленных счетов зависают на согласовании без пуша
A47: Конверсия воронки в оплату (факт) | B47: 0.045 | C47: Текущая конверсия из нового лида в оплаченный счет (4.5%)
A48: Коэффициент возврата потерь (To-Be) | B48: 0.35 | C48: 35% выявленных сливов гарантированно спасается в первый месяц
A51: 🤖 ИНТЕГРАЦИЯ С TELEGRAM BOT API
A52: BOT_TOKEN | B52: placeholder_bot_token_env
A53: ROP_CHAT_ID | B53: -1001234567890
A54: CEO_CHAT_ID | B54: -1009876543210
A55: TEAM_CHAT_ID | B55: -1005554443332
A56: DISPATCHER_SCHEDULE | B56: Каждый час (L1/L2/L3) + 09:15 (Утренний пульс)
A57: DISPATCHER_STATUS | B57: 🟢 ACTIVE (Триггер: каждый час + 09:15)

Sheet raw_touchpoints
A1: touch_id | B1: deal_id | C1: client_id | D1: touch_date | E1: channel | F1: campaign_id | G1: touch_stage | H1: weight_pct | I1: deal_amount | J1: is_won | K1: attributed_won_rev | L1: pipeline_attr_val | M1: synced_at | Z1: data_snapshot_date | AA1: data_version | AB1: uploaded_by | AC1: upload_hash
A2: TP-101 | B2: D-101 | C2: ga_11 | D2: 46259 | E2: Органика SEO | F2: cmp_seo | G2: 1. First Touch | H2: 0.3 | I2: =IFERROR(VLOOKUP(B2, raw_deals!$A$2:$C1000, 3, FALSE), 0) -> 450000 | J2: =IFERROR(VLOOKUP(B2, raw_deals!$A$2:$O1000, 15, FALSE), FALSE) -> TRUE | K2: =IF(J2=TRUE, I2*H2, 0) -> 135000 | L2: =IF(J2=FALSE, I2*H2*IFERROR(VLOOKUP(VLOOKUP(B2, raw_deals!$A$2:$D1000, 4, FALSE), '⚙️ Настройки'!$A$12:$D$18, 4, FALSE), 0), 0) -> 0 | M2: 46294
A3: TP-102 | B3: D-101 | C3: ga_11 | D3: 46267 | E3: Яндекс Директ | F3: cmp_yd | G3: 2. Lead Creation | H3: 0.3 | I3: =IFERROR(VLOOKUP(B3, raw_deals!$A$2:$C1000, 3, FALSE), 0) -> 450000 | J3: =IFERROR(VLOOKUP(B3, raw_deals!$A$2:$O1000, 15, FALSE), FALSE) -> TRUE | K3: =IF(J3=TRUE, I3*H3, 0) -> 135000 | L3: =IF(J3=FALSE, I3*H3*IFERROR(VLOOKUP(VLOOKUP(B3, raw_deals!$A$2:$D1000, 4, FALSE), '⚙️ Настройки'!$A$12:$D$18, 4, FALSE), 0), 0) -> 0 | M3: 46294
A4: TP-103 | B4: D-101 | C4: ga_11 | D4: 46272 | E4: Партнеры | F4: cmp_ref | G4: 3. Middle Nurture | H4: 0.1 | I4: =IFERROR(VLOOKUP(B4, raw_deals!$A$2:$C1000, 3, FALSE), 0) -> 450000 | J4: =IFERROR(VLOOKUP(B4, raw_deals!$A$2:$O1000, 15, FALSE), FALSE) -> TRUE | K4: =IF(J4=TRUE, I4*H4, 0) -> 45000 | L4: =IF(J4=FALSE, I4*H4*IFERROR(VLOOKUP(VLOOKUP(B4, raw_deals!$A$2:$D1000, 4, FALSE), '⚙️ Настройки'!$A$12:$D$18, 4, FALSE), 0), 0) -> 0 | M4: 46294
A5: TP-104 | B5: D-101 | C5: ga_11 | D5: 46277 | E5: Google Ads | F5: cmp_ga | G5: 4. Deal Close | H5: 0.3 | I5: =IFERROR(VLOOKUP(B5, raw_deals!$A$2:$C1000, 3, FALSE), 0) -> 450000 | J5: =IFERROR(VLOOKUP(B5, raw_deals!$A$2:$O1000, 15, FALSE), FALSE) -> TRUE | K5: =IF(J5=TRUE, I5*H5, 0) -> 135000 | L5: =IF(J5=FALSE, I5*H5*IFERROR(VLOOKUP(VLOOKUP(B5, raw_deals!$A$2:$D1000, 4, FALSE), '⚙️ Настройки'!$A$12:$D$18, 4, FALSE), 0), 0) -> 0 | M5: 46294
A6: TP-105 | B6: D-102 | C6: ga_12 | D6: 46262 | E6: Контур.Фокус | F6: cmp_kf | G6: 1. First Touch | H6: 0.3 | I6: =IFERROR(VLOOKUP(B6, raw_deals!$A$2:$C1000, 3, FALSE), 0) -> 1200000 | J6: =IFERROR(VLOOKUP(B6, raw_deals!$A$2:$O1000, 15, FALSE), FALSE) -> TRUE | K6: =IF(J6=TRUE, I6*H6, 0) -> 360000 | L6: =IF(J6=FALSE, I6*H6*IFERROR(VLOOKUP(VLOOKUP(B6, raw_deals!$A$2:$D1000, 4, FALSE), '⚙️ Настройки'!$A$12:$D$18, 4, FALSE), 0), 0) -> 0 | M6: 46294
A7: TP-106 | B7: D-102 | C7: ga_12 | D7: 46269 | E7: Яндекс Директ | F7: cmp_yd | G7: 2. Lead Creation | H7: 0.3 | I7: =IFERROR(VLOOKUP(B7, raw_deals!$A$2:$C1000, 3, FALSE), 0) -> 1200000 | J7: =IFERROR(VLOOKUP(B7, raw_deals!$A$2:$O1000, 15, FALSE), FALSE) -> TRUE | K7: =IF(J7=TRUE, I7*H7, 0) -> 360000 | L7: =IF(J7=FALSE, I7*H7*IFERROR(VLOOKUP(VLOOKUP(B7, raw_deals!$A$2:$D1000, 4, FALSE), '⚙️ Настройки'!$A$12:$D$18, 4, FALSE), 0), 0) -> 0 | M7: 46294
A8: TP-107 | B8: D-102 | C8: ga_12 | D8: 46275 | E8: Контур.Фокус | F8: cmp_kf | G8: 3. Middle Nurture | H8: 0.1 | I8: =IFERROR(VLOOKUP(B8, raw_deals!$A$2:$C1000, 3, FALSE), 0) -> 1200000 | J8: =IFERROR(VLOOKUP(B8, raw_deals!$A$2:$O1000, 15, FALSE), FALSE) -> TRUE | K8: =IF(J8=TRUE, I8*H8, 0) -> 120000 | L8: =IF(J8=FALSE, I8*H8*IFERROR(VLOOKUP(VLOOKUP(B8, raw_deals!$A$2:$D1000, 4, FALSE), '⚙️ Настройки'!$A$12:$D$18, 4, FALSE), 0), 0) -> 0 | M8: 46294
A9: TP-108 | B9: D-102 | C9: ga_12 | D9: 46281 | E9: Контур.Фокус | F9: cmp_kf | G9: 4. Deal Close | H9: 0.3 | I9: =IFERROR(VLOOKUP(B9, raw_deals!$A$2:$C1000, 3, FALSE), 0) -> 1200000 | J9: =IFERROR(VLOOKUP(B9, raw_deals!$A$2:$O1000, 15, FALSE), FALSE) -> TRUE | K9: =IF(J9=TRUE, I9*H9, 0) -> 360000 | L9: =IF(J9=FALSE, I9*H9*IFERROR(VLOOKUP(VLOOKUP(B9, raw_deals!$A$2:$D1000, 4, FALSE), '⚙️ Настройки'!$A$12:$D$18, 4, FALSE), 0), 0) -> 0 | M9: 46294
A10: TP-109 | B10: D-104 | C10: ga_14 | D10: 46277 | E10: Контур.Фокус | F10: cmp_kf | G10: 1. First Touch | H10: 0.3 | I10: =IFERROR(VLOOKUP(B10, raw_deals!$A$2:$C1000, 3, FALSE), 0) -> 850000 | J10: =IFERROR(VLOOKUP(B10, raw_deals!$A$2:$O1000, 15, FALSE), FALSE) -> FALSE | K10: =IF(J10=TRUE, I10*H10, 0) -> 0 | L10: =IF(J10=FALSE, I10*H10*IFERROR(VLOOKUP(VLOOKUP(B10, raw_deals!$A$2:$D1000, 4, FALSE), '⚙️ Настройки'!$A$12:$D$18, 4, FALSE), 0), 0) -> 153000 | M10: 46294
A11: TP-110 | B11: D-104 | C11: ga_14 | D11: 46279 | E11: Яндекс Директ | F11: cmp_yd | G11: 2. Lead Creation | H11: 0.3 | I11: =IFERROR(VLOOKUP(B11, raw_deals!$A$2:$C1000, 3, FALSE), 0) -> 850000 | J11: =IFERROR(VLOOKUP(B11, raw_deals!$A$2:$O1000, 15, FALSE), FALSE) -> FALSE | K11: =IF(J11=TRUE, I11*H11, 0) -> 0 | L11: =IF(J11=FALSE, I11*H11*IFERROR(VLOOKUP(VLOOKUP(B11, raw_deals!$A$2:$D1000, 4, FALSE), '⚙️ Настройки'!$A$12:$D$18, 4, FALSE), 0), 0) -> 153000 | M11: 46294
A12: TP-111 | B12: D-104 | C12: ga_14 | D12: 46283 | E12: Контур.Фокус | F12: cmp_kf | G12: 3. Middle Nurture | H12: 0.1 | I12: =IFERROR(VLOOKUP(B12, raw_deals!$A$2:$C1000, 3, FALSE), 0) -> 850000 | J12: =IFERROR(VLOOKUP(B12, raw_deals!$A$2:$O1000, 15, FALSE), FALSE) -> FALSE | K12: =IF(J12=TRUE, I12*H12, 0) -> 0 | L12: =IF(J12=FALSE, I12*H12*IFERROR(VLOOKUP(VLOOKUP(B12, raw_deals!$A$2:$D1000, 4, FALSE), '⚙️ Настройки'!$A$12:$D$18, 4, FALSE), 0), 0) -> 51000 | M12: 46294
A13: TP-112 | B13: D-105 | C13: ga_15 | D13: 46266 | E13: Партнеры | F13: cmp_ref | G13: 1. First Touch | H13: 0.5 | I13: =IFERROR(VLOOKUP(B13, raw_deals!$A$2:$C1000, 3, FALSE), 0) -> 3000000 | J13: =IFERROR(VLOOKUP(B13, raw_deals!$A$2:$O1000, 15, FALSE), FALSE) -> FALSE | K13: =IF(J13=TRUE, I13*H13, 0) -> 0 | L13: =IF(J13=FALSE, I13*H13*IFERROR(VLOOKUP(VLOOKUP(B13, raw_deals!$A$2:$D1000, 4, FALSE), '⚙️ Настройки'!$A$12:$D$18, 4, FALSE), 0), 0) -> 900000 | M13: 46294
A14: TP-113 | B14: D-105 | C14: ga_15 | D14: 46280 | E14: Яндекс Директ | F14: cmp_yd | G14: 2. Lead Creation | H14: 0.5 | I14: =IFERROR(VLOOKUP(B14, raw_deals!$A$2:$C1000, 3, FALSE), 0) -> 3000000 | J14: =IFERROR(VLOOKUP(B14, raw_deals!$A$2:$O1000, 15, FALSE), FALSE) -> FALSE | K14: =IF(J14=TRUE, I14*H14, 0) -> 0 | L14: =IF(J14=FALSE, I14*H14*IFERROR(VLOOKUP(VLOOKUP(B14, raw_deals!$A$2:$D1000, 4, FALSE), '⚙️ Настройки'!$A$12:$D$18, 4, FALSE), 0), 0) -> 900000 | M14: 46294
A15: TP-111B | B15: D-104 | C15: ga_14 | D15: 46287 | E15: Яндекс Директ | F15: cmp_yd | G15: 4. Deal Close | H15: 0.3 | I15: =IFERROR(VLOOKUP(B15, raw_deals!$A$2:$C1000, 3, FALSE), 0) -> 850000 | J15: =IFERROR(VLOOKUP(B15, raw_deals!$A$2:$O1000, 15, FALSE), FALSE) -> FALSE | K15: =IF(J15=TRUE, I15*H15, 0) -> 0 | L15: =IF(J15=FALSE, I15*H15*IFERROR(VLOOKUP(VLOOKUP(B15, raw_deals!$A$2:$D1000, 4, FALSE), '⚙️ Настройки'!$A$12:$D$18, 4, FALSE), 0), 0) -> 153000 | M15: 46294

Sheet raw_deals
A1: deal_id | B1: client_name | C1: amount | D1: stage_id | E1: stage_name | F1: created_date | G1: stage_changed_date | H1: manager_id | I1: segment_code | J1: lead_source | K1: client_id | L1: scoring_tier | M1: loss_code | N1: synced_at | O1: is_won | P1: is_lost | Q1: days_in_stage | R1: aging_cohort | S1: weighted_val | T1: cycle_days | U1: utm_source | V1: utm_medium | W1: utm_campaign | X1: yclid | Y1: gclid | Z1: data_snapshot_date | AA1: data_version | AB1: uploaded_by | AC1: upload_hash | AD1: next_action_type | AE1: next_action_date | AF1: next_action_owner | AG1: next_action_channel | AH1: next_action_health | AI1: deal_health_score
A2: D-101 | B2: ООО "Альфа Трейд" | C2: 450000 | D2: 6 | E2: 6. Успешно реализовано | F2: 46267 | G2: 46277 | H2: 102 | I2: SEG1 | J2: Яндекс Директ | K2: ga_11 | L2: A | N2: 46285.472 | O2: =IF(A2="","",D2=6) -> TRUE | P2: =IF(A2="","",D2=7) -> FALSE | Q2: =IF(A2="","",IF(D2>=6,0,IF(ISBLANK(G2),0,IF(calc_engine!$B$1>INT(G2),INT(calc_engine!$B$1-G2),0)))) -> 0 | R2: =IF(A2="","",IF(D2>=6,"closed",IF(Q2<=3,"0-3",IF(Q2<=7,"4-7",IF(Q2<=14,"8-14",IF(Q2<=30,"15-30","zombie")))))) -> closed | S2: =IF(A2="","",C2*IFERROR(VLOOKUP(D2,'⚙️ Настройки'!$A$12:$D$18,4,FALSE),0)) -> 450000 | T2: =IF(A2="","",IF(D2>=6,IF(G2>F2,INT(G2-F2),1),IF(calc_engine!$B$1>INT(F2),INT(calc_engine!$B$1-F2),1))) -> 10 | U2: yandex | V2: cpc | W2: retarget_b2b | X2: yclid_101 | Z2: =calc_engine!$B$1 -> 46294 | AH2: =IF(A2="","", IF(AD2="","🔴 NO NEXT ACTION", IF(AE2<calc_engine!$B$1,"🔴 OVERDUE", IF(AE2-calc_engine!$B$1<=1,"🟡 TODAY", IF(AE2-calc_engine!$B$1<=3,"🟢 SOON","🟢 PLANNED"))))) -> 🔴 NO NEXT ACTION | AI2: =IF(A2="","", ROUND( IF(Q2<=1, 30, IF(Q2<=3, 20, IF(Q2<=7, 10, 0))) + IF(AD2<>"", 25, 0) + IF(T2<=14, 20, 10) + IF(I2="SEG1", 15, 10) + IF(C2>=500000, 10, 5), 0)) -> 70
A3: D-102 | B3: АО "Северсталь Ресурс" | C3: 1200000 | D3: 6 | E3: 6. Успешно реализовано | F3: 46269 | G3: 46281 | H3: 101 | I3: SEG1 | J3: Контур.Фокус | K3: ga_12 | L3: A | N3: 46285.472 | O3: =IF(A3="","",D3=6) -> TRUE | P3: =IF(A3="","",D3=7) -> FALSE | Q3: =IF(A3="","",IF(D3>=6,0,IF(ISBLANK(G3),0,IF(calc_engine!$B$1>INT(G3),INT(calc_engine!$B$1-G3),0)))) -> 0 | R3: =IF(A3="","",IF(D3>=6,"closed",IF(Q3<=3,"0-3",IF(Q3<=7,"4-7",IF(Q3<=14,"8-14",IF(Q3<=30,"15-30","zombie")))))) -> closed | S3: =IF(A3="","",C3*IFERROR(VLOOKUP(D3,'⚙️ Настройки'!$A$12:$D$18,4,FALSE),0)) -> 1200000 | T3: =IF(A3="","",IF(D3>=6,IF(G3>F3,INT(G3-F3),1),IF(calc_engine!$B$1>INT(F3),INT(calc_engine!$B$1-F3),1))) -> 12 | U3: kontur | V3: cold | W3: cold_parsing | Z3: =calc_engine!$B$1 -> 46294 | AH3: =IF(A3="","", IF(AD3="","🔴 NO NEXT ACTION", IF(AE3<calc_engine!$B$1,"🔴 OVERDUE", IF(AE3-calc_engine!$B$1<=1,"🟡 TODAY", IF(AE3-calc_engine!$B$1<=3,"🟢 SOON","🟢 PLANNED"))))) -> 🔴 NO NEXT ACTION | AI3: =IF(A3="","", ROUND( IF(Q3<=1, 30, IF(Q3<=3, 20, IF(Q3<=7, 10, 0))) + IF(AD3<>"", 25, 0) + IF(T3<=14, 20, 10) + IF(I3="SEG1", 15, 10) + IF(C3>=500000, 10, 5), 0)) -> 75
A4: D-103 | B4: ИП Смирнов О.В. | C4: 150000 | D4: 5 | E4: 5. Счет выставлен | F4: 46275 | G4: 46285 | H4: 103 | I4: SEG2 | J4: Google Ads | K4: ga_13 | L4: B | N4: 46285.472 | O4: =IF(A4="","",D4=6) -> FALSE | P4: =IF(A4="","",D4=7) -> FALSE | Q4: =IF(A4="","",IF(D4>=6,0,IF(ISBLANK(G4),0,IF(calc_engine!$B$1>INT(G4),INT(calc_engine!$B$1-G4),0)))) -> 9 | R4: =IF(A4="","",IF(D4>=6,"closed",IF(Q4<=3,"0-3",IF(Q4<=7,"4-7",IF(Q4<=14,"8-14",IF(Q4<=30,"15-30","zombie")))))) -> 8-14 | S4: =IF(A4="","",C4*IFERROR(VLOOKUP(D4,'⚙️ Настройки'!$A$12:$D$18,4,FALSE),0)) -> 127500 | T4: =IF(A4="","",IF(D4>=6,IF(G4>F4,INT(G4-F4),1),IF(calc_engine!$B$1>INT(F4),INT(calc_engine!$B$1-F4),1))) -> 19 | U4: google | V4: cpc | W4: search_brand | Y4: gclid_103 | Z4: =calc_engine!$B$1 -> 46294 | AD4: счёт | AE4: 46293 | AF4: 102 | AG4: phone | AH4: =IF(A4="","", IF(AD4="","🔴 NO NEXT ACTION", IF(AE4<calc_engine!$B$1,"🔴 OVERDUE", IF(AE4-calc_engine!$B$1<=1,"🟡 TODAY", IF(AE4-calc_engine!$B$1<=3,"🟢 SOON","🟢 PLANNED"))))) -> 🔴 OVERDUE | AI4: =IF(A4="","", ROUND( IF(Q4<=1, 30, IF(Q4<=3, 20, IF(Q4<=7, 10, 0))) + IF(AD4<>"", 25, 0) + IF(T4<=14, 20, 10) + IF(I4="SEG1", 15, 10) + IF(C4>=500000, 10, 5), 0)) -> 50
A5: D-104 | B5: ООО "Вектор Плюс" | C5: 850000 | D5: 4 | E5: 4. КП и согласование | F5: 46277 | G5: 46282 | H5: 101 | I5: SEG1 | J5: Контур.Фокус | K5: ga_14 | L5: A | N5: 46285.472 | O5: =IF(A5="","",D5=6) -> FALSE | P5: =IF(A5="","",D5=7) -> FALSE | Q5: =IF(A5="","",IF(D5>=6,0,IF(ISBLANK(G5),0,IF(calc_engine!$B$1>INT(G5),INT(calc_engine!$B$1-G5),0)))) -> 12 | R5: =IF(A5="","",IF(D5>=6,"closed",IF(Q5<=3,"0-3",IF(Q5<=7,"4-7",IF(Q5<=14,"8-14",IF(Q5<=30,"15-30","zombie")))))) -> 8-14 | S5: =IF(A5="","",C5*IFERROR(VLOOKUP(D5,'⚙️ Настройки'!$A$12:$D$18,4,FALSE),0)) -> 510000 | T5: =IF(A5="","",IF(D5>=6,IF(G5>F5,INT(G5-F5),1),IF(calc_engine!$B$1>INT(F5),INT(calc_engine!$B$1-F5),1))) -> 17 | U5: kontur | V5: cold | W5: cold_parsing | Z5: =calc_engine!$B$1 -> 46294 | AD5: КП | AE5: 46294 | AF5: 101 | AG5: email | AH5: =IF(A5="","", IF(AD5="","🔴 NO NEXT ACTION", IF(AE5<calc_engine!$B$1,"🔴 OVERDUE", IF(AE5-calc_engine!$B$1<=1,"🟡 TODAY", IF(AE5-calc_engine!$B$1<=3,"🟢 SOON","🟢 PLANNED"))))) -> 🟡 TODAY | AI5: =IF(A5="","", ROUND( IF(Q5<=1, 30, IF(Q5<=3, 20, IF(Q5<=7, 10, 0))) + IF(AD5<>"", 25, 0) + IF(T5<=14, 20, 10) + IF(I5="SEG1", 15, 10) + IF(C5>=500000, 10, 5), 0)) -> 60
A6: D-105 | B6: ООО "Глобал Инвест" | C6: 3000000 | D6: 4 | E6: 4. КП и согласование | F6: 46266 | G6: 46280 | H6: 102 | I6: Петров Александр (КАМ) | J6: Партнеры | K6: ga_15 | L6: A | N6: 46285.472 | O6: =IF(A6="","",D6=6) -> FALSE | P6: =IF(A6="","",D6=7) -> FALSE | Q6: =IF(A6="","",IF(D6>=6,0,IF(ISBLANK(G6),0,IF(calc_engine!$B$1>INT(G6),INT(calc_engine!$B$1-G6),0)))) -> 14 | R6: =IF(A6="","",IF(D6>=6,"closed",IF(Q6<=3,"0-3",IF(Q6<=7,"4-7",IF(Q6<=14,"8-14",IF(Q6<=30,"15-30","zombie")))))) -> 8-14 | S6: =IF(A6="","",C6*IFERROR(VLOOKUP(D6,'⚙️ Настройки'!$A$12:$D$18,4,FALSE),0)) -> 1800000 | T6: =IF(A6="","",IF(D6>=6,IF(G6>F6,INT(G6-F6),1),IF(calc_engine!$B$1>INT(F6),INT(calc_engine!$B$1-F6),1))) -> 28 | U6: partner | V6: referral | W6: ref_network | Z6: =calc_engine!$B$1 -> 46294 | AD6: КП | AE6: 46295 | AF6: 103 | AG6: meeting | AH6: =IF(A6="","", IF(AD6="","🔴 NO NEXT ACTION", IF(AE6<calc_engine!$B$1,"🔴 OVERDUE", IF(AE6-calc_engine!$B$1<=1,"🟡 TODAY", IF(AE6-calc_engine!$B$1<=3,"🟢 SOON","🟢 PLANNED"))))) -> 🟡 TODAY | AI6: =IF(A6="","", ROUND( IF(Q6<=1, 30, IF(Q6<=3, 20, IF(Q6<=7, 10, 0))) + IF(AD6<>"", 25, 0) + IF(T6<=14, 20, 10) + IF(I6="SEG1", 15, 10) + IF(C6>=500000, 10, 5), 0)) -> 55
A7: D-106 | B7: ООО "СнабСервис" | C7: 280000 | D7: 3 | E7: 3. Встреча / Демо | F7: 46279 | G7: 46291 | H7: 102 | I7: SEG2 | J7: Яндекс Директ | K7: ga_16 | L7: B | N7: 46285.472 | O7: =IF(A7="","",D7=6) -> FALSE | P7: =IF(A7="","",D7=7) -> FALSE | Q7: =IF(A7="","",IF(D7>=6,0,IF(ISBLANK(G7),0,IF(calc_engine!$B$1>INT(G7),INT(calc_engine!$B$1-G7),0)))) -> 3 | R7: =IF(A7="","",IF(D7>=6,"closed",IF(Q7<=3,"0-3",IF(Q7<=7,"4-7",IF(Q7<=14,"8-14",IF(Q7<=30,"15-30","zombie")))))) -> 0-3 | S7: =IF(A7="","",C7*IFERROR(VLOOKUP(D7,'⚙️ Настройки'!$A$12:$D$18,4,FALSE),0)) -> 98000 | T7: =IF(A7="","",IF(D7>=6,IF(G7>F7,INT(G7-F7),1),IF(calc_engine!$B$1>INT(F7),INT(calc_engine!$B$1-F7),1))) -> 15 | U7: yandex | V7: cpc | W7: search_rf | X7: yclid_106 | Z7: =calc_engine!$B$1 -> 46294 | AD7: встреча | AE7: 46297 | AF7: 102 | AG7: meeting | AH7: =IF(A7="","", IF(AD7="","🔴 NO NEXT ACTION", IF(AE7<calc_engine!$B$1,"🔴 OVERDUE", IF(AE7-calc_engine!$B$1<=1,"🟡 TODAY", IF(AE7-calc_engine!$B$1<=3,"🟢 SOON","🟢 PLANNED"))))) -> 🟢 SOON | AI7: =IF(A7="","", ROUND( IF(Q7<=1, 30, IF(Q7<=3, 20, IF(Q7<=7, 10, 0))) + IF(AD7<>"", 25, 0) + IF(T7<=14, 20, 10) + IF(I7="SEG1", 15, 10) + IF(C7>=500000, 10, 5), 0)) -> 70
A8: D-107 | B8: ИП Николаев А.С. | C8: 120000 | D8: 2 | E8: 2. Квалификация / ЛПР | F8: 46280 | G8: 46293 | H8: 103 | I8: SEG2 | J8: Органика SEO | K8: ga_17 | L8: C | N8: 46285.472 | O8: =IF(A8="","",D8=6) -> FALSE | P8: =IF(A8="","",D8=7) -> FALSE | Q8: =IF(A8="","",IF(D8>=6,0,IF(ISBLANK(G8),0,IF(calc_engine!$B$1>INT(G8),INT(calc_engine!$B$1-G8),0)))) -> 1 | R8: =IF(A8="","",IF(D8>=6,"closed",IF(Q8<=3,"0-3",IF(Q8<=7,"4-7",IF(Q8<=14,"8-14",IF(Q8<=30,"15-30","zombie")))))) -> 0-3 | S8: =IF(A8="","",C8*IFERROR(VLOOKUP(D8,'⚙️ Настройки'!$A$12:$D$18,4,FALSE),0)) -> 18000 | T8: =IF(A8="","",IF(D8>=6,IF(G8>F8,INT(G8-F8),1),IF(calc_engine!$B$1>INT(F8),INT(calc_engine!$B$1-F8),1))) -> 14 | U8: organic | V8: search | W8: seo_blog | Z8: =calc_engine!$B$1 -> 46294 | AD8: звонок | AE8: 46300 | AF8: 103 | AG8: phone | AH8: =IF(A8="","", IF(AD8="","🔴 NO NEXT ACTION", IF(AE8<calc_engine!$B$1,"🔴 OVERDUE", IF(AE8-calc_engine!$B$1<=1,"🟡 TODAY", IF(AE8-calc_engine!$B$1<=3,"🟢 SOON","🟢 PLANNED"))))) -> 🟢 PLANNED | AI8: =IF(A8="","", ROUND( IF(Q8<=1, 30, IF(Q8<=3, 20, IF(Q8<=7, 10, 0))) + IF(AD8<>"", 25, 0) + IF(T8<=14, 20, 10) + IF(I8="SEG1", 15, 10) + IF(C8>=500000, 10, 5), 0)) -> 90
A9: D-108 | B9: ООО "Ритейл Групп" | C9: 950000 | D9: 1 | E9: 1. Новый лид | F9: 46283 | G9: 46294 | H9: 103 | I9: SEG1 | J9: Контур.Фокус | K9: ga_18 | L9: A | N9: 46285.472 | O9: =IF(A9="","",D9=6) -> FALSE | P9: =IF(A9="","",D9=7) -> FALSE | Q9: =IF(A9="","",IF(D9>=6,0,IF(ISBLANK(G9),0,IF(calc_engine!$B$1>INT(G9),INT(calc_engine!$B$1-G9),0)))) -> 0 | R9: =IF(A9="","",IF(D9>=6,"closed",IF(Q9<=3,"0-3",IF(Q9<=7,"4-7",IF(Q9<=14,"8-14",IF(Q9<=30,"15-30","zombie")))))) -> 0-3 | S9: =IF(A9="","",C9*IFERROR(VLOOKUP(D9,'⚙️ Настройки'!$A$12:$D$18,4,FALSE),0)) -> 47500 | T9: =IF(A9="","",IF(D9>=6,IF(G9>F9,INT(G9-F9),1),IF(calc_engine!$B$1>INT(F9),INT(calc_engine!$B$1-F9),1))) -> 11 | U9: kontur | V9: cold | W9: cold_parsing | Z9: =calc_engine!$B$1 -> 46294 | AD9: звонок | AE9: 46295 | AF9: 103 | AG9: phone | AH9: =IF(A9="","", IF(AD9="","🔴 NO NEXT ACTION", IF(AE9<calc_engine!$B$1,"🔴 OVERDUE", IF(AE9-calc_engine!$B$1<=1,"🟡 TODAY", IF(AE9-calc_engine!$B$1<=3,"🟢 SOON","🟢 PLANNED"))))) -> 🟡 TODAY | AI9: =IF(A9="","", ROUND( IF(Q9<=1, 30, IF(Q9<=3, 20, IF(Q9<=7, 10, 0))) + IF(AD9<>"", 25, 0) + IF(T9<=14, 20, 10) + IF(I9="SEG1", 15, 10) + IF(C9>=500000, 10, 5), 0)) -> 100
A10: D-109 | B10: ООО "ПромКомплект" | C10: 600000 | D10: 7 | E10: 7. Закрыто и не реализовано | F10: 46268 | G10: 46275 | H10: 102 | I10: SEG1 | J10: Яндекс Директ | K10: ga_19 | L10: A | M10: L1 | N10: 46285.472 | O10: =IF(A10="","",D10=6) -> FALSE | P10: =IF(A10="","",D10=7) -> TRUE | Q10: =IF(A10="","",IF(D10>=6,0,IF(ISBLANK(G10),0,IF(calc_engine!$B$1>INT(G10),INT(calc_engine!$B$1-G10),0)))) -> 0 | R10: =IF(A10="","",IF(D10>=6,"closed",IF(Q10<=3,"0-3",IF(Q10<=7,"4-7",IF(Q10<=14,"8-14",IF(Q10<=30,"15-30","zombie")))))) -> closed | S10: =IF(A10="","",C10*IFERROR(VLOOKUP(D10,'⚙️ Настройки'!$A$12:$D$18,4,FALSE),0)) -> 0 | T10: =IF(A10="","",IF(D10>=6,IF(G10>F10,INT(G10-F10),1),IF(calc_engine!$B$1>INT(F10),INT(calc_engine!$B$1-F10),1))) -> 7 | U10: yandex | V10: cpc | W10: retarget_b2b | X10: yclid_109 | Z10: =calc_engine!$B$1 -> 46294 | AH10: =IF(A10="","", IF(AD10="","🔴 NO NEXT ACTION", IF(AE10<calc_engine!$B$1,"🔴 OVERDUE", IF(AE10-calc_engine!$B$1<=1,"🟡 TODAY", IF(AE10-calc_engine!$B$1<=3,"🟢 SOON","🟢 PLANNED"))))) -> 🔴 NO NEXT ACTION | AI10: =IF(A10="","", ROUND( IF(Q10<=1, 30, IF(Q10<=3, 20, IF(Q10<=7, 10, 0))) + IF(AD10<>"", 25, 0) + IF(T10<=14, 20, 10) + IF(I10="SEG1", 15, 10) + IF(C10>=500000, 10, 5), 0)) -> 75
A11: D-110 | B11: ЗАО "ТехноМаш" | C11: 400000 | D11: 7 | E11: 7. Закрыто и не реализовано | F11: 46270 | G11: 46279 | H11: 102 | I11: SEG2 | J11: Google Ads | K11: ga_20 | L11: B | M11: L2 | N11: 46285.472 | O11: =IF(A11="","",D11=6) -> FALSE | P11: =IF(A11="","",D11=7) -> TRUE | Q11: =IF(A11="","",IF(D11>=6,0,IF(ISBLANK(G11),0,IF(calc_engine!$B$1>INT(G11),INT(calc_engine!$B$1-G11),0)))) -> 0 | R11: =IF(A11="","",IF(D11>=6,"closed",IF(Q11<=3,"0-3",IF(Q11<=7,"4-7",IF(Q11<=14,"8-14",IF(Q11<=30,"15-30","zombie")))))) -> closed | S11: =IF(A11="","",C11*IFERROR(VLOOKUP(D11,'⚙️ Настройки'!$A$12:$D$18,4,FALSE),0)) -> 0 | T11: =IF(A11="","",IF(D11>=6,IF(G11>F11,INT(G11-F11),1),IF(calc_engine!$B$1>INT(F11),INT(calc_engine!$B$1-F11),1))) -> 9 | U11: google | V11: cpc | W11: search_brand | Y11: gclid_110 | Z11: =calc_engine!$B$1 -> 46294 | AH11: =IF(A11="","", IF(AD11="","🔴 NO NEXT ACTION", IF(AE11<calc_engine!$B$1,"🔴 OVERDUE", IF(AE11-calc_engine!$B$1<=1,"🟡 TODAY", IF(AE11-calc_engine!$B$1<=3,"🟢 SOON","🟢 PLANNED"))))) -> 🔴 NO NEXT ACTION | AI11: =IF(A11="","", ROUND( IF(Q11<=1, 30, IF(Q11<=3, 20, IF(Q11<=7, 10, 0))) + IF(AD11<>"", 25, 0) + IF(T11<=14, 20, 10) + IF(I11="SEG1", 15, 10) + IF(C11>=500000, 10, 5), 0)) -> 65
A12: D-099 | B12: ООО "ПромСбыт" | C12: 180000 | D12: 5 | E12: 5. Счет выставлен | F12: 46235 | G12: 46244 | H12: 103 | I12: SEG2 | J12: Яндекс Директ | K12: ga_08 | L12: Tier B | N12: 46259 | O12: =IF(A12="","",D12=6) -> FALSE | P12: =IF(A12="","",D12=7) -> FALSE | Q12: =IF(A12="","",IF(D12>=6,0,IF(ISBLANK(G12),0,IF(calc_engine!$B$1>INT(G12),INT(calc_engine!$B$1-G12),0)))) -> 50 | R12: =IF(A12="","",IF(D12>=6,"closed",IF(Q12<=3,"0-3",IF(Q12<=7,"4-7",IF(Q12<=14,"8-14",IF(Q12<=30,"15-30","zombie")))))) -> zombie | S12: =IF(A12="","",C12*IFERROR(VLOOKUP(D12,'⚙️ Настройки'!$A$12:$D$18,4,FALSE),0)) -> 153000 | T12: =IF(A12="","",IF(D12>=6,IF(G12>F12,INT(G12-F12),1),IF(calc_engine!$B$1>INT(F12),INT(calc_engine!$B$1-F12),1))) -> 59 | U12: yandex | V12: cpc | W12: b2b_context | Z12: =calc_engine!$B$1 -> 46294 | AD12: follow-up | AE12: 46292 | AF12: 101 | AG12: whatsapp | AH12: =IF(A12="","", IF(AD12="","🔴 NO NEXT ACTION", IF(AE12<calc_engine!$B$1,"🔴 OVERDUE", IF(AE12-calc_engine!$B$1<=1,"🟡 TODAY", IF(AE12-calc_engine!$B$1<=3,"🟢 SOON","🟢 PLANNED"))))) -> 🔴 OVERDUE | AI12: =IF(A12="","", ROUND( IF(Q12<=1, 30, IF(Q12<=3, 20, IF(Q12<=7, 10, 0))) + IF(AD12<>"", 25, 0) + IF(T12<=14, 20, 10) + IF(I12="SEG1", 15, 10) + IF(C12>=500000, 10, 5), 0)) -> 50
O13: =IF(A13="","",D13=6) | P13: =IF(A13="","",D13=7) | Q13: =IF(A13="","",IF(D13>=6,0,IF(ISBLANK(G13),0,IF(calc_engine!$B$1>INT(G13),INT(calc_engine!$B$1-G13),0)))) | R13: =IF(A13="","",IF(D13>=6,"closed",IF(Q13<=3,"0-3",IF(Q13<=7,"4-7",IF(Q13<=14,"8-14",IF(Q13<=30,"15-30","zombie")))))) | S13: =IF(A13="","",C13*IFERROR(VLOOKUP(D13,'⚙️ Настройки'!$A$12:$D$18,4,FALSE),0)) | T13: =IF(A13="","",IF(D13>=6,IF(G13>F13,INT(G13-F13),1),IF(calc_engine!$B$1>INT(F13),INT(calc_engine!$B$1-F13),1)))

Sheet raw_calls
A1: call_id | B1: deal_id | C1: manager_id | D1: call_date | E1: duration_sec | F1: call_type | G1: cr1 | H1: cr2 | I1: cr3 | J1: cr4 | K1: cr5 | L1: cr6 | M1: cr7 | N1: cr8 | O1: cr9 | P1: cr10 | Q1: cr11 | R1: cr12 | S1: cr13 | T1: total_score | U1: next_step_flag | V1: error_summary | W1: ai_recommendation | X1: synced_at | Z1: data_snapshot_date | AA1: data_version | AB1: uploaded_by | AC1: upload_hash
A2: C-501 | B2: D-101 | C2: 102 | D2: 46275 | E2: 420 | F2: qualification | G2: 1 | H2: 1 | I2: 1 | J2: 1 | K2: 1 | L2: 1 | M2: 1 | N2: 1 | O2: 1 | P2: 1 | Q2: 1 | R2: 1 | S2: 1 | T2: =SUM(G2:S2) -> 13 | U2: =T2>=9 -> TRUE | V2: Без дефектов | W2: Эталонный скрипт | X2: 46285.472
A3: C-502 | B3: D-104 | C3: 101 | D3: 46279 | E3: 310 | F3: negotiation | G3: 1 | H3: 1 | I3: 1 | J3: 1 | K3: 1 | L3: 0 | M3: 1 | N3: 1 | O3: 1 | P3: 1 | Q3: 0 | R3: 1 | S3: 1 | T3: =SUM(G3:S3) -> 11 | U3: =T3>=9 -> TRUE | V3: Слабая отработка цены | W3: Предложить рассрочку | X3: 46285.472
A4: C-503 | B4: D-106 | C4: 102 | D4: 46281 | E4: 180 | F4: meeting_confirm | G4: 1 | H4: 1 | I4: 0 | J4: 0 | K4: 1 | L4: 0 | M4: 1 | N4: 1 | O4: 0 | P4: 0 | Q4: 0 | R4: 1 | S4: 0 | T4: =SUM(G4:S4) -> 6 | U4: =T4>=9 -> FALSE | V4: Нет фиксации даты | W4: Закрывать на конкретный слот | X4: 46285.472
A5: C-504 | B5: D-107 | C5: 103 | D5: 46281 | E5: 540 | F5: qualification | G5: 1 | H5: 1 | I5: 1 | J5: 1 | K5: 1 | L5: 1 | M5: 1 | N5: 0 | O5: 1 | P5: 1 | Q5: 1 | R5: 1 | S5: 1 | T5: =SUM(G5:S5) -> 12 | U5: =T5>=9 -> TRUE | V5: Не выявлен бюджет | W5: Уточнить вилку затрат | X5: 46285.472
A6: C-505 | B6: D-109 | C6: 102 | D6: 46273 | E6: 210 | F6: lost | G6: 1 | H6: 0 | I6: 0 | J6: 0 | K6: 0 | L6: 0 | M6: 0 | N6: 1 | O6: 0 | P6: 0 | Q6: 0 | R6: 0 | S6: 0 | T6: =SUM(G6:S6) -> 2 | U6: =T6>=9 -> FALSE | V6: Срыв контакта | W6: Передать в автодожим WhatsApp | X6: 46285.472
A7: C-506 | B7: D-108 | C7: 103 | D7: 46283 | E7: 290 | F7: cold_inbound | G7: 1 | H7: 1 | I7: 1 | J7: 1 | K7: 1 | L7: 1 | M7: 1 | N7: 1 | O7: 1 | P7: 1 | Q7: 1 | R7: 1 | S7: 1 | T7: =SUM(G7:S7) -> 13 | U7: =T7>=9 -> TRUE | V7: Без дефектов | W7: Быстрый перевод на этап встречи | X7: 46285.472

Sheet 🌐 Мультиканальная_Атрибуция
A1: 🌐 МУЛЬТИКАНАЛЬНАЯ АТРИБУЦИЯ ВЫРУЧКИ: W-SHAPED REVENUE ENGINE (V17.6)
A3: Выручка Closed-Won | B3: Маркетинговый бюджет | C3: W-Shaped ROMI | D3: Первое касание (Opener) | E3: Закрывающее (Closer) | F3: Взвешенный пайплайн W
A4: =calc_engine!E137 -> 1650000 | B4: =calc_engine!B137 -> 240000 | C4: =calc_engine!G137 -> 5.875 | D4: Контур.Фокус / SEO | E4: Google Ads / Контур | F4: =SUM(raw_touchpoints!$L$2:$L1000) -> 2310000
A6: ⚖️ 1. КАЛИБРОВКА МОДЕЛЕЙ АТРИБУЦИИ: FIRST-TOUCH vs LAST-TOUCH vs W-SHAPED
A7: Канал привлечения | B7: Расход, ₽ | C7: Last-Touch (V10) | D7: W-Shaped (V11) | E7: LT ROMI | F7: W-Shaped ROMI | G7: Дельта выручки, ₽ | H7: Эффект перераспределения | I7: Решение RevOps
A8: =calc_engine!A132 -> Яндекс Директ | B8: =calc_engine!B132 -> 120000 | C8: =calc_engine!D132 -> 0 | D8: =calc_engine!E132 -> 495000 | E8: =calc_engine!G132 -> -1 | F8: =calc_engine!H132 -> 3.125 | G8: =D8-C8 -> 495000 | H8: =IF(G8>0, "🟢 НЕДООЦЕНЕН (+ " & TEXT(G8, "#,##0 ₽") & ")", IF(G8<0, "🔴 ПЕРЕОЦЕНЕН В V10 (" & TEXT(G8, "#,##0 ₽") & ")", "⚪ БЕЗ ИЗМЕНЕНИЙ")) -> 🟢 НЕДООЦЕНЕН (+ 495,000 ₽) | I8: =calc_engine!I132 -> 🛡️ ЗАКРЫВАЕТ СДЕЛКИ (НЕ ОТКЛЮЧАТЬ!)
A9: =calc_engine!A133 -> Контур.Фокус | B9: =calc_engine!B133 -> 35000 | C9: =calc_engine!D133 -> 1200000 | D9: =calc_engine!E133 -> 840000 | E9: =calc_engine!G133 -> 33.285714 | F9: =calc_engine!H133 -> 23 | G9: =D9-C9 -> -360000 | H9: =IF(G9>0, "🟢 НЕДООЦЕНЕН (+ " & TEXT(G9, "#,##0 ₽") & ")", IF(G9<0, "🔴 ПЕРЕОЦЕНЕН В V10 (" & TEXT(G9, "#,##0 ₽") & ")", "⚪ БЕЗ ИЗМЕНЕНИЙ")) -> 🔴 ПЕРЕОЦЕНЕН В V10 (-360,000 ₽) | I9: =calc_engine!I133 -> 🚀 ЛИДЕР МАСШТАБИРОВАНИЯ
A10: =calc_engine!A134 -> Google Ads | B10: =calc_engine!B134 -> 85000 | C10: =calc_engine!D134 -> 450000 | D10: =calc_engine!E134 -> 135000 | E10: =calc_engine!G134 -> 4.2941176 | F10: =calc_engine!H134 -> 0.58823529 | G10: =D10-C10 -> -315000 | H10: =IF(G10>0, "🟢 НЕДООЦЕНЕН (+ " & TEXT(G10, "#,##0 ₽") & ")", IF(G10<0, "🔴 ПЕРЕОЦЕНЕН В V10 (" & TEXT(G10, "#,##0 ₽") & ")", "⚪ БЕЗ ИЗМЕНЕНИЙ")) -> 🔴 ПЕРЕОЦЕНЕН В V10 (-315,000 ₽) | I10: =calc_engine!I134 -> 🟢 СБАЛАНСИРОВАН
A11: =calc_engine!A135 -> Органика SEO | B11: =calc_engine!B135 -> 0 | C11: =calc_engine!D135 -> 0 | D11: =calc_engine!E135 -> 135000 | E11: =calc_engine!G135 -> 0 | F11: =calc_engine!H135 -> 0 | G11: =D11-C11 -> 135000 | H11: =IF(G11>0, "🟢 НЕДООЦЕНЕН (+ " & TEXT(G11, "#,##0 ₽") & ")", IF(G11<0, "🔴 ПЕРЕОЦЕНЕН В V10 (" & TEXT(G11, "#,##0 ₽") & ")", "⚪ БЕЗ ИЗМЕНЕНИЙ")) -> 🟢 НЕДООЦЕНЕН (+ 135,000 ₽) | I11: =calc_engine!I135 -> 🌱 ОРГАНИЧЕСКИЙ ДРАЙВЕР
A12: =calc_engine!A136 -> Партнеры | B12: =calc_engine!B136 -> 0 | C12: =calc_engine!D136 -> 0 | D12: =calc_engine!E136 -> 45000 | E12: =calc_engine!G136 -> 0 | F12: =calc_engine!H136 -> 0 | G12: =D12-C12 -> 45000 | H12: =IF(G12>0, "🟢 НЕДООЦЕНЕН (+ " & TEXT(G12, "#,##0 ₽") & ")", IF(G12<0, "🔴 ПЕРЕОЦЕНЕН В V10 (" & TEXT(G12, "#,##0 ₽") & ")", "⚪ БЕЗ ИЗМЕНЕНИЙ")) -> 🟢 НЕДООЦЕНЕН (+ 45,000 ₽) | I12: =calc_engine!I136 -> 🌱 ОРГАНИЧЕСКИЙ ДРАЙВЕР
A13: ИТОГО / БАЛАНС: | B13: =SUM(B8:B12) -> 240000 | C13: =SUM(C8:C12) -> 1650000 | D13: =SUM(D8:D12) -> 1650000 | E13: =calc_engine!F137 -> 5.875 | F13: =calc_engine!G137 -> 5.875 | G13: =SUM(G8:G12) -> 0 | H13: ✅ 100% Баланс SSOT | I13: Полное сохранение выручки
A15: 🔄 2. РЕЕСТР СКВОЗНЫХ КАСАНИЙ КЛИЕНТОВ (CUSTOMER JOURNEY MULTI-TOUCH FEED)
A16: ID касания | B16: ID сделки | C16: Client ID | D16: Дата касания | E16: Канал касания | F16: Этап в цепочке | G16: Вес W-Shaped | H16: Атрибутированная выручка
A17: =raw_touchpoints!A2 -> TP-101 | B17: =raw_touchpoints!B2 -> D-101 | C17: =raw_touchpoints!C2 -> ga_11 | D17: =raw_touchpoints!D2 -> 46259 | E17: =raw_touchpoints!E2 -> Органика SEO | F17: =raw_touchpoints!G2 -> 1. First Touch | G17: =raw_touchpoints!H2 -> 0.3 | H17: =raw_touchpoints!K2 -> 135000
A18: =raw_touchpoints!A3 -> TP-102 | B18: =raw_touchpoints!B3 -> D-101 | C18: =raw_touchpoints!C3 -> ga_11 | D18: =raw_touchpoints!D3 -> 46267 | E18: =raw_touchpoints!E3 -> Яндекс Директ | F18: =raw_touchpoints!G3 -> 2. Lead Creation | G18: =raw_touchpoints!H3 -> 0.3 | H18: =raw_touchpoints!K3 -> 135000
A19: =raw_touchpoints!A4 -> TP-103 | B19: =raw_touchpoints!B4 -> D-101 | C19: =raw_touchpoints!C4 -> ga_11 | D19: =raw_touchpoints!D4 -> 46272 | E19: =raw_touchpoints!E4 -> Партнеры | F19: =raw_touchpoints!G4 -> 3. Middle Nurture | G19: =raw_touchpoints!H4 -> 0.1 | H19: =raw_touchpoints!K4 -> 45000
A20: =raw_touchpoints!A5 -> TP-104 | B20: =raw_touchpoints!B5 -> D-101 | C20: =raw_touchpoints!C5 -> ga_11 | D20: =raw_touchpoints!D5 -> 46277 | E20: =raw_touchpoints!E5 -> Google Ads | F20: =raw_touchpoints!G5 -> 4. Deal Close | G20: =raw_touchpoints!H5 -> 0.3 | H20: =raw_touchpoints!K5 -> 135000
A21: =raw_touchpoints!A6 -> TP-105 | B21: =raw_touchpoints!B6 -> D-102 | C21: =raw_touchpoints!C6 -> ga_12 | D21: =raw_touchpoints!D6 -> 46262 | E21: =raw_touchpoints!E6 -> Контур.Фокус | F21: =raw_touchpoints!G6 -> 1. First Touch | G21: =raw_touchpoints!H6 -> 0.3 | H21: =raw_touchpoints!K6 -> 360000
A22: =raw_touchpoints!A7 -> TP-106 | B22: =raw_touchpoints!B7 -> D-102 | C22: =raw_touchpoints!C7 -> ga_12 | D22: =raw_touchpoints!D7 -> 46269 | E22: =raw_touchpoints!E7 -> Яндекс Директ | F22: =raw_touchpoints!G7 -> 2. Lead Creation | G22: =raw_touchpoints!H7 -> 0.3 | H22: =raw_touchpoints!K7 -> 360000
A23: =raw_touchpoints!A8 -> TP-107 | B23: =raw_touchpoints!B8 -> D-102 | C23: =raw_touchpoints!C8 -> ga_12 | D23: =raw_touchpoints!D8 -> 46275 | E23: =raw_touchpoints!E8 -> Контур.Фокус | F23: =raw_touchpoints!G8 -> 3. Middle Nurture | G23: =raw_touchpoints!H8 -> 0.1 | H23: =raw_touchpoints!K8 -> 120000
A24: =raw_touchpoints!A9 -> TP-108 | B24: =raw_touchpoints!B9 -> D-102 | C24: =raw_touchpoints!C9 -> ga_12 | D24: =raw_touchpoints!D9 -> 46281 | E24: =raw_touchpoints!E9 -> Контур.Фокус | F24: =raw_touchpoints!G9 -> 4. Deal Close | G24: =raw_touchpoints!H9 -> 0.3 | H24: =raw_touchpoints!K9 -> 360000

Sheet 🧪 QA_Suite
A1: 118 РЕГРЕССИОННЫХ ТЕСТОВ (REVOPS ENTERPRISE V17.6)
A2: 📄 1. One-Pager | B2: ⚡ 2. Пульс компании | C2: 📋 3. Пульт РОПа | D2: 💸 4. 7 Грехов ОП | E2: 🎯 5. Action Center | F2: 🎙️ 6. ИИ-Аудит | G2: ⚡ 7. Экспресс 3 цифры | H2: 🧪 8. QA Suite | I2: ⚙️ 9. Настройки
A3: 🟢 ENTERPRISE READY (100%) | B3: Всего тестов | C3: Пройдено (PASS) | D3: Сбоев (FAIL) | E3: Индекс надежности | F3: Вердикт надежности | G3: Дата валидации
A4: Статус аудита | B4: =COUNTA(A7:A124) -> 118 | C4: =COUNTIF(G7:G124, "🟢 PASS") -> 118 | D4: =COUNTIF(G7:G124, "🔴 FAIL") -> 0 | E4: =C4/B4 -> 1 | F4: =IF(C4=B4, "🟢 CENTURY ENTERPRISE READY (100%)", IF(D4>0, "🔴 DEFECTS DETECTED", "🟡 IN PROGRESS")) -> 🟢 CENTURY ENTERPRISE READY (100%) | G4: 03.10.2026
A6: ID | B6: Категория | C6: Проверяемый инвариант (Assert Description) | D6: Формула проверки | E6: Ожидание | F6: Факт | G6: Статус | H6: Диагностика для клиента (Vector D Explainability) | I6: Рекомендация по исправлению (Auto-Fix)
A7: T-01 | B7: Финансы | C7: Closed-Won выручка calc_engine!B19 == SUMIF по stage_id=6 | D7: =SUMIFS(raw_invoices!$G$2:$G$1000, raw_invoices!$H$2:$H$1000, "paid") -> 1650000 | E7: =calc_engine!B19 -> 1650000 | F7: =D7 -> 1650000 | G7: =IF(E7=F7, "🟢 PASS", "🔴 FAIL") -> 🟢 PASS | H7: Расхождение выручки между calc_engine и raw_deals. Проверьте stage_id закрытых сделок. | I7: -
A8: T-02 | B8: Финансы | C8: First-Touch Won Revenue сходится к B19 | D8: =calc_engine!C137 -> 1650000 | E8: =calc_engine!B19 -> 1650000 | F8: =calc_engine!C137 -> 1650000 | G8: =IF(ABS(E8-F8)<1, "🟢 PASS", "🔴 FAIL") -> 🟢 PASS | H8: Сумма First-Touch атрибуции не равна Closed-Won выручке. Проверьте веса FT.
A9: T-03 | B9: Финансы | C9: Last-Touch Won Revenue сходится к B19 | D9: =calc_engine!D137 -> 1650000 | E9: =calc_engine!B19 -> 1650000 | F9: =calc_engine!D137 -> 1650000 | G9: =IF(ABS(E9-F9)<1, "🟢 PASS", "🔴 FAIL") -> 🟢 PASS | H9: Сумма Last-Touch атрибуции не равна Closed-Won выручке. Проверьте веса LT.
A10: T-04 | B10: Финансы | C10: W-Shaped Won Revenue сходится к B19 | D10: =calc_engine!E137 -> 1650000 | E10: =calc_engine!B19 -> 1650000 | F10: =calc_engine!E137 -> 1650000 | G10: =IF(ABS(E10-F10)<1, "🟢 PASS", "🔴 FAIL") -> 🟢 PASS | H10: Сумма W-Shaped выигранной выручки расходится с B19. Проверьте веса в raw_touchpoints!K.
A11: T-05 | B11: Финансы | C11: Суммарный маркетинг spend B137 сходится с фактом raw_marketing!E | D11: =calc_engine!B137 -> 240000 | E11: =SUM(raw_marketing!$E$2:$E1000) -> 240000 | F11: =calc_engine!B137 -> 240000 | G11: =IF(E11=F11, "🟢 PASS", "🔴 FAIL") -> 🟢 PASS | H11: Сумма рекламных бюджетов в calc_engine расходится с первичным реестром raw_marketing.
A12: T-06 | B12: Финансы | C12: Активный пайплайн calc_engine!B17 == SUMIF(raw_deals!D, '<=5', raw_deals!C) | D12: =SUMIF(raw_deals!$D$2:$D1000, "<=5", raw_deals!$C$2:$C1000) -> 5530000 | E12: =calc_engine!B17 -> 5530000 | F12: =SUMIF(raw_deals!$D$2:$D1000, "<=5", raw_deals!$C$2:$C1000) -> 5530000 | G12: =IF(E12=F12, "🟢 PASS", "🔴 FAIL") -> 🟢 PASS | H12: Сумма открытых сделок в пайплайне calc_engine расходится с raw_deals.
A13: T-07 | B13: Финансы | C13: Отсутствие сделок с отрицательной суммой чека (MIN >= 0) | D13: =MIN(raw_deals!$C$2:$C1000)>=0 -> TRUE | E13: TRUE | F13: =MIN(raw_deals!$C$2:$C1000)>=0 -> TRUE | G13: =IF(D13=E13, "🟢 PASS", "🔴 FAIL") -> 🟢 PASS | H13: Все суммы сделок положительные (мин. чек: 120 000 ₽).
A14: T-08 | B14: Финансы | C14: Сумма выставленных счетов raw_invoices!G >= Суммы оплат B19 | D14: TRUE | E14: TRUE | F14: =SUM(raw_invoices!$G$2:$G$1000)>=calc_engine!B19 -> TRUE | G14: =IF(F14=TRUE, "🟢 PASS", "🔴 FAIL") -> 🟢 PASS | H14: Сумма поступивших оплат превышает сумму выставленных счетов.
A15: T-09 | B15: Атрибуция | C15: Сумма весов W-Shaped касаний для сделки D-101 == 1.0 | D15: =SUMIF(raw_touchpoints!$B$2:$B125, "D-101", raw_touchpoints!$H$2:$H125) -> 1 | E15: 1 | F15: =SUMIF(raw_touchpoints!$B$2:$B1000, "D-101", raw_touchpoints!$H$2:$H1000) -> 1 | G15: =IF(ABS(F15-1)<0.01, "🟢 PASS", "🔴 FAIL") -> 🟢 PASS | H15: Сумма весов касаний D-101 не равна 100%. Проверьте калибровку весов.
A16: T-10 | B16: Атрибуция | C16: Сумма весов W-Shaped касаний для сделки D-102 == 1.0 | D16: =SUMIF(raw_touchpoints!$B$2:$B125, "D-102", raw_touchpoints!$H$2:$H125) -> 1 | E16: 1 | F16: =SUMIF(raw_touchpoints!$B$2:$B1000, "D-102", raw_touchpoints!$H$2:$H1000) -> 1 | G16: =IF(ABS(F16-1)<0.01, "🟢 PASS", "🔴 FAIL") -> 🟢 PASS | H16: Сумма весов касаний D-102 не равна 100%.
A17: T-11 | B17: Атрибуция | C17: Сумма весов W-Shaped касаний для сделки D-104 == 1.0 | D17: =SUMIF(raw_touchpoints!$B$2:$B125, "D-104", raw_touchpoints!$H$2:$H125) -> 1 | E17: 1 | F17: =SUMIF(raw_touchpoints!$B$2:$B1000, "D-104", raw_touchpoints!$H$2:$H1000) -> 1 | G17: =IF(ABS(F17-1)<0.01, "🟢 PASS", "🔴 FAIL") -> 🟢 PASS | H17: Сумма весов касаний D-104 расходится с 1.0. Проверьте TP-109..TP-111B.
A18: T-12 | B18: Атрибуция | C18: Сумма весов W-Shaped касаний для сделки D-105 == 1.0 | D18: =SUMIF(raw_touchpoints!$B$2:$B125, "D-105", raw_touchpoints!$H$2:$H125) -> 1 | E18: 1 | F18: =SUMIF(raw_touchpoints!$B$2:$B1000, "D-105", raw_touchpoints!$H$2:$H1000) -> 1 | G18: =IF(ABS(F18-1)<0.01, "🟢 PASS", "🔴 FAIL") -> 🟢 PASS | H18: Сумма весов касаний D-105 не равна 100%.
A19: T-13 | B19: Атрибуция | C19: Все веса касаний в строгом диапазоне [0.0, 1.0] | D19: TRUE | E19: TRUE | F19: =AND(MIN(raw_touchpoints!$H$2:$H1000)>=0, MAX(raw_touchpoints!$H$2:$H1000)<=1) -> TRUE | G19: =IF(F19=TRUE, "🟢 PASS", "🔴 FAIL") -> 🟢 PASS | H19: В raw_touchpoints!H есть вес <0 или >1.
A20: T-14 | B20: Атрибуция | C20: Каждое касание мапится на реальную сделку в raw_deals | D20: 0 | E20: 0 | F20: =COUNTIF(raw_touchpoints!$I$2:$I1000, 0) -> 0 | G20: =IF(F20=0, "🟢 PASS", "🔴 FAIL") -> 🟢 PASS | H20: В raw_touchpoints обнаружено касание с несуществующим deal_id.
A21: T-15 | B21: Атрибуция | C21: W-Shaped пайплайн-атрибуция Col L неотрицательна (>= 0) | D21: TRUE | E21: TRUE | F21: =MIN(raw_touchpoints!$L$2:$L1000)>=0 -> TRUE | G21: =IF(F21=TRUE, "🟢 PASS", "🔴 FAIL") -> 🟢 PASS | H21: В raw_touchpoints!L обнаружены отрицательные значения атрибуции.
A22: T-16 | B22: Воронка & SLA | C22: Все нормативы SLA этапов воронки строго > 0 часов | D22: TRUE | E22: TRUE | F22: =MIN('⚙️ Настройки'!$C$12:$C$16)>0 -> TRUE | G22: =IF(F22=TRUE, "🟢 PASS", "🔴 FAIL") -> 🟢 PASS | H22: В Настройках указан нулевой или отрицательный SLA-норматив этапа.
A23: T-17 | B23: Воронка & SLA | C23: Количество открытых сделок в воронке (1..5) == calc_engine!B16 | D23: =COUNTIFS(raw_deals!$D$2:$D1000, ">=1", raw_deals!$D$2:$D1000, "<=5") -> 7 | E23: =calc_engine!B16 -> 7 | F23: =D23 -> 7 | G23: =IF(E23=F23, "🟢 PASS", "🔴 FAIL") -> 🟢 PASS | H23: Количество открытых сделок в воронке расходится с метрикой B16.
A24: T-18 | B24: Воронка & SLA | C24: Все stage_id сделок валидны (целые числа от 1 до 7) | D24: TRUE | E24: TRUE | F24: =AND(MIN(raw_deals!$D$2:$D1000)>=1, MAX(raw_deals!$D$2:$D1000)<=7) -> TRUE | G24: =IF(F24=TRUE, "🟢 PASS", "🔴 FAIL") -> 🟢 PASS | H24: В raw_deals!D обнаружен недопустимый номер этапа (вне 1..7).
A25: T-19 | B25: Воронка & SLA | C25: Сделки stage_id=6 строго имеют статус 'Успешно реализовано' | D25: 0 | E25: 0 | F25: =COUNTIFS(raw_deals!$D$2:$D1000, 6, raw_deals!$E$2:$E1000, "<>*Успешно реализовано*") -> 0 | G25: =IF(F25=0, "🟢 PASS", "🔴 FAIL") -> 🟢 PASS | H25: Рассинхрон stage_id=6 и stage_name в raw_deals.
A26: T-20 | B26: Воронка & SLA | C26: Сделки stage_id=7 строго имеют статус 'Закрыто и не реализовано' | D26: 0 | E26: 0 | F26: =COUNTIFS(raw_deals!$D$2:$D1000, 7, raw_deals!$E$2:$E1000, "<>*не реализовано*") -> 0 | G26: =IF(F26=0, "🟢 PASS", "🔴 FAIL") -> 🟢 PASS | H26: Рассинхрон stage_id=7 и stage_name в raw_deals.
A27: T-21 | B27: Воронка & SLA | C27: Вероятности этапов в Настройках монотонны (Win% 1 < Win% 5) | D27: TRUE | E27: TRUE | F27: ='⚙️ Настройки'!$D$12<'⚙️ Настройки'!$D$16 -> TRUE | G27: =IF(F27=TRUE, "🟢 PASS", "🔴 FAIL") -> 🟢 PASS | H27: Вероятность закрытия лида превышает вероятность закрытия выставленного счета.
A28: T-22 | B28: Воронка & SLA | C28: SLA факт рассчитывается без ошибок деления на ноль | D28: TRUE | E28: TRUE | F28: =ISNUMBER(AVERAGE(raw_deals!$Q$2:$Q1000)) -> TRUE | G28: =IF(F28=TRUE, "🟢 PASS", "🔴 FAIL") -> 🟢 PASS | H28: Ошибка расчета времени нахождения в этапе days_in_stage.
A29: T-23 | B29: Воронка & SLA | C29: Коэффициент соблюдения SLA в диапазоне [0.0, 1.0] | D29: TRUE | E29: TRUE | F29: =AND(calc_engine!B31>=0, calc_engine!B31<=1) -> TRUE | G29: =IF(F29=TRUE, "🟢 PASS", "🔴 FAIL") -> 🟢 PASS | H29: Индекс соблюдения SLA calc_engine!B31 вышел за границы 0..100%.
A30: T-24 | B30: ИИ-Аудит речи | C30: Средний балл речи calc_engine!B32 в допустимом диапазоне [1, 13] | D30: TRUE | E30: TRUE | F30: =AND(calc_engine!B32>=1, calc_engine!B32<=13) -> TRUE | G30: =IF(F30=TRUE, "🟢 PASS", "🔴 FAIL") -> 🟢 PASS | H30: Средний чек-лист качества речи вышел за шкалу 13 критериев.
A31: T-25 | B31: ИИ-Аудит речи | C31: Длительность всех звонков в raw_calls > 0 секунд | D31: TRUE | E31: TRUE | F31: =MIN(raw_calls!$E$2:$E1000)>0 -> TRUE | G31: =IF(F31=TRUE, "🟢 PASS", "🔴 FAIL") -> 🟢 PASS | H31: В raw_calls обнаружены звонки с нулевой или отрицательной длительностью.
A32: T-26 | B32: ИИ-Аудит речи | C32: Все звонки привязаны к существующим менеджерам [101..104] | D32: TRUE | E32: TRUE | F32: =AND(MIN(raw_calls!$C$2:$C1000)>=101, MAX(raw_calls!$C$2:$C1000)<=104) -> TRUE | G32: =IF(F32=TRUE, "🟢 PASS", "🔴 FAIL") -> 🟢 PASS | H32: В raw_calls найден звонок с неизвестным manager_id.
A33: T-27 | B33: ИИ-Аудит речи | C33: Все звонки привязаны к существующим сделкам воронки | D33: TRUE | E33: TRUE | F33: =COUNTIF(raw_calls!$B$2:$B1000, "D-*")=COUNTA(raw_calls!$B$2:$B1000) -> TRUE | G33: =IF(F33=TRUE, "🟢 PASS", "🔴 FAIL") -> 🟢 PASS | H33: В raw_calls обнаружен звонок без привязки к сделке D-*.
A34: T-28 | B34: ИИ-Аудит речи | C34: Доля фиксации Next Step calc_engine!B33 в диапазоне [0.0, 1.0] | D34: TRUE | E34: TRUE | F34: =AND(calc_engine!B33>=0, calc_engine!B33<=1) -> TRUE | G34: =IF(F34=TRUE, "🟢 PASS", "🔴 FAIL") -> 🟢 PASS | H34: Конверсия Next Step calc_engine!B33 вышла за пределы 0..100%.
A35: T-29 | B35: ИИ-Аудит речи | C35: Хронометраж звонка в ИИ_Аудит!E17 зафиксирован в формате времени | D35: TRUE | E35: TRUE | F35: =ISNUMBER(SEARCH(":", '🎙️ ИИ_Аудит'!E17)) -> TRUE | G35: =IF(F35=TRUE, "🟢 PASS", "🔴 FAIL") -> 🟢 PASS | H35: В колонке длительности звонка нарушен формат времени.
A36: T-30 | B36: ИИ-Аудит речи | C36: Выручка под угрозой в ИИ_Аудит!J4 сходится с итогом выборки V27 | D36: ='🎙️ ИИ_Аудит'!V27 -> 2,840,000 ₽ | E36: ='🎙️ ИИ_Аудит'!J4 -> 2,840,000 ₽ | F36: =D36 -> 2,840,000 ₽ | G36: =IF(E36=F36, "🟢 PASS", "🔴 FAIL") -> 🟢 PASS | H36: Сумма финансового риска брака звонков расходится с контрольной суммой выборки.
A37: T-31 | B37: Финансы & DSO | C37: DSO (Days Sales Outstanding) calc_engine!B27 неотрицательный | D37: TRUE | E37: TRUE | F37: =calc_engine!B27>=0 -> TRUE | G37: =IF(F37=TRUE, "🟢 PASS", "🔴 FAIL") -> 🟢 PASS | H37: DSO отрицательный. Проверьте формулу оборачиваемости дебиторки.
A38: T-32 | B38: Финансы & DSO | C38: Статусы счетов валидны (paid, overdue, forecast) | D38: 0 | E38: 0 | F38: =COUNTIFS(raw_invoices!$H$2:$H$1000, "<>paid", raw_invoices!$H$2:$H$1000, "<>overdue", raw_invoices!$H$2:$H$1000, "<>forecast", raw_invoices!$H$2:$H$1000, "<>") -> 0 | G38: =IF(F38=0, "🟢 PASS", "🔴 FAIL") -> 🟢 PASS | H38: В raw_invoices обнаружен неизвестный статус инвойса.
A39: T-33 | B39: Финансы & DSO | C39: Просроченная дебиторка B145 <= общей суммы счетов | D39: TRUE | E39: TRUE | F39: =calc_engine!B145<=SUM(raw_invoices!$G$2:$G$1000) -> TRUE | G39: =IF(F39=TRUE, "🟢 PASS", "🔴 FAIL") -> 🟢 PASS | H39: Просроченная дебиторка превышает общую сумму выставленных счетов.
A40: T-34 | B40: Финансы & DSO | C40: Cash-In calc_engine!B19 строго равен Closed-Won выручке | D40: =SUMIF(raw_invoices!$H$2:$H$1000, "paid", raw_invoices!$G$2:$G$1000) -> 1650000 | E40: =calc_engine!B19 -> 1650000 | F40: =D40 -> 1650000 | G40: =IF(E40=F40, "🟢 PASS", "🔴 FAIL") -> 🟢 PASS | H40: Фактические поступления Cash-In расходятся с закрытыми сделками.
A41: T-35 | B41: Финансы & DSO | C41: Отсутствие счетов с отрицательной суммой в raw_invoices!G | D41: TRUE | E41: TRUE | F41: =MIN(raw_invoices!$G$2:$G$1000)>=0 -> TRUE | G41: =IF(F41=TRUE, "🟢 PASS", "🔴 FAIL") -> 🟢 PASS | H41: Обнаружен счет с отрицательной суммой к оплате.
A42: T-36 | B42: Финансы & DSO | C42: Сумма оплаченных счетов (paid) равна Closed-Won выручке B19 | D42: =SUMIF(raw_invoices!$H$2:$H$1000, "paid", raw_invoices!$G$2:$G$1000) -> 1650000 | E42: =calc_engine!B19 -> 1650000 | F42: =D42 -> 1650000 | G42: =IF(E42=F42, "🟢 PASS", "🔴 FAIL") -> 🟢 PASS | H42: Сумма оплаченных инвойсов в реестре raw_invoices расходится с выручкой B19.
A43: T-37 | B43: Алерты & Риски | C43: Суммы в raw_alerts!D строго числовые (ISNUMBER) | D43: TRUE | E43: TRUE | F43: =AND(ISNUMBER(raw_alerts!$D$2), ISNUMBER(raw_alerts!$D$3), ISNUMBER(raw_alerts!$D$4)) -> TRUE | G43: =IF(F43=TRUE, "🟢 PASS", "🔴 FAIL") -> 🟢 PASS | H43: Суммы алертов сохранены как текст, SUM(raw_alerts!D) сломается.
A44: T-38 | B44: Алерты & Риски | C44: Суммы всех зарегистрированных алертов > 0 | D44: TRUE | E44: TRUE | F44: =MIN(raw_alerts!$D$2:$D$6)>0 -> TRUE | G44: =IF(F44=TRUE, "🟢 PASS", "🔴 FAIL") -> 🟢 PASS | H44: В raw_alerts найден алерт с нулевой или отрицательной суммой риска.
A45: T-39 | B45: Алерты & Риски | C45: Доля базы РОПа calc_engine!B35 в диапазоне [0.0, 1.0] | D45: TRUE | E45: TRUE | F45: =AND(calc_engine!B35>=0, calc_engine!B35<=1) -> TRUE | G45: =IF(F45=TRUE, "🟢 PASS", "🔴 FAIL") -> 🟢 PASS | H45: Коэффициент нагрузки РОПа вышел за границы 0..100%.
A46: T-40 | B46: Алерты & Риски | C46: Нормативные лимиты сделок сотрудников в Настройках > 0 | D46: TRUE | E46: TRUE | F46: =MIN('⚙️ Настройки'!$D$21:$D$24)>0 -> TRUE | G46: =IF(F46=TRUE, "🟢 PASS", "🔴 FAIL") -> 🟢 PASS | H46: В Настройках емкости указан нулевой лимит сделок менеджера.
A47: T-41 | B47: Алерты & Риски | C47: Количество активных правил мониторинга в Радаре >= 5 | D47: TRUE | E47: TRUE | F47: =COUNTA('🚨 Радар_Алертов'!$A$4:$A$9)>=5 -> TRUE | G47: =IF(F47=TRUE, "🟢 PASS", "🔴 FAIL") -> 🟢 PASS | H47: В Радаре алертов отключены или удалены базовые триггеры.
A48: T-42 | B48: Алерты & Риски | C48: РОП Иванов Д. (101) имеет активные сделки в контуре | D48: TRUE | E48: TRUE | F48: =COUNTIF(raw_deals!$H$2:$H1000, 101)>0 -> TRUE | G48: =IF(F48=TRUE, "🟢 PASS", "🔴 FAIL") -> 🟢 PASS | H48: У РОПа нет сделок в воронке, проверка перегруза невозможна.
A49: T-43 | B49: Система & Стабильность | C49: Отсутствие #REF! в ключевой метрике выручки | D49: TRUE | E49: TRUE | F49: =NOT(ISERROR(calc_engine!B19)) -> TRUE | G49: =IF(F49=TRUE, "🟢 PASS", "🔴 FAIL") -> 🟢 PASS | H49: Сломана ссылка #REF! в расчете выручки calc_engine!B19.
A50: T-44 | B50: Система & Стабильность | C50: Отсутствие #VALUE! в расчете когорт LTV | D50: TRUE | E50: TRUE | F50: =NOT(ISERROR('📈 Когорты_LTV'!D10)) -> TRUE | G50: =IF(F50=TRUE, "🟢 PASS", "🔴 FAIL") -> 🟢 PASS | H50: Ошибка типов данных #VALUE! в когортном анализе.
A51: T-45 | B51: Система & Стабильность | C51: Отсутствие #NAME? во взвешенном пайплайне | D51: TRUE | E51: TRUE | F51: =NOT(ISERROR(calc_engine!B18)) -> TRUE | G51: =IF(F51=TRUE, "🟢 PASS", "🔴 FAIL") -> 🟢 PASS | H51: Неизвестная функция #NAME? в расчетном ядре calc_engine!B18.
A52: T-46 | B52: Система & Стабильность | C52: Отсутствие #DIV/0! в расчете конверсий воронки | D52: TRUE | E52: TRUE | F52: =NOT(ISERROR(calc_engine!B24)) -> TRUE | G52: =IF(F52=TRUE, "🟢 PASS", "🔴 FAIL") -> 🟢 PASS | H52: Деление на ноль #DIV/0! в Win Rate воронки calc_engine!B24.
A53: T-47 | B53: Система & Стабильность | C53: Системная дата calc_engine!$B$1 равна DATE(2026, 9, 29) | D53: 46294 | E53: 46294 | F53: =INT(calc_engine!$B$1) -> 46294 | G53: =IF(E53=F53, "🟢 PASS", "🔴 FAIL") -> 🟢 PASS | H53: Дрейф системной даты проекта. Должно быть 2026-09-29.
A54: T-48 | B54: Система & Стабильность | C54: Выбранный филиал / холдинг в Настройках не пустой | D54: =EXACT('🗄️ DWH_и_Безопасность'!$F$4, "✅ PASS 100% (43 листа)") -> FALSE | E54: =EXACT('🗄️ DWH_и_Безопасность'!$F$4, "✅ PASS 100% (43 листа)") -> FALSE | F54: ='⚙️ Настройки'!$D$9<>"" -> TRUE | G54: =IF(F54=TRUE, "🟢 PASS", "🔴 FAIL") -> 🟢 PASS | H54: Сброшен селектор филиала в ⚙️ Настройки!D9.
A55: T-49 | B55: Система & Стабильность | C55: Выбранная роль пользователя в Настройках не пустая | D55: TRUE | E55: TRUE | F55: ='⚙️ Настройки'!$B$10<>"" -> TRUE | G55: =IF(F55=TRUE, "🟢 PASS", "🔴 FAIL") -> 🟢 PASS | H55: Сброшен селектор роли в ⚙️ Настройки!B10.
A56: T-50 | B56: Система & Стабильность | C56: Версия архитектуры в Настройках — Enterprise OS | D56: TRUE | E56: TRUE | F56: =ISNUMBER(SEARCH("Enterprise OS", '⚙️ Настройки'!$B$5)) -> TRUE | G56: =IF(F56=TRUE, "🟢 PASS", "🔴 FAIL") -> 🟢 PASS | H56: Повреждена строка версии архитектуры в ⚙️ Настройки!B5.
A57: T-51 | B57: Качество данных | C57: Интегральный DQ Score платформы ≥ 0.85 | D57: ='📊 Data_Quality'!C8 -> 1 | E57: ='📊 Data_Quality'!C8 -> 1 | F57: 0.85 | G57: =IF(E57>=F57, "🟢 PASS", "🔴 FAIL") -> 🟢 PASS | H57: Индекс качества данных ниже допустимого порога 0.85.
A58: T-52 | B58: Качество данных | C58: Отсутствие незаполненных deal_id в активных сделках | D58: =COUNTIFS(raw_deals!$A$2:$A$1000, "", raw_deals!$B$2:$B$1000, "<>") -> 0 | E58: =COUNTIFS(raw_deals!$A$2:$A$1000, "", raw_deals!$B$2:$B$1000, "<>") -> 0 | F58: 0 | G58: =IF(E58=F58, "🟢 PASS", "🔴 FAIL") -> 🟢 PASS | H58: Обнаружены строки с контрагентом, но без присвоенного deal_id.
A59: T-53 | B59: Качество данных | C59: Отсутствие дубликатов deal_id в первичном реестре raw_deals | D59: {=SUMPRODUCT((raw_deals!$A$2:$A$1000<>"")*(COUNTIF(raw_deals!$A$2:$A$1000, raw_deals!$A$2:$A$1000)>1))} -> 0 | E59: {=SUMPRODUCT((raw_deals!$A$2:$A$1000<>"")*(COUNTIF(raw_deals!$A$2:$A$1000, raw_deals!$A$2:$A$1000)>1))} -> 0 | F59: 0 | G59: =IF(E59=F59, "🟢 PASS", "🔴 FAIL") -> 🟢 PASS | H59: Обнаружены дубликаты deal_id в CRM реестре raw_deals.
A60: T-54 | B60: История стадий | C60: Stage_History заполнена для всех закрытых сделок | D60: =AND(COUNTIF('📊 Stage_History'!$A$2:$A$1000, "D-101")>0, COUNTIF('📊 Stage_History'!$A$2:$A$1000, "D-102")>0) -> TRUE | E60: =AND(COUNTIF('📊 Stage_History'!$A$2:$A$1000, "D-101")>0, COUNTIF('📊 Stage_History'!$A$2:$A$1000, "D-102")>0) -> TRUE | F60: TRUE | G60: =IF(E60=F60, "🟢 PASS", "🔴 FAIL") -> 🟢 PASS | H60: Закрытые сделки отсутствуют в листе Stage_History.
A61: T-55 | B61: История стадий | C61: Каждая сделка имеет минимум 1 запись в Stage_History | D61: =MIN(COUNTIF('📊 Stage_History'!$A$2:$A$1000, raw_deals!$A$2), COUNTIF('📊 Stage_History'!$A$2:$A$1000, raw_deals!$A$3), COUNTIF('📊 Stage_History'!$A$2:$A$1000, raw_deals!$A$4), COUNTIF('📊 Stage_History'!$A$2:$A$1000, raw_deals!$A$5), COUNTIF('📊 Stage_History'!$A$2:$A$1000, raw_deals!$A$6), COUNTIF('📊 Stage_History'!$A$2:$A$1000, raw_deals!$A$7), COUNTIF('📊 Stage_History'!$A$2:$A$1000, raw_deals!$A$8), COUNTIF('📊 Stage_History'!$A$2:$A$1000, raw_deals!$A$9), COUNTIF('📊 Stage_History'!$A$2:$A$1000, raw_deals!$A$10), COUNTIF('📊 Stage_History'!$A$2:$A$1000, raw_deals!$A$11), COUNTIF('📊 Stage_History'!$A$2:$A$1000, raw_deals!$A$12)) -> 1 | E61: =MIN(COUNTIF('📊 Stage_History'!$A$2:$A$1000, raw_deals!$A$2), COUNTIF('📊 Stage_History'!$A$2:$A$1000, raw_deals!$A$3), COUNTIF('📊 Stage_History'!$A$2:$A$1000, raw_deals!$A$4), COUNTIF('📊 Stage_History'!$A$2:$A$1000, raw_deals!$A$5), COUNTIF('📊 Stage_History'!$A$2:$A$1000, raw_deals!$A$6), COUNTIF('📊 Stage_History'!$A$2:$A$1000, raw_deals!$A$7), COUNTIF('📊 Stage_History'!$A$2:$A$1000, raw_deals!$A$8), COUNTIF('📊 Stage_History'!$A$2:$A$1000, raw_deals!$A$9), COUNTIF('📊 Stage_History'!$A$2:$A$1000, raw_deals!$A$10), COUNTIF('📊 Stage_History'!$A$2:$A$1000, raw_deals!$A$11), COUNTIF('📊 Stage_History'!$A$2:$A$1000, raw_deals!$A$12)) -> 1 | F61: 1 | G61: =IF(E61>=F61, "🟢 PASS", "🔴 FAIL") -> 🟢 PASS | H61: Обнаружены сделки без истории переходов по стадиям.
A62: T-56 | B62: История стадий | C62: Все статусы sla_status принадлежат множеству {В НОРМЕ, СРЫВ} | D62: =COUNTIFS('📊 Stage_History'!$G$2:$G$1000, "<>🟢 В НОРМЕ", '📊 Stage_History'!$G$2:$G$1000, "<>🔴 СРЫВ", '📊 Stage_History'!$G$2:$G$1000, "<>") -> 0 | E62: =COUNTIFS('📊 Stage_History'!$G$2:$G$1000, "<>🟢 В НОРМЕ", '📊 Stage_History'!$G$2:$G$1000, "<>🔴 СРЫВ", '📊 Stage_History'!$G$2:$G$1000, "<>") -> 0 | F62: 0 | G62: =IF(E62=F62, "🟢 PASS", "🔴 FAIL") -> 🟢 PASS | H62: В Stage_History обнаружены некорректные статусы SLA.
A63: T-57 | B63: Next Action | C63: Дата следующего шага next_action_date >= created_date | D63: =COUNTIFS(raw_deals!$AE$2:$AE$1000, "<>", raw_deals!$AE$2:$AE$1000, "<2026-09-01") -> 0 | E63: =COUNTIFS(raw_deals!$AE$2:$AE$1000, "<>", raw_deals!$AE$2:$AE$1000, "<2026-09-01") -> 0 | F63: 0 | G63: =IF(E63=F63, "🟢 PASS", "🔴 FAIL") -> 🟢 PASS | H63: Обнаружены даты следующего действия предшествующие созданию сделки.
A64: T-58 | B64: Next Action | C64: Deal Health Score принадлежит отрезку [0, 100] | D64: =COUNTIFS(raw_deals!$AI$2:$AI$1000, "<0") + COUNTIFS(raw_deals!$AI$2:$AI$1000, ">100") -> 0 | E64: =COUNTIFS(raw_deals!$AI$2:$AI$1000, "<0") + COUNTIFS(raw_deals!$AI$2:$AI$1000, ">100") -> 0 | F64: 0 | G64: =IF(E64=F64, "🟢 PASS", "🔴 FAIL") -> 🟢 PASS | H64: Значения Deal Health Score выходят за диапазон 0..100.
A65: T-59 | B65: SLA & Эскалации | C65: Все переходы transition_id покрыты в матрице SLA | D65: =COUNTIF('⏱️ SLA_Matrix'!$A$2:$A$100, "TR-*") -> 5 | E65: =COUNTIF('⏱️ SLA_Matrix'!$A$2:$A$100, "TR-*") -> 5 | F65: 5 | G65: =IF(E65=F65, "🟢 PASS", "🔴 FAIL") -> 🟢 PASS | H65: Не все переходы воронки зафиксированы в SLA_Matrix.
A66: T-59-B | B66: SLA & Эскалации | C66: Нормативы SLA_Matrix монотонны (L1 <= L2 <= L3) | D66: =AND('⏱️ SLA_Matrix'!E2<='⏱️ SLA_Matrix'!F2, '⏱️ SLA_Matrix'!F2<='⏱️ SLA_Matrix'!G2, '⏱️ SLA_Matrix'!E3<='⏱️ SLA_Matrix'!F3, '⏱️ SLA_Matrix'!F3<='⏱️ SLA_Matrix'!G3, '⏱️ SLA_Matrix'!E4<='⏱️ SLA_Matrix'!F4, '⏱️ SLA_Matrix'!F4<='⏱️ SLA_Matrix'!G4, '⏱️ SLA_Matrix'!E5<='⏱️ SLA_Matrix'!F5, '⏱️ SLA_Matrix'!F5<='⏱️ SLA_Matrix'!G5, '⏱️ SLA_Matrix'!E6<='⏱️ SLA_Matrix'!F6, '⏱️ SLA_Matrix'!F6<='⏱️ SLA_Matrix'!G6) -> TRUE | E66: =AND('⏱️ SLA_Matrix'!E2<='⏱️ SLA_Matrix'!F2, '⏱️ SLA_Matrix'!F2<='⏱️ SLA_Matrix'!G2, '⏱️ SLA_Matrix'!E3<='⏱️ SLA_Matrix'!F3, '⏱️ SLA_Matrix'!F3<='⏱️ SLA_Matrix'!G3, '⏱️ SLA_Matrix'!E4<='⏱️ SLA_Matrix'!F4, '⏱️ SLA_Matrix'!F4<='⏱️ SLA_Matrix'!G4, '⏱️ SLA_Matrix'!E5<='⏱️ SLA_Matrix'!F5, '⏱️ SLA_Matrix'!F5<='⏱️ SLA_Matrix'!G5, '⏱️ SLA_Matrix'!E6<='⏱️ SLA_Matrix'!F6, '⏱️ SLA_Matrix'!F6<='⏱️ SLA_Matrix'!G6) -> TRUE | F66: TRUE | G66: =IF(E66=F66, "🟢 PASS", "🔴 FAIL") -> 🟢 PASS | H66: Нарушена монотонность эскалационных часов в SLA_Matrix.
A67: T-61 | B67: SLA & Эскалации | C67: Индекс соблюдения SLA принадлежит интервалу [0, 1] | D67: =AND(calc_engine!B31>=0, calc_engine!B31<=1) -> TRUE | E67: =AND(calc_engine!B31>=0, calc_engine!B31<=1) -> TRUE | F67: TRUE | G67: =IF(E67=F67, "🟢 PASS", "🔴 FAIL") -> 🟢 PASS | H67: Индекс SLA выходит за границы допустимого интервала [0, 1].
A68: T-62 | B68: SLA & Эскалации | C68: Action_Center не содержит пустых priority у зарегистрированных действий | D68: =COUNTIFS('🎯 Action_Center'!$E$2:$E$100, "", '🎯 Action_Center'!$A$2:$A$100, "?*") -> 0 | E68: =COUNTIFS('🎯 Action_Center'!$E$2:$E$100, "", '🎯 Action_Center'!$A$2:$A$100, "?*") -> 0 | F68: 0 | G68: =IF(E68=F68, "🟢 PASS", "🔴 FAIL") -> 🟢 PASS | H68: В Action_Center обнаружены задачи без присвоенного приоритета.
A69: T-63 | B69: Межлистовой баланс | C69: Closed-Won выручка calc_engine!B19 == SUMIF по stage_id=6 | D69: =calc_engine!B19 -> 1650000 | E69: =SUMIF(raw_deals!$D$2:$D$1000, 6, raw_deals!$C$2:$C$1000) -> 1650000 | F69: =calc_engine!B19 -> 1650000 | G69: =IF(E69=F69, "🟢 PASS", "🔴 FAIL") -> 🟢 PASS | H69: Расхождение выручки между calc_engine и raw_deals. | I69: Проверить stage_id и сумму закрытых сделок в raw_deals.
A70: T-64 | B70: Межлистовой баланс | C70: Оплаченная дебиторка calc_engine!B144 == SUMIF по paid | D70: =calc_engine!B144 -> 1650000 | E70: =SUMIF(raw_invoices!$H$2:$H$1000, "paid", raw_invoices!$G$2:$G$1000) -> 1650000 | F70: =calc_engine!B144 -> 1650000 | G70: =IF(E70=F70, "🟢 PASS", "🔴 FAIL") -> 🟢 PASS | H70: Сумма оплаченных счетов расходится с B144. | I70: Сверить реестр счетов raw_invoices и банковские выписки.
A71: T-65 | B71: Межлистовой баланс | C71: Просроченная задолженность calc_engine!B146 == SUMIF по overdue | D71: =calc_engine!B146 -> 330000 | E71: =SUMIF(raw_invoices!$H$2:$H$1000, "overdue", raw_invoices!$G$2:$G$1000) -> 330000 | F71: =calc_engine!B146 -> 330000 | G71: =IF(E71=F71, "🟢 PASS", "🔴 FAIL") -> 🟢 PASS | H71: Сумма просрочки расходится со сводкой B146. | I71: Провести ревизию счетов со статусом overdue в raw_invoices.
A72: T-66 | B72: Межлистовой баланс | C72: CPL в маркетинге calc_marketing!B6 == calc_engine!B137 / SUM(leads) | D72: =ROUND(calc_marketing!B6, 2) -> 2330.1 | E72: =ROUND(calc_engine!B137 / MAX(SUM(raw_marketing!$H$2:$H$1000), 1), 2) -> 2330.1 | F72: =ROUND(calc_marketing!B6, 2) -> 2330.1 | G72: =IF(E72=F72, "🟢 PASS", "🔴 FAIL") -> 🟢 PASS | H72: Стоимость лида CPL расходится между листами. | I72: Сверить рекламный расход B137 и число лидов в raw_marketing.
A73: T-67 | B73: Межлистовой баланс | C73: ROMI в маркетинге calc_marketing!B8 == (E137 - B137) / B137 | D73: =ROUND(calc_marketing!B8, 4) -> 5.875 | E73: =ROUND((calc_engine!E137 - calc_engine!B137) / MAX(calc_engine!B137, 1), 4) -> 5.875 | F73: =ROUND(calc_marketing!B8, 4) -> 5.875 | G73: =IF(E73=F73, "🟢 PASS", "🔴 FAIL") -> 🟢 PASS | H73: Показатель окупаемости ROMI не сходится с SSOT. | I73: Пересчитать веса атрибуции в raw_touchpoints и расход B137.
A74: T-68 | B74: Ссылочная целостность | C74: Каждый звонок имеет привязку к существующей сделке (FK deal_id) | D74: =COUNTIFS(raw_calls!$B$2:$B$1000, "?*", raw_calls!$A$2:$A$1000, "?*") - SUMPRODUCT((raw_calls!$B$2:$B$1000<>"") * (ISNUMBER(MATCH(raw_calls!$B$2:$B$1000, raw_deals!$A$2:$A$1000, 0)))) -> 0 | E74: =COUNTIFS(raw_calls!$B$2:$B$1000, "?*", raw_calls!$A$2:$A$1000, "?*") - SUMPRODUCT((raw_calls!$B$2:$B$1000<>"") * (ISNUMBER(MATCH(raw_calls!$B$2:$B$1000, raw_deals!$A$2:$A$1000, 0)))) -> 0 | F74: 0 | G74: =IF(E74=F74, "🟢 PASS", "🔴 FAIL") -> 🟢 PASS | H74: Обнаружены звонки без привязки к сделке. | I74: Привязать звонок к карточке сделки в CRM.
A75: T-69 | B75: Ссылочная целостность | C75: Каждый счёт имеет привязку к сделке (FK deal_id) | D75: =COUNTIFS(raw_invoices!$B$2:$B$1000, "?*", raw_invoices!$A$2:$A$1000, "?*") - SUMPRODUCT((raw_invoices!$B$2:$B$1000<>"") * (ISNUMBER(MATCH(raw_invoices!$B$2:$B$1000, raw_deals!$A$2:$A$1000, 0)))) -> 0 | E75: =COUNTIFS(raw_invoices!$B$2:$B$1000, "?*", raw_invoices!$A$2:$A$1000, "?*") - SUMPRODUCT((raw_invoices!$B$2:$B$1000<>"") * (ISNUMBER(MATCH(raw_invoices!$B$2:$B$1000, raw_deals!$A$2:$A$1000, 0)))) -> 0 | F75: 0 | G75: =IF(E75=F75, "🟢 PASS", "🔴 FAIL") -> 🟢 PASS | H75: Обнаружены счета без привязки к сделке. | I75: Проставить корректный deal_id в реестре raw_invoices.
A76: T-70 | B76: Ссылочная целостность | C76: Каждый платеж имеет привязку к счету или сделке (FK) | D76: =COUNTIFS(raw_payments!$B$2:$B$1000, "?*", raw_payments!$A$2:$A$1000, "?*") - SUMPRODUCT((raw_payments!$B$2:$B$1000<>"") * (ISNUMBER(MATCH(raw_payments!$B$2:$B$1000, raw_deals!$A$2:$A$1000, 0)))) -> 0 | E76: =COUNTIFS(raw_payments!$B$2:$B$1000, "?*", raw_payments!$A$2:$A$1000, "?*") - SUMPRODUCT((raw_payments!$B$2:$B$1000<>"") * (ISNUMBER(MATCH(raw_payments!$B$2:$B$1000, raw_deals!$A$2:$A$1000, 0)))) -> 0 | F76: 0 | G76: =IF(E76=F76, "🟢 PASS", "🔴 FAIL") -> 🟢 PASS | H76: Обнаружены неидентифицированные платежи. | I76: Уточнить контрагента в банке и привязать платеж.
A77: T-71 | B77: Ссылочная целостность | C77: Каждое маркетинговое касание имеет сделку в raw_deals | D77: =COUNTIFS(raw_touchpoints!$B$2:$B$1000, "?*", raw_touchpoints!$A$2:$A$1000, "?*") - SUMPRODUCT((raw_touchpoints!$B$2:$B$1000<>"") * (ISNUMBER(MATCH(raw_touchpoints!$B$2:$B$1000, raw_deals!$A$2:$A$1000, 0)))) -> 0 | E77: =COUNTIFS(raw_touchpoints!$B$2:$B$1000, "?*", raw_touchpoints!$A$2:$A$1000, "?*") - SUMPRODUCT((raw_touchpoints!$B$2:$B$1000<>"") * (ISNUMBER(MATCH(raw_touchpoints!$B$2:$B$1000, raw_deals!$A$2:$A$1000, 0)))) -> 0 | F77: 0 | G77: =IF(E77=F77, "🟢 PASS", "🔴 FAIL") -> 🟢 PASS | H77: Касания в CDP не смаплены со сделками. | I77: Запустить сессионный Reverse ETL stitcher в CDP.
A78: T-72 | B78: Уникальность ID | C78: Идентификаторы сделок deal_id уникальны (0 дубликатов) | D78: {=SUMPRODUCT((raw_deals!$A$2:$A$1000<>"")*(COUNTIF(raw_deals!$A$2:$A$1000, raw_deals!$A$2:$A$1000)>1))} -> 0 | E78: {=SUMPRODUCT((raw_deals!$A$2:$A$1000<>"")*(COUNTIF(raw_deals!$A$2:$A$1000, raw_deals!$A$2:$A$1000)>1))} -> 0 | F78: 0 | G78: =IF(E78=F78, "🟢 PASS", "🔴 FAIL") -> 🟢 PASS | H78: Обнаружены дубликаты deal_id в CRM. | I78: Найти дубль в raw_deals, объединить через VLOOKUP + IFERROR.
A79: T-73 | B79: Уникальность ID | C79: Идентификаторы звонков call_id уникальны (0 дубликатов) | D79: {=SUMPRODUCT((raw_calls!$A$2:$A$1000<>"")*(COUNTIF(raw_calls!$A$2:$A$1000, raw_calls!$A$2:$A$1000)>1))} -> 0 | E79: {=SUMPRODUCT((raw_calls!$A$2:$A$1000<>"")*(COUNTIF(raw_calls!$A$2:$A$1000, raw_calls!$A$2:$A$1000)>1))} -> 0 | F79: 0 | G79: =IF(E79=F79, "🟢 PASS", "🔴 FAIL") -> 🟢 PASS | H79: Обнаружены дубликаты звонков call_id. | I79: Дедуплицировать логи телефонии по call_id.
A80: T-74 | B80: Уникальность ID | C80: Номера счетов invoice_id уникальны (0 дубликатов) | D80: {=SUMPRODUCT((raw_invoices!$A$2:$A$1000<>"")*(COUNTIF(raw_invoices!$A$2:$A$1000, raw_invoices!$A$2:$A$1000)>1))} -> 0 | E80: {=SUMPRODUCT((raw_invoices!$A$2:$A$1000<>"")*(COUNTIF(raw_invoices!$A$2:$A$1000, raw_invoices!$A$2:$A$1000)>1))} -> 0 | F80: 0 | G80: =IF(E80=F80, "🟢 PASS", "🔴 FAIL") -> 🟢 PASS | H80: Обнаружены дубликаты счетов в 1С биллинге. | I80: Проверить реестр выставления счетов в 1С.
A81: T-75 | B81: Временная отсечка | C81: Отсутствие событий с датой позже отчетной отсечки calc_engine!$B$1 | D81: =COUNTIF('📅 Deal_Event_Log'!$C$2:$C$1000, ">" & TEXT(calc_engine!$B$1, "YYYY-MM-DD 23:59:59")) -> 0 | E81: =COUNTIF('📅 Deal_Event_Log'!$C$2:$C$1000, ">" & TEXT(calc_engine!$B$1, "YYYY-MM-DD 23:59:59")) -> 0 | F81: 0 | G81: =IF(E81=F81, "🟢 PASS", "🔴 FAIL") -> 🟢 PASS | H81: Обнаружены события из будущего. | I81: Скорректировать системную дату синхронизации.
A82: T-76 | B82: Временная отсечка | C82: Отсутствие отрицательных значений цикла сделки cycle_days | D82: =COUNTIF(raw_deals!$T$2:$T$1000, "<0") -> 0 | E82: =COUNTIF(raw_deals!$T$2:$T$1000, "<0") -> 0 | F82: 0 | G82: =IF(E82=F82, "🟢 PASS", "🔴 FAIL") -> 🟢 PASS | H82: Отрицательная длительность сделок. | I82: Проверить даты created_date и stage_changed_date.
A83: T-77 | B83: Временная отсечка | C83: Даты касаний закрытых сделок не превышают дату закрытия | D83: =COUNTIFS(raw_touchpoints!$B$2:$B$1000, "D-101", raw_touchpoints!$C$2:$C$1000, ">2026-09-12") + COUNTIFS(raw_touchpoints!$B$2:$B$1000, "D-102", raw_touchpoints!$C$2:$C$1000, ">2026-09-16") -> 0 | E83: =COUNTIFS(raw_touchpoints!$B$2:$B$1000, "D-101", raw_touchpoints!$C$2:$C$1000, ">2026-09-12") + COUNTIFS(raw_touchpoints!$B$2:$B$1000, "D-102", raw_touchpoints!$C$2:$C$1000, ">2026-09-16") -> 0 | F83: 0 | G83: =IF(E83=F83, "🟢 PASS", "🔴 FAIL") -> 🟢 PASS | H83: Касания зафиксированы после закрытия сделки. | I83: Исключить пост-конверсионные клики из атрибуции.
A84: T-78 | B84: Бизнес-правила | C84: Closed-Won сделки (этап 6) имеют подтвержденные поступления | D84: =AND(COUNTIF(raw_payments!$B$2:$B$1000, "D-101")>0, COUNTIF(raw_payments!$B$2:$B$1000, "D-102")>0) -> TRUE | E84: =AND(COUNTIF(raw_payments!$B$2:$B$1000, "D-101")>0, COUNTIF(raw_payments!$B$2:$B$1000, "D-102")>0) -> TRUE | F84: TRUE | G84: =IF(E84=F84, "🟢 PASS", "🔴 FAIL") -> 🟢 PASS | H84: Выигранные сделки не имеют оплат в банке. | I84: Создать счёт в raw_invoices или изменить stage на 5.
A85: T-79 | B85: Бизнес-правила | C85: Ни один менеджер не имеет критического перегруза >150% | D85: =COUNTIF('⚙️ Настройки'!$E$21:$E$24, ">1.5") -> 0 | E85: =COUNTIF('⚙️ Настройки'!$E$21:$E$24, ">1.5") -> 0 | F85: 0 | G85: =IF(E85=F85, "🟢 PASS", "🔴 FAIL") -> 🟢 PASS | H85: Критический перегруз сотрудников отдела продаж. | I85: Открыть 🎯 Action_Center, выполнить делегирование на свободного КАМа.
A86: T-80 | B86: Бизнес-правила | C86: Суммы сделок не отрицательны (скидка не превышает 100%) | D86: =COUNTIF(raw_deals!$C$2:$C$1000, "<0") -> 0 | E86: =COUNTIF(raw_deals!$C$2:$C$1000, "<0") -> 0 | F86: 0 | G86: =IF(E86=F86, "🟢 PASS", "🔴 FAIL") -> 🟢 PASS | H86: Обнаружены отрицательные суммы в сделках. | I86: Уменьшить скидку до 15% или запросить апрув CFO.
A87: T-81 | B87: Бизнес-правила | C87: Все сделки на этапе выставленного счета (5) имеют выставленный счет | D87: =AND(COUNTIF(raw_invoices!$B$2:$B$1000, "D-103")>0, COUNTIF(raw_invoices!$B$2:$B$1000, "D-099")>0) -> TRUE | E87: =AND(COUNTIF(raw_invoices!$B$2:$B$1000, "D-103")>0, COUNTIF(raw_invoices!$B$2:$B$1000, "D-099")>0) -> TRUE | F87: TRUE | G87: =IF(E87=F87, "🟢 PASS", "🔴 FAIL") -> 🟢 PASS | H87: Сделка на этапе 5 без счета в биллинге. | I87: Сгенерировать и выставить счет в 1С.
A88: T-82 | B88: Бизнес-правила | C88: Каждая сделка имеет заполненный источник лида lead_source | D88: =COUNTIFS(raw_deals!$A$2:$A$1000, "?*", raw_deals!$J$2:$J$1000, "") -> 0 | E88: =COUNTIFS(raw_deals!$A$2:$A$1000, "?*", raw_deals!$J$2:$J$1000, "") -> 0 | F88: 0 | G88: =IF(E88=F88, "🟢 PASS", "🔴 FAIL") -> 🟢 PASS | H88: Обнаружены лиды без указания источника привлечения. | I88: Проставить рекламный канал / источник в CRM.
A89: T-83 | B89: Операционный контур | C89: Action_Center: Уникальность task_id (TSK-NNN) | D89: =COUNTIF('🎯 Action_Center'!$A$2:$A$50, "ACT*")=COUNTA('🎯 Action_Center'!$A$2:$A$50) -> TRUE | E89: TRUE | F89: =COUNTIF('🎯 Action_Center'!$A$2:$A$50, "ACT*")=COUNTA('🎯 Action_Center'!$A$2:$A$50) -> TRUE | G89: =IF(D89=E89, "🟢 PASS", "🔴 FAIL") -> 🟢 PASS | H89: Обнаружены дубликаты или некорректные идентификаторы задач в Action_Center. | I89: Проверить столбец Action_Center!A и устранить дубли.
A90: T-84 | B90: Операционный контур | C90: Action_Center: Неотрицательность сумм финансового риска | D90: =MIN('🎯 Action_Center'!$F$2:$F$50)>=0 -> TRUE | E90: TRUE | F90: =MIN('🎯 Action_Center'!$F$2:$F$50)>=0 -> TRUE | G90: =IF(D90=E90, "🟢 PASS", "🔴 FAIL") -> 🟢 PASS | H90: Отрицательная сумма ущерба в Action_Center. | I90: Проверить столбец F в Action_Center.
A91: T-85 | B91: Операционный контур | C91: Action_Center: Назначение ответственных по всем открытым задачам | D91: =COUNTIFS('🎯 Action_Center'!$H$2:$H$50, "OPEN", '🎯 Action_Center'!$G$2:$G$50, "")=0 -> TRUE | E91: TRUE | F91: =COUNTIFS('🎯 Action_Center'!$H$2:$H$50, "OPEN", '🎯 Action_Center'!$G$2:$G$50, "")=0 -> TRUE | G91: =IF(D91=E91, "🟢 PASS", "🔴 FAIL") -> 🟢 PASS | H91: Есть открытые задачи без назначенного куратора. | I91: Назначить ответственного в Action_Center!G.
A92: T-86 | B92: Операционный контур | C92: Action_Center: Наличие дедлайнов задач | D92: =COUNTIF('🎯 Action_Center'!$J$2:$J$50, ">0")=COUNTA('🎯 Action_Center'!$J$2:$J$50) -> TRUE | E92: TRUE | F92: =COUNTIF('🎯 Action_Center'!$J$2:$J$50, ">0")=COUNTA('🎯 Action_Center'!$J$2:$J$50) -> TRUE | G92: =IF(D92=E92, "🟢 PASS", "🔴 FAIL") -> 🟢 PASS | H92: Обнаружены задачи без дедлайна. | I92: Заполнить колонку Action_Center!J.
A93: T-87 | B93: Воронка & SLA | C93: SLA_Matrix: Положительность нормативов времени перехода | D93: =MIN('⏱️ SLA_Matrix'!$D$2:$D$6)>0 -> TRUE | E93: TRUE | F93: =MIN('⏱️ SLA_Matrix'!$D$2:$D$6)>0 -> TRUE | G93: =IF(D93=E93, "🟢 PASS", "🔴 FAIL") -> 🟢 PASS | H93: Норматив SLA равен нулю или отрицателен. | I93: Проверить колонку D в SLA_Matrix.
A94: T-88 | B94: Воронка & SLA | C94: SLA_Matrix: Положительность порогов эскалации L1/L2 | D94: =COUNTIF('⏱️ SLA_Matrix'!$F$2:$F$6, ">0")=COUNTA('⏱️ SLA_Matrix'!$F$2:$F$6) -> TRUE | E94: TRUE | F94: =COUNTIF('⏱️ SLA_Matrix'!$F$2:$F$6, ">0")=COUNTA('⏱️ SLA_Matrix'!$F$2:$F$6) -> TRUE | G94: =IF(D94=E94, "🟢 PASS", "🔴 FAIL") -> 🟢 PASS | H94: Порог эскалации не задан. | I94: Заполнить колонку F в SLA_Matrix.
A95: T-89 | B95: История стадий & Log | C95: Deal_Event_Log: Уникальность event_id (EVT-NNN) | D95: =COUNTIF('📅 Deal_Event_Log'!$A$2:$A$100, "EVT*")=COUNTA('📅 Deal_Event_Log'!$A$2:$A$100) -> TRUE | E95: TRUE | F95: =COUNTIF('📅 Deal_Event_Log'!$A$2:$A$100, "EVT*")=COUNTA('📅 Deal_Event_Log'!$A$2:$A$100) -> TRUE | G95: =IF(D95=E95, "🟢 PASS", "🔴 FAIL") -> 🟢 PASS | H95: Дубликаты event_id в журнале событий. | I95: Проверить Deal_Event_Log!A.
A96: T-90 | B96: История стадий & Log | C96: Deal_Event_Log: Ссылочная целостность deal_id | D96: =COUNTIF('📅 Deal_Event_Log'!$B$2:$B$100, "D-*")=COUNTA('📅 Deal_Event_Log'!$B$2:$B$100) -> TRUE | E96: TRUE | F96: =COUNTIF('📅 Deal_Event_Log'!$B$2:$B$100, "D-*")=COUNTA('📅 Deal_Event_Log'!$B$2:$B$100) -> TRUE | G96: =IF(D96=E96, "🟢 PASS", "🔴 FAIL") -> 🟢 PASS | H96: События ссылаются на некорректный deal_id. | I96: Проверить deal_id в Deal_Event_Log!B.
A97: T-91 | B97: История стадий & Log | C97: Stage_History: Неотрицательность длительности в этапе | D97: =MIN('📊 Stage_History'!$E$2:$E$100)>=0 -> TRUE | E97: TRUE | F97: =MIN('📊 Stage_History'!$E$2:$E$100)>=0 -> TRUE | G97: =IF(D97=E97, "🟢 PASS", "🔴 FAIL") -> 🟢 PASS | H97: Отрицательная длительность этапа в Stage_History. | I97: Проверить формулу E в Stage_History.
A98: T-92 | B98: История стадий & Log | C98: Stage_History: Валидность deal_id | D98: =COUNTIF('📊 Stage_History'!$A$2:$A$100, "D-*")=COUNTA('📊 Stage_History'!$A$2:$A$100) -> TRUE | E98: TRUE | F98: =COUNTIF('📊 Stage_History'!$A$2:$A$100, "D-*")=COUNTA('📊 Stage_History'!$A$2:$A$100) -> TRUE | G98: =IF(D98=E98, "🟢 PASS", "🔴 FAIL") -> 🟢 PASS | H98: Некорректный deal_id в Stage_History. | I98: Проверить колонку B в Stage_History.
A99: T-93 | B99: Data Contract | C99: Data_Contract: Реестр контрактных правил (>= 54 полей) | D99: =COUNTA('📋 Data_Contract'!$B$2:$B$100)>=54 -> TRUE | E99: TRUE | F99: =COUNTA('📋 Data_Contract'!$B$2:$B$100)>=54 -> TRUE | G99: =IF(D99=E99, "🟢 PASS", "🔴 FAIL") -> 🟢 PASS | H99: Количество описанных контрактных полей менее 54. | I99: Дополнить правила в Data_Contract.
A100: T-94 | B100: Data Contract | C100: ID_Registry: Уникальность и валидность префиксов Universal ID | D100: =COUNTIF('🆔 ID_Registry'!$B$2:$B$9, "*-*")=COUNTA('🆔 ID_Registry'!$B$2:$B$9) -> TRUE | E100: TRUE | F100: =COUNTIF('🆔 ID_Registry'!$B$2:$B$9, "*-*")=COUNTA('🆔 ID_Registry'!$B$2:$B$9) -> TRUE | G100: =IF(D100=E100, "🟢 PASS", "🔴 FAIL") -> 🟢 PASS | H100: Некорректный префикс сущности в ID_Registry. | I100: Проверить ID_Registry!A.
A101: T-95 | B101: Executive Дайджест | C101: Executive_OnePager: Сходимость факта выручки с calc_engine | D101: ='📄 Executive_OnePager'!$A$5=calc_engine!$B$19 -> TRUE | E101: TRUE | F101: ='📄 Executive_OnePager'!$A$5=calc_engine!$B$19 -> TRUE | G101: =IF(D101=E101, "🟢 PASS", "🔴 FAIL") -> 🟢 PASS | H101: Расхождение выручки между Executive_OnePager и calc_engine. | I101: Синхронизировать OnePager!A5.
...

Sheet 💳 Финансы_и_AI_Дожим
A1: 💳 ФИНАНСОВЫЙ КОНТУР, REVERSE ETL И АГЕНТНЫЙ AI-ДОЖИМ (V17.6 BLOCK I)
A3: Фактический Cash-In | B3: Ожидаемый Cash-In (30д) | C3: Дебиторка (Pending AR) | D3: Просрочено (Overdue) | E3: DSO (Срок оплаты) | F3: Потенциал AI-дожима
A4: =calc_engine!B144 -> 1650000 | B4: =calc_engine!B147 -> 4075000 | C4: =calc_engine!B145 -> 0 | D4: =calc_engine!B146 -> 330000 | E4: =calc_engine!B148 & " дн." -> 6 дн. | F4: =calc_engine!B154 -> 1000000
A6: 📅 1. ПЛАТЕЖНЫЙ КАЛЕНДАРЬ И КОНТРОЛЬ ДЕБИТОРСКОЙ ЗАДОЛЖЕННОСТИ (CASH FLOW 30–60 ДНЕЙ)
A7: № Счета | B7: Сделка | C7: Контрагент | D7: Срок оплаты | E7: Сумма, ₽ | F7: Статус инвойса | G7: Просрочка, дн | H7: Финансовый риск | I7: Регламент финотдела
A8: =raw_invoices!A2 -> INV-201 | B8: =raw_invoices!B2 -> D-101 | C8: =raw_invoices!D2 -> ООО "Альфа Трейд" | D8: =raw_invoices!F2 -> 46277 | E8: =raw_invoices!G2 -> 450000 | F8: =raw_invoices!H2 -> paid | G8: =raw_invoices!J2 -> 0 | H8: =IF(raw_invoices!H2="overdue", "🔴 ВЫСОКИЙ РИСК (ПРОСРОЧКА)", IF(raw_invoices!H2="forecast", "🟡 В ПЛАНЕ (FORECAST)", IF(raw_invoices!H2="paid", "🟢 ОПЛАЧЕНО", "⚪ ИНФО"))) -> 🟢 ОПЛАЧЕНО | I8: =IF(F8="overdue", "Претензия + автозвонок РОПа", IF(F8="pending", "Контроль оплаты бухгалтерией", "Поступление зафиксировано")) -> Поступление зафиксировано
A9: =raw_invoices!A3 -> INV-202 | B9: =raw_invoices!B3 -> D-102 | C9: =raw_invoices!D3 -> АО "Северсталь Ресурс" | D9: =raw_invoices!F3 -> 46281 | E9: =raw_invoices!G3 -> 1200000 | F9: =raw_invoices!H3 -> paid | G9: =raw_invoices!J3 -> 0 | H9: =IF(raw_invoices!H3="overdue", "🔴 ВЫСОКИЙ РИСК (ПРОСРОЧКА)", IF(raw_invoices!H3="forecast", "🟡 В ПЛАНЕ (FORECAST)", IF(raw_invoices!H3="paid", "🟢 ОПЛАЧЕНО", "⚪ ИНФО"))) -> 🟢 ОПЛАЧЕНО | I9: =IF(F9="overdue", "Претензия + автозвонок РОПа", IF(F9="pending", "Контроль оплаты бухгалтерией", "Поступление зафиксировано")) -> Поступление зафиксировано
A10: =raw_invoices!A4 -> INV-203 | B10: =raw_invoices!B4 -> D-103 | C10: =raw_invoices!D4 -> ИП Смирнов О.В. | D10: =raw_invoices!F4 -> 46285 | E10: =raw_invoices!G4 -> 150000 | F10: =raw_invoices!H4 -> overdue | G10: =raw_invoices!J4 -> 9 | H10: =IF(raw_invoices!H4="overdue", "🔴 ВЫСОКИЙ РИСК (ПРОСРОЧКА)", IF(raw_invoices!H4="forecast", "🟡 В ПЛАНЕ (FORECAST)", IF(raw_invoices!H4="paid", "🟢 ОПЛАЧЕНО", "⚪ ИНФО"))) -> 🔴 ВЫСОКИЙ РИСК (ПРОСРОЧКА) | I10: =IF(F10="overdue", "Претензия + автозвонок РОПа", IF(F10="pending", "Контроль оплаты бухгалтерией", "Поступление зафиксировано")) -> Претензия + автозвонок РОПа
A11: =raw_invoices!A5 -> INV-204 | B11: =raw_invoices!B5 -> D-104 | C11: =raw_invoices!D5 -> ООО "Вектор Плюс" | D11: =raw_invoices!F5 -> 46293 | E11: =raw_invoices!G5 -> 850000 | F11: =raw_invoices!H5 -> forecast | G11: =raw_invoices!J5 -> 1 | H11: =IF(raw_invoices!H5="overdue", "🔴 ВЫСОКИЙ РИСК (ПРОСРОЧКА)", IF(raw_invoices!H5="forecast", "🟡 В ПЛАНЕ (FORECAST)", IF(raw_invoices!H5="paid", "🟢 ОПЛАЧЕНО", "⚪ ИНФО"))) -> 🟡 В ПЛАНЕ (FORECAST) | I11: =IF(F11="overdue", "Претензия + автозвонок РОПа", IF(F11="pending", "Контроль оплаты бухгалтерией", "Поступление зафиксировано")) -> Поступление зафиксировано
A12: =raw_invoices!A6 -> INV-205 | B12: =raw_invoices!B6 -> D-105 | C12: =raw_invoices!D6 -> ООО "Глобал Инвест" | D12: =raw_invoices!F6 -> 46300 | E12: =raw_invoices!G6 -> 3000000 | F12: =raw_invoices!H6 -> forecast | G12: =raw_invoices!J6 -> 0 | H12: =IF(raw_invoices!H6="overdue", "🔴 ВЫСОКИЙ РИСК (ПРОСРОЧКА)", IF(raw_invoices!H6="forecast", "🟡 В ПЛАНЕ (FORECAST)", IF(raw_invoices!H6="paid", "🟢 ОПЛАЧЕНО", "⚪ ИНФО"))) -> 🟡 В ПЛАНЕ (FORECAST) | I12: =IF(F12="overdue", "Претензия + автозвонок РОПа", IF(F12="pending", "Контроль оплаты бухгалтерией", "Поступление зафиксировано")) -> Поступление зафиксировано
A13: =raw_invoices!A7 -> INV-206 | B13: =raw_invoices!B7 -> D-101 | C13: =raw_invoices!D7 -> ООО "Альфа Трейд" | D13: =raw_invoices!F7 -> 46307 | E13: =raw_invoices!G7 -> 75000 | F13: =raw_invoices!H7 -> forecast | G13: =raw_invoices!J7 -> 0 | H13: =IF(raw_invoices!H7="overdue", "🔴 ВЫСОКИЙ РИСК (ПРОСРОЧКА)", IF(raw_invoices!H7="forecast", "🟡 В ПЛАНЕ (FORECAST)", IF(raw_invoices!H7="paid", "🟢 ОПЛАЧЕНО", "⚪ ИНФО"))) -> 🟡 В ПЛАНЕ (FORECAST) | I13: =IF(F13="overdue", "Претензия + автозвонок РОПа", IF(F13="pending", "Контроль оплаты бухгалтерией", "Поступление зафиксировано")) -> Поступление зафиксировано
A14: =raw_invoices!A8 -> INV-207 | B14: =raw_invoices!B8 -> D-102 | C14: =raw_invoices!D8 -> АО "Северсталь Ресурс" | D14: =raw_invoices!F8 -> 46311 | E14: =raw_invoices!G8 -> 150000 | F14: =raw_invoices!H8 -> forecast | G14: =raw_invoices!J8 -> 0 | H14: =IF(raw_invoices!H8="overdue", "🔴 ВЫСОКИЙ РИСК (ПРОСРОЧКА)", IF(raw_invoices!H8="forecast", "🟡 В ПЛАНЕ (FORECAST)", IF(raw_invoices!H8="paid", "🟢 ОПЛАЧЕНО", "⚪ ИНФО"))) -> 🟡 В ПЛАНЕ (FORECAST)
A15: =raw_invoices!A9 -> INV-208
A16: ID Сделки | B16: Клиент | C16: Пайплайн, ₽ | D16: Текущий куратор | E16: Действие Reverse ETL | F16: Новый исполнитель CRM | G16: Статус синхронизации | H16: API Payload | I16: Команда оператора
A17: D-105 | B17: ООО "Глобал Инвест" | C17: 3000000 | D17: Иванов Дмитрий (РОП) | E17: Снятие перегруза РОПа (P0) | F17: Петров Александр (КАМ) | G17: ⚡ ГОТОВО К ПУШУ | H17: {"deal_id":"D-105","manager_id":102} | I17: Отправить в CRM
A18: D-104 | B18: ООО "Вектор Плюс" | C18: 850000 | D18: Иванов Дмитрий (РОП) | E18: Сохранение VIP-кураторства | F18: Иванов Дмитрий (РОП) | G18: ✅ В СИНХРОНЕ | H18: {"deal_id":"D-104","manager_id":101} | I18: Синхронизировано
A19: D-103 | B19: ИП Смирнов О.В. | C19: 150000 | D19: Сидоров Роман (SDR) | E19: Дожим оплаты инвойса | F19: Сидоров Роман (SDR) | G19: ✅ В СИНХРОНЕ | H19: {"deal_id":"D-103","stage_id":5} | I19: Синхронизировано
A21: 🤖 3. АГЕНТНЫЙ AI-ДОЖИМ ОТКАЗНИКОВ (AGENTIC LOSS RECOVERY & TRANSCRIPT SYNTHESIS)
A22: ID Сделки | B22: Отказник | C22: Потерянный чек | D22: Код срыва | E22: Суть ошибки по транскрипту LLM | F22: Персонализированный AI-оффер дожима | G22: Канал касания | H22: Шанс возврата | I22: Статус AI Агента
A23: D-109 | B23: ООО "ПромКомплект" | C23: 600000 | D23: L1 (Дорого) | E23: Срыв контакта в звонке C-505 (2 балла): прямой спор по цене | F23: Оффер "Enterprise Lite": разбивка платежа на 3 транша по 200 000 ₽ + аудит процессов в подарок | G23: WhatsApp Business API | H23: 0.5 | I23: 🚀 В ОЧЕРЕДИ ОТПРАВКИ
A24: D-110 | B24: ЗАО "ТехноМаш" | C24: 400000 | D24: L2 (Конкурент) | E24: Не сформирована ценность интеграции, уход к альтернативе | F24: Кейс-сравнение с конкурентом: окупаемость за 1.0 мес + персональная сессия с техническим директором | G24: Email + звонок РОПа | H24: 0.35 | I24: ⚡ ТРЕБУЕТ АППРУВА РОПА

Sheet raw_invoices
A1: invoice_id | B1: deal_id | C1: client_id | D1: client_name | E1: issue_date | F1: due_date | G1: amount | H1: status | I1: paid_date | J1: overdue_days | K1: synced_at | Z1: data_snapshot_date | AA1: data_version | AB1: uploaded_by | AC1: upload_hash
A2: INV-201 | B2: D-101 | C2: ga_11 | D2: ООО "Альфа Трейд" | E2: 46267 | F2: 46277 | G2: 450000 | H2: paid | I2: 46277 | J2: =IF(A2="","", IF(AND(H2<>"", H2="paid"), 0, IF(ISBLANK(F2), 0, IF(calc_engine!$B$1>IF(ISNUMBER(F2), F2, DATEVALUE(F2)), calc_engine!$B$1-IF(ISNUMBER(F2), F2, DATEVALUE(F2)), 0)))) -> 0 | K2: 46286
A3: INV-202 | B3: D-102 | C3: ga_12 | D3: АО "Северсталь Ресурс" | E3: 46269 | F3: 46281 | G3: 1200000 | H3: paid | I3: 46281 | J3: =IF(A3="","", IF(AND(H3<>"", H3="paid"), 0, IF(ISBLANK(F3), 0, IF(calc_engine!$B$1>IF(ISNUMBER(F3), F3, DATEVALUE(F3)), calc_engine!$B$1-IF(ISNUMBER(F3), F3, DATEVALUE(F3)), 0)))) -> 0 | K3: 46286
A4: INV-203 | B4: D-103 | C4: ga_13 | D4: ИП Смирнов О.В. | E4: 46275 | F4: 46285 | G4: 150000 | H4: overdue | J4: =IF(A4="","", IF(AND(H4<>"", H4="paid"), 0, IF(ISBLANK(F4), 0, IF(calc_engine!$B$1>IF(ISNUMBER(F4), F4, DATEVALUE(F4)), calc_engine!$B$1-IF(ISNUMBER(F4), F4, DATEVALUE(F4)), 0)))) -> 9 | K4: 46286
A5: INV-204 | B5: D-104 | C5: ga_14 | D5: ООО "Вектор Плюс" | E5: 46283 | F5: 46293 | G5: 850000 | H5: forecast | J5: =IF(A5="","", IF(AND(H5<>"", H5="paid"), 0, IF(ISBLANK(F5), 0, IF(calc_engine!$B$1>IF(ISNUMBER(F5), F5, DATEVALUE(F5)), calc_engine!$B$1-IF(ISNUMBER(F5), F5, DATEVALUE(F5)), 0)))) -> 1 | K5: 46286
A6: INV-205 | B6: D-105 | C6: ga_15 | D6: ООО "Глобал Инвест" | E6: 46285 | F6: 46300 | G6: 3000000 | H6: forecast | J6: =IF(A6="","", IF(AND(H6<>"", H6="paid"), 0, IF(ISBLANK(F6), 0, IF(calc_engine!$B$1>IF(ISNUMBER(F6), F6, DATEVALUE(F6)), calc_engine!$B$1-IF(ISNUMBER(F6), F6, DATEVALUE(F6)), 0)))) -> 0 | K6: 46286
A7: INV-206 | B7: D-101 | C7: ga_11 | D7: ООО "Альфа Трейд" | E7: 46290 | F7: 46307 | G7: 75000 | H7: forecast | J7: =IF(A7="","", IF(AND(H7<>"", H7="paid"), 0, IF(ISBLANK(F7), 0, IF(calc_engine!$B$1>IF(ISNUMBER(F7), F7, DATEVALUE(F7)), calc_engine!$B$1-IF(ISNUMBER(F7), F7, DATEVALUE(F7)), 0)))) -> 0 | K7: 46286
A8: INV-207 | B8: D-102 | C8: ga_12 | D8: АО "Северсталь Ресурс" | E8: 46290 | F8: 46311 | G8: 150000 | H8: forecast | J8: =IF(A8="","", IF(AND(H8<>"", H8="paid"), 0, IF(ISBLANK(F8), 0, IF(calc_engine!$B$1>IF(ISNUMBER(F8), F8, DATEVALUE(F8)), calc_engine!$B$1-IF(ISNUMBER(F8), F8, DATEVALUE(F8)), 0)))) -> 0 | K8: 46286
A9: INV-208 | B9: D-099 | C9: ga_08 | D9: ООО "ПромСбыт" | E9: 46244 | F9: 46259 | G9: 180000 | H9: overdue | J9: =IF(A9="","", IF(AND(H9<>"", H9="paid"), 0, IF(ISBLANK(F9), 0, IF(calc_engine!$B$1>IF(ISNUMBER(F9), F9, DATEVALUE(F9)), calc_engine!$B$1-IF(ISNUMBER(F9), F9, DATEVALUE(F9)), 0)))) -> 35 | K9: 46286

Sheet 👥 Мотивация_ОП
A1: 👥 СИСТЕМА ДИНАМИЧЕСКОЙ МОТИВАЦИИ И PAYROLL ОП (REVOPS V17.6 BLOCK II)
A3: Общий фонд оплаты труда (ФОТ) | B3: Окладная часть | C3: Бонусная часть (Commissions) | D3: Средний чек бонуса | E3: Удержано за брак речи | F3: Доля ФОТ в выручке компании
A4: =SUM(calc_engine!$H$172:$H$174) -> 401050 | B4: =SUM(calc_engine!$C$172:$C$174) -> 320000 | C4: =A4 - B4 -> 81050 | D4: =C4 / MAX(COUNTA(calc_engine!$B$172:$B$174), 1) -> 27016.667 | E4: =calc_engine!D173 * calc_engine!E173 * (1 - calc_engine!G173) -> 6750 | F4: =A4 / calc_engine!$B$19 -> 0.24306061
A6: 📋 РАСЧЕТНАЯ ВЕДОМОСТЬ НАЧИСЛЕНИЯ ПРЕМИЙ С ПРИВЯЗКОЙ К SLA И КАЧЕСТВУ ДИАЛОГОВ
A7: Сотрудник | B7: Роль | C7: Оклад, ₽ | D7: Закрыто Won, ₽ | E7: Базовый % | F7: Коэфф. SLA | G7: Коэфф. речи (ИИ) | H7: Итого на руки, ₽ | I7: Статус начисления / Корректировки
A8: =calc_engine!B172 -> Иванов Дмитрий (РОП) | B8: РОП / Team Lead | C8: =calc_engine!C172 -> 150000 | D8: =calc_engine!D172 -> 1200000 | E8: =calc_engine!E172 -> 0.03 | F8: =calc_engine!F172 -> 1 | G8: =calc_engine!G172 -> 1.05 | H8: =calc_engine!H172 -> 187800 | I8: 🟢 Бонус за личные закрытия + надбавка речи (+5%)
A9: =calc_engine!B173 -> Петров Александр (КАМ) | B9: КАМ (Enterprise) | C9: =calc_engine!C173 -> 100000 | D9: =calc_engine!D173 -> 450000 | E9: =calc_engine!E173 -> 0.05 | F9: =calc_engine!F173 -> 1 | G9: =calc_engine!G173 -> 0.7 | H9: =calc_engine!H173 -> 115750 | I9: 🔴 ДЕПРЕМИРОВАНИЕ (-30% бонуса за срыв звонков C-503/C-505)
A10: =calc_engine!B174 -> Сидоров Роман (SDR) | B10: SDR (Квалификация) | C10: =calc_engine!C174 -> 70000 | D10: =calc_engine!D174 -> 0 | E10: =calc_engine!E174 -> 0 | F10: =calc_engine!F174 -> 1 | G10: =calc_engine!G174 -> 1.1 | H10: =calc_engine!H174 -> 97500 | I10: 🟢 Премия за квалификацию + надбавка речи (+10%)
A11: ИТОГО ФОТ: | C11: =SUM(C8:C10) -> 320000 | D11: =SUM(D8:D10) -> 1650000 | H11: =SUM(H8:H10) -> 401050
A13: 💡 ПРАВИЛО РЕВОПС: При среднем балле звонков менеджера ниже 9.0 из 13 (лист «🎙️ ИИ_Аудит»), переменная часть бонуса автоматически дисконтируется на 30%.

Sheet 🔮 Симулятор_Роста
A1: 🔮 СЦЕНАРНЫЙ СИМУЛЯТОР ВЫРУЧКИ И МАСШТАБИРОВАНИЯ (WHAT-IF REVENUE SANDBOX V17.6)
A2: ⚡ Интерактивное моделирование изменения рекламных бюджетов, конверсий воронки и найма менеджеров без риска повреждения боевых формул.
A3: 🎛️ ВЫБОР ПРЕСЕТА СЦЕНАРИЯ: | C3: 2. Базовый (+30% бюджет, +3% CR, +1 КАМ)
A4: 🎛️ 1. ВВОД ГИПОТЕЗ РОСТА (РЫЧАГИ МАСШТАБИРОВАНИЯ) | F4: 📊 2. ФИНАНСОВЫЙ ЭФФЕКТ СЦЕНАРИЯ (TO-BE ПРОГНОЗ)
A5: Параметр гипотезы | B5: Базовое значение (As-Is) | C5: Сценарная дельта (Ввод) | D5: Новый сценарный уровень | F5: Финансовая метрика | G5: Факт сейчас (As-Is) | H5: Прогноз сценария (To-Be) | I5: Прирост выручки / Прибыли
A6: Рекламный бюджет в месяц | B6: =calc_engine!B62 -> 240000 | C6: =IF(ISNUMBER(SEARCH("Консервативный",$C$3)), 0.15, IF(ISNUMBER(SEARCH("Базовый",$C$3)), 0.3, IF(ISNUMBER(SEARCH("Агрессивный",$C$3)), 0.5, 0.5))) -> 0.3 | D6: =B6 * (1 + C6) -> 312000 | F6: Входящий поток лидов | G6: =calc_engine!E2 -> 11 | H6: =ROUND(G6 * (1 + C6),0) -> 14 | I6: =H6 - G6 -> 3
A7: Конверсия закрытия воронки (CR) | B7: =calc_engine!$B$24 -> 0.5 | C7: =IF(ISNUMBER(SEARCH("Консервативный",$C$3)), 0.02, IF(ISNUMBER(SEARCH("Базовый",$C$3)), 0.03, IF(ISNUMBER(SEARCH("Агрессивный",$C$3)), 0.05, 0.05))) -> 0.03 | D7: =B7 + C7 -> 0.53 | F7: Закрытых сделок за месяц | G7: =calc_engine!$B$22 -> 2 | H7: =ROUND(H6 * D7,0) -> 7 | I7: =H7 - G7 -> 5
A8: Расширение штата КАМов (чел) | B8: =1 -> 1 | C8: =IF(ISNUMBER(SEARCH("Консервативный",$C$3)), 0, IF(ISNUMBER(SEARCH("Базовый",$C$3)), 1, IF(ISNUMBER(SEARCH("Агрессивный",$C$3)), 2, 1))) -> 1 | D8: =B8 + C8 -> 2 | F8: Прогнозная выручка месяца | G8: =calc_engine!$B$19 -> 1650000 | H8: =H7 * calc_engine!$B$21 -> 5775000 | I8: =H8 - G8 -> 4125000
A9: Плановое снижение брака звонков | B9: =calc_engine!$B$31 -> 0.82051282 | C9: =IF(ISNUMBER(SEARCH("Консервативный",$C$3)), 0.05, IF(ISNUMBER(SEARCH("Базовый",$C$3)), 0.1, IF(ISNUMBER(SEARCH("Агрессивный",$C$3)), 0.15, 0.15))) -> 0.1 | D9: =B9 * (1 - C9) -> 0.73846154 | F9: Выполнение плана (от 5 млн ₽) | G9: =G8 / '⚙️ Настройки'!$B$9 -> 0.33 | H9: =H8 / '⚙️ Настройки'!$B$9 -> 1.155 | I9: =H9 - G9 -> 0.825
A12: ="🎯 ВЕРДИКТ СИМУЛЯТОРА: При изменении маркетинга на " & TEXT(C6, "+0.0%") & " и росте конверсии на " & TEXT(C7, "+0.0%") & ", выручка вырастет с " & TEXT(G8, "#,##0 ₽") & " до " & TEXT(H8, "#,##0 ₽") & " (" & TEXT(I8, "+#,##0 ₽") & " к кассе), обеспечив " & TEXT(H9, "0.0%") & " выполнения месячного плана!" -> 🎯 ВЕРДИКТ СИМУЛЯТОРА: При изменении маркетинга на +30.0% и росте конверсии на +3.0%, выручка вырастет с 1,650,000 ₽ до 5,775,000 ₽ (+4,125,000 ₽ к кассе), обеспечив 115.5% выполнения месячного плана!
A13: 🎲 ПРЕДИКТИВНЫЙ КОРИДОР ВЫРУЧКИ МОНТЕ-КАРЛО (ВЕРОЯТНОСТЬ 95%)
A14: Метрика Монте-Карло | B14: Значение, ₽ | C14: Доверительный интервал | D14: Вероятность | E14: Статус выполнения плана | F14: Рекомендация ИИ
A15: Пессимистичный порог (P10 - 90% защита): | B15: =calc_simulator!B10 -> 3230796 | C15: Коридор уверенности 95% | D15: ="90% гарантия (" & TEXT(calc_simulator!B10, "#,##0 ₽") & ")" -> 90% гарантия (3,230,796 ₽) | E15: 🟢 Касса защищена | F15: Базовые обязательства закрыты
A16: Медианное ожидание кассы (P50): | B16: =calc_simulator!B11 -> 4187250 | C16: Наиболее вероятный итог | D16: ="50% медиана (" & TEXT(calc_simulator!B11, "#,##0 ₽") & ")" -> 50% медиана (4,187,250 ₽) | E16: 🟡 В шаге от плана | F16: Требуется дожим 2 сделок из Пульта РОПа
A17: Оптимистичный таргет (P90 с ИИ-дожимом): | B17: =calc_simulator!B12 -> 5013195 | C17: С учетом реанимации базы | D17: ="Таргет с ИИ (" & TEXT(calc_simulator!B12, "#,##0 ₽") & ")" -> Таргет с ИИ (5,013,195 ₽) | E17: 🚀 План 5.0M взят! | F17: Запуск автодожима по отказникам L1-L4
A18: Вероятность выполнения плана 5 000 000 ₽: | B18: =calc_simulator!B13 -> 0.72 | C18: Сводная вероятность | D18: =calc_simulator!B14 -> 🟢 ВЫСОКАЯ ВЕРОЯТНОСТЬ | E18: План: 5 000 000 ₽ | F18: Фокус РОПа: перехват сделки D-104

Sheet 🗄️ DWH_и_Безопасность
A1: 🗄️ ENTERPRISE БЕЗОПАСНОСТЬ (RBAC), ЖУРНАЛ АУДИТА И DWH МОСТ (V17.6 MASTER)
A2: 📄 1. One-Pager | B2: ⚡ 2. Пульс компании | C2: 📋 3. Пульт РОПа | D2: 💸 4. 7 Грехов ОП | E2: 🎯 5. Action Center | F2: 🎙️ 6. ИИ-Аудит | G2: ⚡ 7. Экспресс 3 цифры | H2: 🧪 8. QA Suite | I2: ⚙️ 9. Настройки
A3: Статус DWH-моста | B3: Архивировано в ClickHouse | C3: Сделок в оперативной памяти | D3: Инцидентов безопасности | E3: Защита ПДн (PII Masking) | F3: Статус QA-валидации
A4: 🟢 CONNECTED (n8n ⇄ ClickHouse) | B4: 48250 | C4: =COUNTIF(raw_deals!$A$2:$A1000, "?*") -> 11 | D4: 0 инцидентов | E4: 🛡️ RBAC АКТИВЕН | F4: ✅ PASS 100% (45 листов)
A6: 🛡️ 1. МАТРИЦА РОЛЕВОГО ДОСТУПА И ЗАЩИТЫ КОММЕРЧЕСКИХ ДАННЫХ (RBAC PROTOCOL)
A7: Роль пользователя | B7: Сотрудники | C7: Доступ к витринам | D7: Доступ к raw-листам | E7: Видимость ПДн (Телефоны/ФИО) | F7: Права на скидки и тарифы | G7: Доступ к кассе и Cash Flow | H7: Статус защищенности
A8: Суперадмин / CEO | B8: Руководство компании | C8: Полный (Все 43 листа) | D8: Полный (Чтение / Запись) | E8: 100% Открыто | F8: Утверждение регламентов | G8: Полный доступ | H8: 🟢 ВЛАДЕЛЕЦ
A9: РОП (Head of Sales) | B9: Иванов Дмитрий | C9: Дашборды ОП, Аудит, Воронка | D9: Ограниченный (Только ОП) | E9: 100% Открыто | F9: Вилка до 15% | G9: Только факт оплат | H9: 🟢 АВТОРИЗОВАН
A10: КАМ / SDR (Sales) | B10: Петров А., Сидоров Р. | C10: Личный пайплайн, Задачи | D10: Запрещен (Только CRM) | E10: 🔒 МАСКИРОВАНО (Хеш) | F10: Запрещено | G10: Запрещено | H10: 🛡️ ОГРАНИЧЕН
A11: Внешний подрядчик | B11: Агентство трафика | C11: Только «Маркетинг & Трафик» | D11: Только raw_marketing | E11: 🔒 СКРЫТО 100% | F11: Запрещено | G11: Запрещено | H11: 🛡️ ИЗОЛИРОВАН
A14: ⚡ 2. АРХИТЕКТУРА ВЫГРУЗКИ В DWH (DATA MARTS & STORAGE TIERING)
A15: Слой данных | B15: Целевое хранилище | C15: Объем записей | D15: Частота репликации | E15: Задержка (Latency) | F15: Архитектурная функция | G15: BI-подключение | H15: Статус синхронизации
A16: Hot Layer (Оперативный) | B16: Google Sheets SSOT | C16: До 2 000 строк (90 дней) | D16: В реальном времени (Webhooks) | E16: < 1.5 сек | F16: Интерфейс РОПа и оперативные расчеты | G16: Google Looker Studio | H16: 🟢 РАБОТАЕТ
A17: Warm / Cold (Архив DWH) | B17: ClickHouse Enterprise | C17: 50 000+ сделок (Архив M0-M36) | D17: Пакетно каждые 6 часов | E17: < 5 мин | F17: Глубокая аналитика LTV и когорт NRR | G17: Power BI / Superset | H17: ⚡ АКТИВНО (n8n ready)
A18: Security Vault (ПДн) | B18: PostgreSQL Encrypted | C18: Зашифрованные профили клиентов | D18: По событию создания лида | E18: < 2.0 сек | F18: Хранение персональных данных по 152-ФЗ | G18: Защищенный бэкенд | H18: 🔒 ЗАШИФРОВАНО
A21: 📋 3. ЖУРНАЛ АУДИТА ОПЕРАЦИЙ (LIVE SECURITY & COMPLIANCE FEED)
A22: ID события | B22: Время инцидента | C22: Инициатор (Email) | D22: Объект изменения | E22: Тип действия | F22: Поле | G22: Было | H22: Стало | I22: Статус безопасности
A23: =raw_audit_log!A2 -> EV-901 | B23: =TEXT(raw_audit_log!B2,"YYYY-MM-DD HH:mm:ss") -> 2026-09-20 18:45:44 | C23: =raw_audit_log!C2 -> etl-service@n8n.internal | D23: =raw_audit_log!D2 -> raw_deals | E23: =raw_audit_log!E2 -> REVERSE_ETL_UPDATE | F23: =raw_audit_log!G2 -> manager_id | G23: =raw_audit_log!H2 -> 101 | H23: =raw_audit_log!I2 -> 102 | I23: =raw_audit_log!K2 -> SUCCESS
A24: =raw_audit_log!A3 -> EV-902 | B24: =TEXT(raw_audit_log!B3,"YYYY-MM-DD HH:mm:ss") -> 2026-09-21 00:45:44 | C24: =raw_audit_log!C3 -> finance@revops-platform.io | D24: =raw_audit_log!D3 -> raw_invoices | E24: =raw_audit_log!E3 -> INVOICE_STATUS_CHANGE | F24: =raw_audit_log!G3 -> status | G24: =raw_audit_log!H3 -> pending | H24: =raw_audit_log!I3 -> overdue | I24: =raw_audit_log!K3 -> SUCCESS
A25: =raw_audit_log!A4 -> EV-903 | B25: =TEXT(raw_audit_log!B4,"YYYY-MM-DD HH:mm:ss") -> 2026-09-21 06:45:44 | C25: =raw_audit_log!C4 -> sec-admin@revops-platform.io | D25: =raw_audit_log!D4 -> calc_engine | E25: =raw_audit_log!E4 -> SCHEMA_EXPANSION | F25: =raw_audit_log!G4 -> BLOCK_II_PAYROLL | G25: =raw_audit_log!H4 -> N/A | H25: =raw_audit_log!I4 -> ACTIVE | I25: =raw_audit_log!K4 -> PROTECTED
A26: =raw_audit_log!A5 -> EV-904 | B26: =TEXT(raw_audit_log!B5,"YYYY-MM-DD HH:mm:ss") -> 2026-09-21 16:45:44 | C26: =raw_audit_log!C5 -> sec-admin@revops-platform.io | D26: =raw_audit_log!D5 -> raw_deals | E26: =raw_audit_log!E5 -> PII_MASKING_APPLIED | F26: =raw_audit_log!G5 -> client_name | G26: =raw_audit_log!H5 -> ClearText | H26: =raw_audit_log!I5 -> SHA256_Hashed | I26: =raw_audit_log!K5 -> RESTRICTED
A55: 43 | B55: 📄 Executive_OnePager | C55: Презентационный | D55: CEO / Собственник | E55: 1

Sheet 🌐 Сквозная_RevOps_Аналитика
A1: 🌐 СКВОЗНАЯ REVOPS-СИСТЕМА: ОТ ПЕРВОГО КЛИКА ДО ПОВТОРНЫХ ПРОДАЖ (LTV)
A2: =HYPERLINK("#gid=777000101","💸 ДИАГНОСТИКА УТЕЧЕК") & " | " & HYPERLINK("#gid=1847360667","⚡ Пульс") & " | " & HYPERLINK("#gid=1005455422","🎯 Воронка") & " | " & HYPERLINK("#gid=1716977957","🌐 Маркетинг") & " | " & HYPERLINK("#gid=34927252","💳 Финансы") & " | " & HYPERLINK("#gid=120000002","👥 Команда") & " | " & HYPERLINK("#gid=1808346887","🔮 Симулятор") & " | " & HYPERLINK("#gid=1689499688","🚨 Радар") & " | " & HYPERLINK("#gid=985355776","⚙️ Настройки") -> 💸 ДИАГНОСТИКА УТЕЧЕК | ⚡ Пульс | 🎯 Воронка | 🌐 Маркетинг | 💳 Финансы | 👥 Команда | 🔮 Симулятор | 🚨 Радар | ⚙️ Настройки | B2: 📈 Когорты LTV & Retention | C2: 👥 Ресурсный План ОП | D2: 🌐 Маркетинг & Атрибуция | E2: 🎯 Воронка & SLA | F2: 📊 Юнит-Экономика | G2: 🎙️ ИИ-Аудит речи | H2: 🚨 Радар алертов | I2: 📋 Реестр задач
A3: Сквозной ROMI | B3: Sales Velocity / мес | C3: Индекс SLA | D3: Ср. балл речи | E3: Next Step % | F3: Нагрузка на РОПа | G3: Win Rate | H3: Честный CAC | I3: LTV клиента
A4: =IFERROR((calc_engine!B19 - SUM(raw_marketing!$E$2:$E1000))/MAX(SUM(raw_marketing!$E$2:$E1000), 1), 0) -> 5.875 | B4: =calc_engine!B28 -> 6750000 | C4: =calc_engine!B31 -> 0.82051282 | D4: =calc_engine!B32 -> 9.5 | E4: =calc_engine!B33 -> 0.66666667 | F4: =calc_engine!B35 -> 0.4 | G4: =calc_engine!B24 -> 0.5 | H4: =calc_engine!B37 -> 120000 | I4: =calc_engine!B38 -> 1060000
A6: 🔄 1. СКВОЗНОЙ ПАЙПЛАЙН: ПРЕВРАЩЕНИЕ ТРАФИКА В ЧИСТУЮ ВЫРУЧКУ
A7: Этап сквозного цикла | B7: Кол-во событий | C7: Объем капитала | D7: Конверсия шага (CR) | E7: Сквозной CR | F7: Норматив SLA | G7: Факт SLA | H7: Статус узла
A8: 1. Входящий трафик (Лиды) | B8: =SUM(raw_marketing!$H$2:$H1000) -> 103 | C8: =SUM(raw_marketing!$E$2:$E1000) -> 240000 | D8: 1 | E8: 1 | F8: ='🎯 Воронка_и_SLA'!D4 -> 24 ч | G8: ='🎯 Воронка_и_SLA'!E4 -> 0.0 ч | H8: ='🎯 Воронка_и_SLA'!F4 -> 🟢 В НОРМЕ
A9: 2. Квалификация и звонки | B9: =calc_engine!B3 -> 1 | C9: =calc_engine!C3 -> 120000 | D9: =IFERROR(B9/MAX(B8,1),0) -> 0.0097087379 | E9: =IFERROR(B9/MAX($B$8,1),0) -> 0.0097087379 | F9: ='🎯 Воронка_и_SLA'!D5 -> 48 ч | G9: ='🎯 Воронка_и_SLA'!E5 -> 24.0 ч | H9: ='🎯 Воронка_и_SLA'!F5 -> 🟢 В НОРМЕ
A10: 3. Проведено встреч / Демо | B10: =calc_engine!B4 -> 1 | C10: =calc_engine!C4 -> 280000 | D10: =IFERROR(B10/MAX(B9,1),0) -> 1 | E10: =IFERROR(B10/MAX($B$8,1),0) -> 0.0097087379 | F10: ='🎯 Воронка_и_SLA'!D6 -> 120 ч | G10: ='🎯 Воронка_и_SLA'!E6 -> 72.0 ч | H10: ='🎯 Воронка_и_SLA'!F6 -> 🟢 В НОРМЕ
A11: 4. КП и согласование договора | B11: =calc_engine!B5 -> 2 | C11: =calc_engine!C5 -> 3850000 | D11: =IFERROR(B11/MAX(B10,1),0) -> 2 | E11: =IFERROR(B11/MAX($B$8,1),0) -> 0.019417476 | F11: ='🎯 Воронка_и_SLA'!D7 -> 48 ч | G11: ='🎯 Воронка_и_SLA'!E7 -> 312.0 ч | H11: ='🎯 Воронка_и_SLA'!F7 -> ⚠️ ПРОСРОЧЕН
A12: 5. Счета на оплате | B12: =calc_engine!B6 -> 2 | C12: =calc_engine!C6 -> 330000 | D12: =IFERROR(B12/MAX(B11,1),0) -> 1 | E12: =IFERROR(B12/MAX($B$8,1),0) -> 0.019417476 | F12: ='🎯 Воронка_и_SLA'!D8 -> 72 ч | G12: ='🎯 Воронка_и_SLA'!E8 -> 708.0 ч | H12: ='🎯 Воронка_и_SLA'!F8 -> ⚠️ ПРОСРОЧЕН
A13: 6. Оплачено (Closed-Won) | B13: =calc_engine!B22 -> 2 | C13: =calc_engine!B19 -> 1650000 | D13: =IFERROR(B13/MAX(B12,1),0) -> 1 | E13: =IFERROR(B13/MAX($B$8,1),0) -> 0.019417476 | F13: ='🎯 Воронка_и_SLA'!D9 -> — | G13: =calc_engine!B25 & " дн" -> 11 дн | H13: 🟢 ВЫРУЧКА
A15: 👥 2. КОМАНДА: КОРРЕЛЯЦИЯ КАЧЕСТВА ДИАЛОГОВ И ВЫРУЧКИ
A16: ID CRM | B16: Сотрудник | C16: Роль | D16: Сделок в работе | E16: Пайплайн, ₽ | F16: Звонков | G16: Ср. балл речи | H16: Next Step % | I16: Выручка (Факт) | J16: Загрузка емкости | K16: Решение РОПа
A17: 101 | B17: Иванов Дмитрий (РОП) | C17: ROP | D17: =calc_engine!D43 -> 1 | E17: =calc_engine!E43 -> 850000 | F17: =calc_engine!F43 -> 1 | G17: =calc_engine!G43 -> 11 | H17: =calc_engine!H43 -> 1 | I17: =SUMIFS(raw_deals!$C$2:$C1000, raw_deals!$H$2:$H1000, 101, raw_deals!$D$2:$D1000, 6) -> 1200000 | J17: =IFERROR(D17/VLOOKUP(A17, '⚙️ Настройки'!$A$21:$D$23, 4, FALSE), 0) -> 0.2 | K17: =IF(AND(C17="ROP", J17>0.7), "🔴 ДЕЛЕГИРОВАТЬ НА КАМ", IF(G17<9, "⚠️ ТРЕНИНГ СКРИПТА", IF(J17>1, "🔴 ПЕРЕГРУЗ", "🟢 В НОРМЕ"))) -> 🟢 В НОРМЕ
A18: 102 | B18: Петров Александр (КАМ) | C18: KAM | D18: =calc_engine!D44 -> 2 | E18: =calc_engine!E44 -> 3280000 | F18: =calc_engine!F44 -> 3 | G18: =calc_engine!G44 -> 7 | H18: =calc_engine!H44 -> 0.33333333 | I18: =SUMIFS(raw_deals!$C$2:$C1000, raw_deals!$H$2:$H1000, 102, raw_deals!$D$2:$D1000, 6) -> 450000 | J18: =IFERROR(D18/VLOOKUP(A18, '⚙️ Настройки'!$A$21:$D$23, 4, FALSE), 0) -> 0.08 | K18: =IF(AND(C18="ROP", J18>0.7), "🔴 ДЕЛЕГИРОВАТЬ НА КАМ", IF(G18<9, "⚠️ ТРЕНИНГ СКРИПТА", IF(J18>1, "🔴 ПЕРЕГРУЗ", "🟢 В НОРМЕ"))) -> ⚠️ ТРЕНИНГ СКРИПТА
A19: 103 | B19: Сидоров Роман (SDR) | C19: SDR | D19: =calc_engine!D45 -> 4 | E19: =calc_engine!E45 -> 1400000 | F19: =calc_engine!F45 -> 2 | G19: =calc_engine!G45 -> 12.5 | H19: =calc_engine!H45 -> 1 | I19: =SUMIFS(raw_deals!$C$2:$C1000, raw_deals!$H$2:$H1000, 103, raw_deals!$D$2:$D1000, 6) -> 0 | J19: =IFERROR(D19/VLOOKUP(A19, '⚙️ Настройки'!$A$21:$D$23, 4, FALSE), 0) -> 0.1 | K19: =IF(AND(C19="ROP", J19>0.7), "🔴 ДЕЛЕГИРОВАТЬ НА КАМ", IF(G19<9, "⚠️ ТРЕНИНГ СКРИПТА", IF(J19>1, "🔴 ПЕРЕГРУЗ", "🟢 В НОРМЕ"))) -> 🟢 В НОРМЕ
A22: 🧲 3. СКВОЗНАЯ МОНЕТИЗАЦИЯ СРЫВОВ И РЕАКТИВАЦИЯ ОТКАЗНИКОВ (L1–L4)
A23: Код | B23: Барьер клиента | C23: Срывов, шт | D23: Списано потерь, ₽ | E23: Вероятность возврата | F23: Потенциал выручки, ₽ | G23: Сценарий дожима
A24: L1 | B24: =VLOOKUP(A24, '⚙️ Настройки'!$A$26:$C$29, 2, FALSE) -> Дорого / нет бюджета | C24: =calc_engine!C74 -> 1 | D24: =calc_engine!D74 -> 600000 | E24: =VLOOKUP(A24, '⚙️ Настройки'!$A$26:$C$29, 3, FALSE) -> 0.5 | F24: =D24*E24 -> 300000 | G24: 📲 Автодожим: спецпредложение Lite + рассрочка
A25: L2 | B25: =VLOOKUP(A25, '⚙️ Настройки'!$A$26:$C$29, 2, FALSE) -> Выбрали конкурента | C25: =calc_engine!C75 -> 1 | D25: =calc_engine!D75 -> 400000 | E25: =VLOOKUP(A25, '⚙️ Настройки'!$A$26:$C$29, 3, FALSE) -> 0.35 | F25: =D25*E25 -> 140000 | G25: 📊 Сравнит. матрица преимуществ + звонок РОПа
A26: L3 | B26: =VLOOKUP(A26, '⚙️ Настройки'!$A$26:$C$29, 2, FALSE) -> Не формат / нет потребности | C26: =calc_engine!C76 -> 0 | D26: =calc_engine!D76 -> 0 | E26: =VLOOKUP(A26, '⚙️ Настройки'!$A$26:$C$29, 3, FALSE) -> 0.1 | F26: =D26*E26 -> 0 | G26: 📩 Дайджест кейсов ниши раз в месяц
A27: L4 | B27: =VLOOKUP(A27, '⚙️ Настройки'!$A$26:$C$29, 2, FALSE) -> Потеря контакта / недозвон | C27: =calc_engine!C77 -> 0 | D27: =calc_engine!D77 -> 0 | E27: =VLOOKUP(A27, '⚙️ Настройки'!$A$26:$C$29, 3, FALSE) -> 0.2 | F27: =D27*E27 -> 0 | G27: 🤖 Автоматический звонок бота + пуш в WhatsApp
A28: ИТОГО РЕЗЕРВ: | F28: =SUM(F24:F27) -> 440000 | G28: 🔥 Деньги, возвращаемые в пайплайн без расходов на маркетинг

Sheet 🌐 Маркетинг_и_Трафик
A1: 🌐 МАРКЕТИНГ И ТРАФИК: CLOSED-LOOP ATTRIBUTION & КАМПАНИИ
A3: Маркетинговый бюджет | B3: Всего лидов (CPL) | C3: Квалиф. лиды (CPQL) | D3: Оплачено сделок | E3: Выручка Won | F3: Сквозной ROMI | G3: CAC (Факт)
A4: =SUMIFS(raw_marketing!$E$2:$E1000, raw_marketing!$A$2:$A1000, ">="&'⚙️ Настройки'!$B$6, raw_marketing!$A$2:$A1000, "<="&'⚙️ Настройки'!$B$7) -> 0 | B4: =SUMIFS(raw_marketing!$H$2:$H1000, raw_marketing!$A$2:$A1000, ">="&'⚙️ Настройки'!$B$6, raw_marketing!$A$2:$A1000, "<="&'⚙️ Настройки'!$B$7) -> 0 | C4: =COUNTIFS(raw_deals!$D$2:$D1000, ">=2", raw_deals!$D$2:$D1000, "<=6", raw_deals!$G$2:$G1000, ">="&'⚙️ Настройки'!$B$6, raw_deals!$G$2:$G1000, "<="&'⚙️ Настройки'!$B$7) -> 0 | D4: =COUNTIFS(raw_deals!$O$2:$O1000, TRUE, raw_deals!$G$2:$G1000, ">="&'⚙️ Настройки'!$B$6, raw_deals!$G$2:$G1000, "<="&'⚙️ Настройки'!$B$7) -> 0 | E4: =SUMIFS(raw_deals!$C$2:$C1000, raw_deals!$O$2:$O1000, TRUE, raw_deals!$G$2:$G1000, ">="&'⚙️ Настройки'!$B$6, raw_deals!$G$2:$G1000, "<="&'⚙️ Настройки'!$B$7) -> 0 | F4: =IFERROR((E4-A4)/MAX(A4,1), 0) -> 0 | G4: =IFERROR(A4/MAX(D4,1), 0) -> 0
A6: 📊 ЭФФЕКТИВНОСТЬ РЕКЛАМНЫХ КАМПАНИЙ И СВЯЗОК
A7: Канал трафика | B7: Кампания | C7: Расход, ₽ | D7: Клики | E7: Лиды | F7: CPL, ₽ | G7: Оплаты | H7: Выручка, ₽ | I7: ROMI | J7: Действие алгоритма
A8: Яндекс Директ | B8: Контекст B2B | C8: =calc_engine!B132 -> 120000 | D8: =SUMIFS(raw_marketing!$F$2:$F1000, raw_marketing!$B$2:$B1000, A8) -> 1850 | E8: =SUMIFS(raw_marketing!$H$2:$H1000, raw_marketing!$B$2:$B1000, A8) -> 48 | F8: =IFERROR(C8/MAX(E8,1), 0) -> 2500 | G8: =COUNTIFS(raw_touchpoints!$E$2:$E$1000, A8, raw_touchpoints!$J$2:$J$1000, TRUE) -> 2 | H8: =calc_engine!E132 -> 495000 | I8: =IFERROR((H8-C8)/MAX(C8,1), 0) -> 3.125 | J8: =IF(C8=0,"⏳ НЕТ ЗАТРАТ",IF(I8>=3,"🚀 МАСШТАБИРОВАТЬ (+50%)",IF(I8>0,"🟢 В НОРМЕ (W-SHAPED)",IF(C8>50000,"🔴 СТОП","🟡 ОПТИМИЗАЦИЯ")))) -> 🚀 МАСШТАБИРОВАТЬ (+50%)
A9: Контур.Фокус | B9: Парсинг Опт | C9: =calc_engine!B133 -> 35000 | D9: =SUMIFS(raw_marketing!$F$2:$F1000, raw_marketing!$B$2:$B1000, A9) -> 620 | E9: =SUMIFS(raw_marketing!$H$2:$H1000, raw_marketing!$B$2:$B1000, A9) -> 24 | F9: =IFERROR(C9/MAX(E9,1), 0) -> 1458.3333 | G9: =COUNTIFS(raw_touchpoints!$E$2:$E$1000, A9, raw_touchpoints!$J$2:$J$1000, TRUE) -> 3 | H9: =calc_engine!E133 -> 840000 | I9: =IFERROR((H9-C9)/MAX(C9,1), 0) -> 23 | J9: =IF(C9=0,"⏳ НЕТ ЗАТРАТ",IF(I9>=3,"🚀 МАСШТАБИРОВАТЬ (+50%)",IF(I9>0,"🟢 В НОРМЕ (W-SHAPED)",IF(C9>50000,"🔴 СТОП","🟡 ОПТИМИЗАЦИЯ")))) -> 🚀 МАСШТАБИРОВАТЬ (+50%)
A10: Google Ads | B10: Поиск Бренд | C10: =calc_engine!B134 -> 85000 | D10: =SUMIFS(raw_marketing!$F$2:$F1000, raw_marketing!$B$2:$B1000, A10) -> 1100 | E10: =SUMIFS(raw_marketing!$H$2:$H1000, raw_marketing!$B$2:$B1000, A10) -> 31 | F10: =IFERROR(C10/MAX(E10,1), 0) -> 2741.9355 | G10: =COUNTIFS(raw_touchpoints!$E$2:$E$1000, A10, raw_touchpoints!$J$2:$J$1000, TRUE) -> 1 | H10: =calc_engine!E134 -> 135000 | I10: =IFERROR((H10-C10)/MAX(C10,1), 0) -> 0.58823529 | J10: =IF(C10=0,"⏳ НЕТ ЗАТРАТ",IF(I10>=3,"🚀 МАСШТАБИРОВАТЬ (+50%)",IF(I10>0,"🟢 В НОРМЕ (W-SHAPED)",IF(C10>50000,"🔴 СТОП","🟡 ОПТИМИЗАЦИЯ")))) -> 🟢 В НОРМЕ (W-SHAPED)
A12: 🔀 2. МУЛЬТИКАНАЛЬНАЯ АТРИБУЦИЯ: СРАВНЕНИЕ FIRST-TOUCH И LAST-TOUCH
A13: Канал привлечения | B13: Расход, ₽ | C13: First-Touch Лиды | D13: FT Оплаты Won | E13: FT Выручка, ₽ | F13: Last-Touch Лиды | G13: LT Оплаты Won | H13: LT Выручка, ₽ | I13: Δ (FT - LT) | J13: Роль канала в цикле сделки
A14: Яндекс Директ | B14: =SUMIF(raw_marketing!$B$2:$B1000, "Яндекс Директ", raw_marketing!$E$2:$E1000) -> 120000 | C14: =COUNTIFS(raw_deals!$J$2:$J1000, "Яндекс Директ") -> 4 | D14: =COUNTIFS(raw_deals!$J$2:$J1000, "Яндекс Директ", raw_deals!$D$2:$D1000, 6) -> 1 | E14: =SUMIFS(raw_deals!$C$2:$C1000, raw_deals!$J$2:$J1000, "Яндекс Директ", raw_deals!$D$2:$D1000, 6) -> 450000 | F14: =COUNTIFS(raw_deals!$U$2:$U1000, "yandex") -> 4 | G14: =COUNTIFS(raw_deals!$U$2:$U1000, "yandex", raw_deals!$D$2:$D1000, 6) -> 1 | H14: =SUMIFS(raw_deals!$C$2:$C1000, raw_deals!$U$2:$U1000, "yandex", raw_deals!$D$2:$D1000, 6) -> 450000 | I14: =E14-H14 -> 0 | J14: 🎯 Сбалансированный (стабильный генератор)
A15: Контур.Фокус | B15: =SUMIF(raw_marketing!$B$2:$B1000, "Контур.Фокус", raw_marketing!$E$2:$E1000) -> 35000 | C15: =COUNTIFS(raw_deals!$J$2:$J1000, "Контур.Фокус") -> 3 | D15: =COUNTIFS(raw_deals!$J$2:$J1000, "Контур.Фокус", raw_deals!$D$2:$D1000, 6) -> 1 | E15: =SUMIFS(raw_deals!$C$2:$C1000, raw_deals!$J$2:$J1000, "Контур.Фокус", raw_deals!$D$2:$D1000, 6) -> 1200000 | F15: =COUNTIFS(raw_deals!$U$2:$U1000, "kontur") -> 3 | G15: =COUNTIFS(raw_deals!$U$2:$U1000, "kontur", raw_deals!$D$2:$D1000, 6) -> 1 | H15: =SUMIFS(raw_deals!$C$2:$C1000, raw_deals!$U$2:$U1000, "kontur", raw_deals!$D$2:$D1000, 6) -> 1200000 | I15: =E15-H15 -> 0 | J15: 🚀 Лидер ROI (высокий чек Enterprise)
A16: Google Ads | B16: =SUMIF(raw_marketing!$B$2:$B1000, "Google Ads", raw_marketing!$E$2:$E1000) -> 85000 | C16: =COUNTIFS(raw_deals!$J$2:$J1000, "Google Ads") -> 2 | D16: =COUNTIFS(raw_deals!$J$2:$J1000, "Google Ads", raw_deals!$D$2:$D1000, 6) -> 0 | E16: =SUMIFS(raw_deals!$C$2:$C1000, raw_deals!$J$2:$J1000, "Google Ads", raw_deals!$D$2:$D1000, 6) -> 0 | F16: =COUNTIFS(raw_deals!$U$2:$U1000, "google") -> 2 | G16: =COUNTIFS(raw_deals!$U$2:$U1000, "google", raw_deals!$D$2:$D1000, 6) -> 0 | H16: =SUMIFS(raw_deals!$C$2:$C1000, raw_deals!$U$2:$U1000, "google", raw_deals!$D$2:$D1000, 6) -> 0 | I16: =E16-H16 -> 0 | J16: 🔴 Утечка бюджета (нет финализации)
A17: Партнеры и Рефералы | B17: 0 | C17: =COUNTIFS(raw_deals!$J$2:$J1000, "Партнеры") -> 1 | D17: =COUNTIFS(raw_deals!$J$2:$J1000, "Партнеры", raw_deals!$D$2:$D1000, 6) -> 0 | E17: =SUMIFS(raw_deals!$C$2:$C1000, raw_deals!$J$2:$J1000, "Партнеры", raw_deals!$D$2:$D1000, 6) -> 0 | F17: =COUNTIFS(raw_deals!$U$2:$U1000, "partner") -> 1 | G17: =COUNTIFS(raw_deals!$U$2:$U1000, "partner", raw_deals!$D$2:$D1000, 6) -> 0 | H17: =SUMIFS(raw_deals!$C$2:$C1000, raw_deals!$U$2:$U1000, "partner", raw_deals!$D$2:$D1000, 6) -> 0 | I17: =E17-H17 -> 0 | J17: 💎 Стратегический пайплайн (3.0M в работе)
A18: Органика SEO | B18: 0 | C18: =COUNTIFS(raw_deals!$J$2:$J1000, "Органика SEO") -> 1 | D18: =COUNTIFS(raw_deals!$J$2:$J1000, "Органика SEO", raw_deals!$D$2:$D1000, 6) -> 0 | E18: =SUMIFS(raw_deals!$C$2:$C1000, raw_deals!$J$2:$J1000, "Органика SEO", raw_deals!$D$2:$D1000, 6) -> 0 | F18: =COUNTIFS(raw_deals!$U$2:$U1000, "organic") -> 1 | G18: =COUNTIFS(raw_deals!$U$2:$U1000, "organic", raw_deals!$D$2:$D1000, 6) -> 0 | H18: =SUMIFS(raw_deals!$C$2:$C1000, raw_deals!$U$2:$U1000, "organic", raw_deals!$D$2:$D1000, 6) -> 0 | I18: =E18-H18 -> 0 | J18: 🌱 Бесплатный охват (накопительный эффект)
A19: ИТОГО АТРИБУЦИЯ | B19: =SUM(B14:B18) -> 240000 | C19: =SUM(C14:C18) -> 11 | D19: =SUM(D14:D18) -> 2 | E19: =SUM(E14:E18) -> 1650000 | F19: =SUM(F14:F18) -> 11 | G19: =SUM(G14:G18) -> 2 | H19: =SUM(H14:H18) -> 1650000 | I19: =SUM(I14:I18) -> 0 | J19: ✅ 100% согласованность моделей
A21: 📐 3. ЮНИТ-КАЛЬКУЛЯТОР ПРЕДЕЛЬНОГО CPL/CAC И АЛГОРИТМИЧЕСКИЕ ДЕЙСТВИЯ
A22: Канал трафика | B22: Средний чек (AOV) | C22: CR Лид → Сделка | D22: Целевой LTV/CAC | E22: Предельный CAC | F22: Предельный CPL | G22: Факт CPL | H22: Факт CAC | I22: Запас рентабельности | J22: Алгоритмическое решение RevOps
A23: Яндекс Директ | B23: =IFERROR(H8/MAX(G8,1),450000) -> 247500 | C23: =IFERROR(G8/MAX(E8,1),0.02) -> 0.041666667 | D23: 3 | E23: =B23*0.7/D23 -> 57750 | F23: =E23*C23 -> 2406.25 | G23: =F8 -> 2500 | H23: =IFERROR(C8/MAX(G8,1),C8) -> 60000 | I23: =IFERROR((E23-H23)/E23, 0) -> -0.038961039 | J23: =IF(H23<=E23, "🟢 УДЕРЖИВАТЬ В НОРМЕ", "🔴 ОПТИМИЗИРОВАТЬ СВЯЗКУ") -> 🔴 ОПТИМИЗИРОВАТЬ СВЯЗКУ
A24: Контур.Фокус | B24: =IFERROR(H9/MAX(G9,1),1200000) -> 280000 | C24: =IFERROR(G9/MAX(E9,1),0.04) -> 0.125 | D24: 3 | E24: =B24*0.7/D24 -> 65333.333 | F24: =E24*C24 -> 8166.6667 | G24: =F9 -> 1458.3333 | H24: =IFERROR(C9/MAX(G9,1),C9) -> 11666.667 | I24: =IFERROR((E24-H24)/E24, 0) -> 0.82142857 | J24: =IF(H24<=E24, "🚀 МАСШТАБИРОВАТЬ (+50% БЮДЖЕТА)", "🟡 СНИЗИТЬ СТАВКУ") -> 🚀 МАСШТАБИРОВАТЬ (+50% БЮДЖЕТА)
A25: Google Ads | B25: =IFERROR(H10/MAX(G10,1), 0) -> 135000 | C25: =IFERROR(G10/MAX(E10,1), 0) -> 0.032258065 | D25: 3 | E25: 150000 | F25: 2000 | G25: =F10 -> 2741.9355 | H25: =IFERROR(C10/MAX(G10,1),C10) -> 85000 | I25: =IFERROR((E25-H25)/E25, -1) -> 0.43333333 | J25: =IF(G10=0, "🔴 ОТКЛЮЧИТЬ КАНАЛ (СЛИВ БЮДЖЕТА)", "🟡 ТЕСТ") -> 🟡 ТЕСТ
A26: СВОДНЫЙ РЕЗУЛЬТАТ | B26: =AVERAGE(B23:B24) -> 263750 | C26: =SUM(G8:G10)/SUM(E8:E10) -> 0.058252427 | D26: 3 | E26: =AVERAGE(E23:E25) -> 91027.778 | F26: =AVERAGE(F23:F25) -> 4190.9722 | G26: =AVERAGE(G23:G25) -> 2233.4229 | H26: =C4/MAX(D4,1) -> 0 | I26: =IFERROR((E26-H26)/E26, 0) -> 1 | J26: 🎯 Перераспределить 85 000 ₽ из Google в Контур

Sheet raw_audit_log
A1: event_id | B1: timestamp | C1: user_email | D1: target_sheet | E1: action_type | F1: record_id | G1: field_name | H1: old_value | I1: new_value | J1: security_level | K1: status
A2: EV-901 | B2: 46285.782 | C2: etl-service@n8n.internal | D2: raw_deals | E2: REVERSE_ETL_UPDATE | F2: D-105 | G2: manager_id | H2: 101 | I2: 102 | J2: INFO | K2: SUCCESS
A3: EV-902 | B3: 46286.032 | C3: finance@revops-platform.io | D3: raw_invoices | E3: INVOICE_STATUS_CHANGE | F3: INV-203 | G3: status | H3: pending | I3: overdue | J3: WARN | K3: SUCCESS
A4: EV-903 | B4: 46286.282 | C4: sec-admin@revops-platform.io | D4: calc_engine | E4: SCHEMA_EXPANSION | F4: ALL | G4: BLOCK_II_PAYROLL | H4: N/A | I4: ACTIVE | J4: SECURITY | K4: PROTECTED
A5: EV-904 | B5: 46286.698 | C5: sec-admin@revops-platform.io | D5: raw_deals | E5: PII_MASKING_APPLIED | F5: D-101..D-110 | G5: client_name | H5: ClearText | I5: SHA256_Hashed | J5: RBAC | K5: RESTRICTED
A6: EV-RBAC-778437 | B6: 46295.061 | C6: dmitriyfedotov1908@gmail.com | D6: ⚙️ Настройки | E6: ROLE_SWITCH | F6: B10 | G6: role | H6: (старт) | I6: undefined [MULTI_USER] [FALLBACK] | J6: RBAC | K6: SUCCESS
A7: EV-RBAC-923048 | B7: 46295.07 | C7: dmitriyfedotov1908@gmail.com | D7: ⚙️ Настройки | E7: ROLE_SWITCH | F7: B10 | G7: role | H7: (старт) | I7: 👑 CEO [MULTI_USER] | J7: RBAC | K7: SUCCESS

Sheet raw_marketing
A1: date | B1: channel | C1: campaign_id | D1: campaign_name | E1: spend | F1: clicks | G1: impressions | H1: leads | I1: synced_at | Z1: data_snapshot_date | AA1: data_version | AB1: uploaded_by | AC1: upload_hash
A2: 46284 | B2: Яндекс Директ | C2: cmp_yd | D2: Контекст B2B | E2: 120000 | F2: 1850 | G2: 42000 | H2: 48 | I2: 46285.472
A3: 46284 | B3: Контур.Фокус | C3: cmp_kf | D3: Парсинг Опт | E3: 35000 | F3: 620 | G3: 1200 | H3: 24 | I3: 46285.472
A4: 46284 | B4: Google Ads | C4: cmp_ga | D4: Поиск Бренд | E4: 85000 | F4: 1100 | G4: 28000 | H4: 31 | I4: 46285.472

Sheet raw_alerts
A1: timestamp | B1: priority | C1: trigger_name | D1: value | E1: threshold | F1: status | G1: resolution_days
A2: 46294.375 | B2: CRITICAL | C2: Брак диалога C-505 (Оценка 2/13, нет Next Step) | D2: 600000 | E2: Score < 9 | F2: OPEN | G2: 1
A3: 46294.375 | B3: CRITICAL | C3: Зависание сделки D-104 на КП > 48ч (12 дней) | D3: 850000 | E3: SLA > 48ч | F3: OPEN | G3: 2
A4: 46294.375 | B4: HIGH | C4: Просрочен счет INV-203 (ИП Смирнов, 9 дней) | D4: 150000 | E4: Due > 72ч | F4: OPEN | G4: 1
A5: 46294.375 | B5: HIGH | C5: Перегруз РОПа Иванова Д. (Лимит 5, факт 1) | D5: 850000 | E5: Capacity | F5: RESOLVED | G5: 0
A6: 46294.375 | B6: MEDIUM | C6: Срыв слота встречи C-503 (ООО СнабСервис) | D6: 280000 | E6: NextStep 0 | F6: OPEN | G6: 3

Sheet raw_payments
A1: payment_id | B1: deal_id | C1: client_id | D1: payment_date | E1: amount | F1: payment_type | G1: description | H1: synced_at | Z1: data_snapshot_date | AA1: data_version | AB1: uploaded_by | AC1: upload_hash
A2: PAY-1001 | B2: D-101 | C2: ga_11 | D2: 46277 | E2: 450000 | F2: initial | G2: Первичная оплата внедрения (M0) | H2: 46285.694
A3: PAY-1002 | B3: D-102 | C3: ga_12 | D3: 46281 | E3: 1200000 | F3: initial | G3: Контракт Enterprise Setup (M0) | H3: 46285.694
A4: PAY-1003 | B4: D-101 | C4: ga_11 | D4: 46307 | E4: 75000 | F4: retainer | G4: Ежемесячный RevOps-саппорт (M1) | H4: 46285.694
A5: PAY-1004 | B5: D-102 | C5: ga_12 | D5: 46311 | E5: 150000 | F5: retainer | G5: Техническая поддержка SLA (M1) | H5: 46285.694
A6: PAY-1005 | B6: D-101 | C6: ga_11 | D6: 46338 | E6: 95000 | F6: expansion | G6: Докупка лицензий телефонии (M2) | H6: 46285.694
A7: PAY-1006 | B7: D-102 | C7: ga_12 | D7: 46342 | E7: 150000 | F7: retainer | G7: Техническая поддержка SLA (M2) | H7: 46285.694

Sheet calc_engine
A1: SYSTEM_TODAY | B1: =DATE(2026, 9, 29) -> 46294 | P1: ='📊 Data_Quality'!C8 -> 1
A2: 1 | B2: =COUNTIF(raw_deals!$D$2:$D1000, 1) -> 1 | C2: =SUMIF(raw_deals!$D$2:$D1000, 1, raw_deals!$C$2:$C1000) -> 950000 | D2: =SUMIF(raw_deals!$D$2:$D1000, 1, raw_deals!$S$2:$S1000) -> 47500 | E2: =COUNTIF(raw_deals!$D$2:$D1000, ">=1") -> 11 | F2: =IFERROR(E3/MAX(E2,1), 0) -> 0.90909091 | G2: =IFERROR(E2/MAX($E$2,1), 0) -> 1 | P2: ='📊 Data_Quality'!C9 -> 🟢 EXCELLENT
A3: 2 | B3: =COUNTIF(raw_deals!$D$2:$D1000, 2) -> 1 | C3: =SUMIF(raw_deals!$D$2:$D1000, 2, raw_deals!$C$2:$C1000) -> 120000 | D3: =SUMIF(raw_deals!$D$2:$D1000, 2, raw_deals!$S$2:$S1000) -> 18000 | E3: =COUNTIF(raw_deals!$D$2:$D1000, ">=2") -> 10 | F3: =IFERROR(E4/MAX(E3,1), 0) -> 0.9 | G3: =IFERROR(E3/MAX($E$2,1), 0) -> 0.90909091
A4: 3 | B4: =COUNTIF(raw_deals!$D$2:$D1000, 3) -> 1 | C4: =SUMIF(raw_deals!$D$2:$D1000, 3, raw_deals!$C$2:$C1000) -> 280000 | D4: =SUMIF(raw_deals!$D$2:$D1000, 3, raw_deals!$S$2:$S1000) -> 98000 | E4: =COUNTIF(raw_deals!$D$2:$D1000, ">=3") -> 9 | F4: =IFERROR(E5/MAX(E4,1), 0) -> 0.88888889 | G4: =IFERROR(E4/MAX($E$2,1), 0) -> 0.81818182
A5: 4 | B5: =COUNTIF(raw_deals!$D$2:$D1000, 4) -> 2 | C5: =SUMIF(raw_deals!$D$2:$D1000, 4, raw_deals!$C$2:$C1000) -> 3850000 | D5: =SUMIF(raw_deals!$D$2:$D1000, 4, raw_deals!$S$2:$S1000) -> 2310000 | E5: =COUNTIF(raw_deals!$D$2:$D1000, ">=4") -> 8 | F5: =IFERROR(E6/MAX(E5,1), 0) -> 0.75 | G5: =IFERROR(E5/MAX($E$2,1), 0) -> 0.72727273
A6: 5 | B6: =COUNTIF(raw_deals!$D$2:$D1000, 5) -> 2 | C6: =SUMIF(raw_deals!$D$2:$D1000, 5, raw_deals!$C$2:$C1000) -> 330000 | D6: =SUMIF(raw_deals!$D$2:$D1000, 5, raw_deals!$S$2:$S1000) -> 280500 | E6: =COUNTIF(raw_deals!$D$2:$D1000, ">=5") -> 6 | F6: =IFERROR(E7/MAX(E6,1), 0) -> 0.33333333 | G6: =IFERROR(E6/MAX($E$2,1), 0) -> 0.54545455
A7: 6 | B7: =COUNTIF(raw_deals!$D$2:$D1000, 6) -> 2 | C7: =SUMIF(raw_deals!$D$2:$D1000, 6, raw_deals!$C$2:$C1000) -> 1650000 | D7: =SUMIF(raw_deals!$D$2:$D1000, 6, raw_deals!$S$2:$S1000) -> 1650000 | E7: =COUNTIF(raw_deals!$D$2:$D1000, 6) -> 2 | F7: — | G7: =IFERROR(E7/MAX($E$2,1), 0) -> 0.18181818
A8: 7 | B8: =COUNTIF(raw_deals!$D$2:$D1000, 7) -> 2 | C8: =SUMIF(raw_deals!$D$2:$D1000, 7, raw_deals!$C$2:$C1000) -> 1000000 | D8: =SUMIF(raw_deals!$D$2:$D1000, 7, raw_deals!$S$2:$S1000) -> 0 | E8: =COUNTIF(raw_deals!$D$2:$D1000, 7) -> 2 | F8: — | G8: =IFERROR(E8/MAX($E$2,1), 0) -> 0.18181818
A16: [МЕТРИКА] Сделок в работе (Active Pipeline Deals) | B16: =COUNTIF(raw_deals!$D$2:$D1000, "<=5") -> 7 | C16: Подсчет сделок на стадиях 1..5 воронки CRM
A17: [МЕТРИКА] Сумма активного пайплайна (Pipeline Amount, ₽) | B17: =SUMIF(raw_deals!$D$2:$D1000, "<=5", raw_deals!$C$2:$C1000) -> 5530000 | C17: Сумма бюджетов сделок в активной работе
A18: [МЕТРИКА] Взвешенный пайплайн (Weighted Pipeline, ₽) | B18: =SUMIF(raw_deals!$D$2:$D1000, "<=5", raw_deals!$S$2:$S1000) -> 2754000 | C18: Сумма взвешенных вероятностями бюджетов пайплайна
A19: [МЕТРИКА] Факт закрытой выручки (Closed Won Revenue, ₽) | B19: =SUMIF(raw_deals!$D$2:$D1000, 6, raw_deals!$C$2:$C1000) -> 1650000 | C19: Сумма бюджетов успешно выигранных сделок (стадия 6)
A20: [МЕТРИКА] Выполнение плана продаж (% Target) | B20: =IFERROR(B19/'⚙️ Настройки'!$B$9, 0) -> 0.33 | C20: Отношение факта выручки к месячному плану из Настроек
A21: [МЕТРИКА] Средний чек закрытой сделки (Average Deal Size, ₽) | B21: =IFERROR(B19/MAX(B22,1), 0) -> 825000 | C21: Факт выручки / Количество выигранных сделок (MAX 1)
A22: [МЕТРИКА] Количество выигранных сделок (Won Deals Count) | B22: =COUNTIF(raw_deals!$D$2:$D1000, 6) -> 2 | C22: Счетчик сделок на стадии 6 (Успешно реализовано)
A23: [МЕТРИКА] Количество проигранных сделок (Lost Deals Count) | B23: =COUNTIF(raw_deals!$D$2:$D1000, 7) -> 2 | C23: Счетчик сделок на стадии 7 (Закрыто и не реализовано)
A24: [МЕТРИКА] Конверсия закрытия воронки (Win Rate %) | B24: =IFERROR(B22/MAX(B22+B23,1), 0) -> 0.5 | C24: Конверсия: выигранные / (выигранные + проигранные)
A25: [МЕТРИКА] Средний цикл сделки, дни (Sales Cycle Days) | B25: =IFERROR(AVERAGEIFS(raw_deals!$T$2:$T1000, raw_deals!$D$2:$D1000, 6), 11) -> 11 | C25: Fallback: 11 дней (нормативный цикл B2B сделки)
A26: [МЕТРИКА] Активные сделки без зомби (Non-Zombie Pipeline) | B26: =COUNTIFS(raw_deals!$D$2:$D1000, "<=5", raw_deals!$R$2:$R1000, "<>zombie") -> 6 | C26: Активные сделки за вычетом зомби-когорты
A27: [МЕТРИКА] Скорость пайплайна в день (Pipeline Velocity / day, ₽) | B27: =IFERROR(B26*B21*B24/MAX(B25,1), 0) -> 225000 | C27: Формула скорости выручки: (Deals * AOV * WinRate) / Cycle
A28: [МЕТРИКА] Прогноз выручки на 30 дней (Pipeline Velocity / 30d, ₽) | B28: =B27*30 -> 6750000 | C28: Проекция суточной скорости пайплайна на 30 календарных дней
A29: [МЕТРИКА] Месячный Run-Rate прогноз (Run-Rate Forecast, ₽) | B29: =IFERROR((B19/MAX(DAY($B$1),1))*DAY(EOMONTH($B$1,0)), B19) -> 1706896.6 | C29: Экстраполяция текущего темпа продаж до конца месяца
A30: [МЕТРИКА] Факт + Взвешенный остаток (Fact + Weighted Pipeline, ₽) | B30: =B19+B18 -> 4404000 | C30: Консервативная сумма: закрытый факт + взвешенный остаток
A31: [МЕТРИКА] Соблюдение SLA этапов CRM (% SLA Compliance) | B31: =IFERROR(COUNTIF('📊 Stage_History'!$G$2:$G$1000, "🟢 В НОРМЕ") / MAX(COUNTA('📊 Stage_History'!$A$2:$A$1000), 1), 0.92) -> 0.82051282 | C31: Fallback: 0.92 (92% норматив соблюдения SLA стадий)
A32: [МЕТРИКА] Средний балл качества речи (Avg Speech Score) | B32: =IFERROR(AVERAGE(raw_calls!$T$2:$T1000), 9.5) -> 9.5 | C32: Fallback: 9.5 баллов (минимальный стандарт речи из 13)
A33: [МЕТРИКА] Доля звонков без брака (% Speech Quality Rate) | B33: =IFERROR(COUNTIF(raw_calls!$U$2:$U1000, TRUE)/MAX(COUNT(raw_calls!$T$2:$T1000),1), 0.67) -> 0.66666667 | C33: Fallback: 0.67 (67% отраслевой бенчмарк чистых звонков)
A34: [МЕТРИКА] Интегральный RevOps Health Score (0..1) | B34: =0.4*MIN(1,B20)+0.35*B31+0.25*IFERROR(B32/13,0) -> 0.60187179 | C34: Взвешенный индекс: 40% план + 35% SLA + 25% качество речи
A35: [МЕТРИКА] Утилизация емкости менеджера 101 (% Capacity) | B35: ='👥 Ресурсный_План'!$L$8 -> 0.4 | C35: Загрузка КАМа сделками относительно лимита из Настроек
A36: [МЕТРИКА] Стоимость привлечения лида CPL, ₽ (Cost Per Lead) | B36: =IFERROR(SUM(raw_marketing!$E$2:$E1000)/MAX(SUM(raw_marketing!$H$2:$H1000),1), 2330) -> 2330.0971 | C36: Fallback: 2330 ₽ (нормативная стоимость B2B лида)
A37: [МЕТРИКА] Стоимость привлечения клиента CAC, ₽ (Customer Acquisition Cost) | B37: =IFERROR(SUM(raw_marketing!$E$2:$E1000)/MAX(B22,1), 120000) -> 120000 | C37: Fallback: 120 000 ₽ (нормативная стоимость привлечения клиента)
A38: [МЕТРИКА] Жизненный цикл клиента LTV, ₽ (Customer Lifetime Value) | B38: =IFERROR(SUM(raw_payments!$E$2:$E1000)/MAX(B22,1), B21*1.2) -> 1060000 | C38: Расчетный LTV клиента с учетом повторных платежей
A39: [МЕТРИКА] Отношение LTV / CAC (Unit Economics Ratio) | B39: =IFERROR(B38/MAX(B37,1), 0) -> 8.8333333 | C39: Ключевое соотношение Unit-экономики (норматив >= 3.0)
A40: [МЕТРИКА] Доля CAC от среднего чека (CAC / AOV) | B40: =IFERROR(B37/MAX(B21,1), 0) -> 0.14545455 | C40: Доля маркетинговых затрат на клиента в среднем чеке
A41: [МЕТРИКА] Общее количество проанализированных звонков (Total Calls) | B41: =COUNT(raw_calls!$T$2:$T1000) -> 6 | C41: Счетчик оцененных звонков в сырой таблице телефонии
D43: =COUNTIFS(raw_deals!$H$2:$H1000, 101, raw_deals!$D$2:$D1000, "<=5") -> 1 | E43: =SUMIFS(raw_deals!$C$2:$C1000, raw_deals!$H$2:$H1000, 101, raw_deals!$D$2:$D1000, "<=5") -> 850000 | F43: =COUNTIF(raw_calls!$C$2:$C1000, 101) -> 1 | G43: =IFERROR(AVERAGEIFS(raw_calls!$T$2:$T1000, raw_calls!$C$2:$C1000, 101), 0) -> 11 | H43: =IFERROR(COUNTIFS(raw_calls!$C$2:$C1000, 101, raw_calls!$U$2:$U1000, TRUE)/MAX(F43,1), 0) -> 1 | I43: =IFERROR(D43/5, 0) -> 0.2
D44: =COUNTIFS(raw_deals!$H$2:$H1000, 102, raw_deals!$D$2:$D1000, "<=5") -> 2 | E44: =SUMIFS(raw_deals!$C$2:$C1000, raw_deals!$H$2:$H1000, 102, raw_deals!$D$2:$D1000, "<=5") -> 3280000 | F44: =COUNTIF(raw_calls!$C$2:$C1000, 102) -> 3 | G44: =IFERROR(AVERAGEIFS(raw_calls!$T$2:$T1000, raw_calls!$C$2:$C1000, 102), 0) -> 7 | H44: =IFERROR(COUNTIFS(raw_calls!$C$2:$C1000, 102, raw_calls!$U$2:$U1000, TRUE)/MAX(F44,1), 0) -> 0.33333333 | I44: =IFERROR(D44/25, 0) -> 0.08
D45: =COUNTIFS(raw_deals!$H$2:$H1000, 103, raw_deals!$D$2:$D1000, "<=5") -> 4 | E45: =SUMIFS(raw_deals!$C$2:$C1000, raw_deals!$H$2:$H1000, 103, raw_deals!$D$2:$D1000, "<=5") -> 1400000 | F45: =COUNTIF(raw_calls!$C$2:$C1000, 103) -> 2 | G45: =IFERROR(AVERAGEIFS(raw_calls!$T$2:$T1000, raw_calls!$C$2:$C1000, 103), 0) -> 12.5 | H45: =IFERROR(COUNTIFS(raw_calls!$C$2:$C1000, 103, raw_calls!$U$2:$U1000, TRUE)/MAX(F45,1), 0) -> 1 | I45: =IFERROR(D45/40, 0) -> 0.1
A50: 📊 АНАЛИЗ ПРИЧИН ОТКАЗОВ (LOSS CODES)
A51: Код | B51: Причина отказа | C51: Кол-во сделок | D51: Объем потерь, ₽ | E51: Вероятность реактивации
A52: L1 | B52: Дорого / нет бюджета | C52: =COUNTIF(raw_deals!$M$2:$M$1000,"L1") -> 1 | D52: =SUMIF(raw_deals!$M$2:$M$1000,"L1",raw_deals!$C$2:$C$1000) -> 600000 | E52: ='⚙️ Настройки'!C26 -> 0.5
A53: L2 | B53: Выбрали конкурента | C53: =COUNTIF(raw_deals!$M$2:$M$1000,"L2") -> 1 | D53: =SUMIF(raw_deals!$M$2:$M$1000,"L2",raw_deals!$C$2:$C$1000) -> 400000 | E53: ='⚙️ Настройки'!C27 -> 0.35
A54: L3 | B54: Не формат / нет потребности | C54: =COUNTIF(raw_deals!$M$2:$M$1000,"L3") -> 0 | D54: =SUMIF(raw_deals!$M$2:$M$1000,"L3",raw_deals!$C$2:$C$1000) -> 0 | E54: ='⚙️ Настройки'!C28 -> 0.1
A55: L4 | B55: Потеря контакта / недозвон | C55: =COUNTIF(raw_deals!$M$2:$M$1000,"L4") -> 0 | D55: =SUMIF(raw_deals!$M$2:$M$1000,"L4",raw_deals!$C$2:$C$1000) -> 0 | E55: ='⚙️ Настройки'!C29 -> 0.2
B56: ИТОГО потенциал реактивации: | C56: =SUM(C52:C55) -> 2 | D56: =SUMPRODUCT(D52:D55, E52:E55) -> 440000
A60: 📊 МАРКЕТИНГ И ТРАФИК (CONSOLIDATED CORE)
A61: Метрика | B61: Значение | C61: Формула / Источник | D61: Период | E61: Статус
A62: Маркетинговый бюджет (Total Spend) | B62: =SUM(raw_marketing!$E$2:$E$1000) -> 240000 | C62: raw_marketing!E | D62: Месяц | E62: Факт
A63: Входящих кликов (Total Clicks) | B63: =SUM(raw_marketing!$F$2:$F$1000) -> 3570 | C63: raw_marketing!F | D63: Месяц | E63: Факт
A64: Всего показов (Total Impressions) | B64: =SUM(raw_marketing!$G$2:$G$1000) -> 71200 | C64: raw_marketing!G | D64: Месяц | E64: Факт
A65: Всего лидов с рекламы (Ad Leads) | B65: =SUM(raw_marketing!$H$2:$H$1000) -> 103 | C65: raw_marketing!H | D65: Месяц | E65: Факт
B66: =COUNTIFS(raw_deals!$R$2:$R1000, "4-7", raw_deals!$D$2:$D1000, "<=5") -> 0 | C66: =SUMIFS(raw_deals!$C$2:$C1000, raw_deals!$R$2:$R1000, "4-7", raw_deals!$D$2:$D1000, "<=5") -> 0
B67: =COUNTIFS(raw_deals!$R$2:$R1000, "8-14", raw_deals!$D$2:$D1000, "<=5") -> 3 | C67: =SUMIFS(raw_deals!$C$2:$C1000, raw_deals!$R$2:$R1000, "8-14", raw_deals!$D$2:$D1000, "<=5") -> 4000000
B68: =COUNTIFS(raw_deals!$R$2:$R1000, "15-30", raw_deals!$D$2:$D1000, "<=5") -> 0 | C68: =SUMIFS(raw_deals!$C$2:$C1000, raw_deals!$R$2:$R1000, "15-30", raw_deals!$D$2:$D1000, "<=5") -> 0
B69: =COUNTIFS(raw_deals!$R$2:$R1000, "zombie", raw_deals!$D$2:$D1000, "<=5") -> 1 | C69: =SUMIFS(raw_deals!$C$2:$C1000, raw_deals!$R$2:$R1000, "zombie", raw_deals!$D$2:$D1000, "<=5") -> 180000
C74: =COUNTIFS(raw_deals!$M$2:$M1000, "L1", raw_deals!$D$2:$D1000, 7) -> 1 | D74: =SUMIFS(raw_deals!$C$2:$C1000, raw_deals!$M$2:$M1000, "L1", raw_deals!$D$2:$D1000, 7) -> 600000
C75: =COUNTIFS(raw_deals!$M$2:$M1000, "L2", raw_deals!$D$2:$D1000, 7) -> 1 | D75: =SUMIFS(raw_deals!$C$2:$C1000, raw_deals!$M$2:$M1000, "L2", raw_deals!$D$2:$D1000, 7) -> 400000
C76: =COUNTIFS(raw_deals!$M$2:$M1000, "L3", raw_deals!$D$2:$D1000, 7) -> 0 | D76: =SUMIFS(raw_deals!$C$2:$C1000, raw_deals!$M$2:$M1000, "L3", raw_deals!$D$2:$D1000, 7) -> 0
C77: =COUNTIFS(raw_deals!$M$2:$M1000, "L4", raw_deals!$D$2:$D1000, 7) -> 0 | D77: =SUMIFS(raw_deals!$C$2:$C1000, raw_deals!$M$2:$M1000, "L4", raw_deals!$D$2:$D1000, 7) -> 0
A85: Яндекс Директ | B85: =SUMIF(raw_marketing!$B$2:$B1000, $A85, raw_marketing!$E$2:$E1000) -> 120000 | C85: =SUMIF(raw_marketing!$B$2:$B1000, $A85, raw_marketing!$H$2:$H1000) -> 48 | D85: =SUMIFS(raw_deals!$C$2:$C1000, raw_deals!$J$2:$J1000, $A85, raw_deals!$D$2:$D1000, 6) -> 450000 | E85: =IFERROR(B85/MAX(C85,1), 0) -> 2500 | F85: =IFERROR((D85-B85)/MAX(B85,1), 0) -> 2.75
A86: Контур.Фокус | B86: =SUMIF(raw_marketing!$B$2:$B1000, $A86, raw_marketing!$E$2:$E1000) -> 35000 | C86: =SUMIF(raw_marketing!$B$2:$B1000, $A86, raw_marketing!$H$2:$H1000) -> 24 | D86: =SUMIFS(raw_deals!$C$2:$C1000, raw_deals!$J$2:$J1000, $A86, raw_deals!$D$2:$D1000, 6) -> 1200000 | E86: =IFERROR(B86/MAX(C86,1), 0) -> 1458.3333 | F86: =IFERROR((D86-B86)/MAX(B86,1), 0) -> 33.285714
A87: Google Ads | B87: =SUMIF(raw_marketing!$B$2:$B1000, $A87, raw_marketing!$E$2:$E1000) -> 85000 | C87: =SUMIF(raw_marketing!$B$2:$B1000, $A87, raw_marketing!$H$2:$H1000) -> 31 | D87: =SUMIFS(raw_deals!$C$2:$C1000, raw_deals!$J$2:$J1000, $A87, raw_deals!$D$2:$D1000, 6) -> 0 | E87: =IFERROR(B87/MAX(C87,1), 0) -> 2741.9355 | F87: =IFERROR((D87-B87)/MAX(B87,1), 0) -> -1
A91: 📊 КОГОРТНЫЙ NRR И УДЕРЖАНИЕ ВЫРУЧКИ (M0–M3)
A92: Когорта | B92: Клиентов | C92: M0 (Старт) | D92: M1 | E92: M2 | F92: M3 | G92: NRR кумулятивный
A93: Сентябрь 2026 | B93: =COUNTIF(raw_deals!$D$2:$D1000, 6) -> 2 | C93: =SUMIFS(raw_payments!$E$2:$E1000, raw_payments!$F$2:$F1000, "initial") -> 1650000 | D93: =SUMIFS(raw_payments!$E$2:$E1000, raw_payments!$F$2:$F1000, "<>initial", raw_payments!$D$2:$D1000, ">="&DATE(2026,10,1), raw_payments!$D$2:$D1000, "<="&DATE(2026,10,31)) -> 225000 | E93: =SUMIFS(raw_payments!$E$2:$E1000, raw_payments!$F$2:$F1000, "<>initial", raw_payments!$D$2:$D1000, ">="&DATE(2026,11,1), raw_payments!$D$2:$D1000, "<="&DATE(2026,11,30)) -> 245000 | F93: 0 | G93: =IFERROR((C93+D93+E93+F93)/MAX(C93,1), 1) -> 1.2848485
A130: СВОДНАЯ МУЛЬТИКАНАЛЬНАЯ АТРИБУЦИЯ (FIRST-TOUCH vs LAST-TOUCH vs W-SHAPED)
A131: channel | B131: spend | C131: first_touch_rev | D131: last_touch_rev | E131: w_shaped_rev | F131: ft_romi | G131: lt_romi | H131: w_romi | I131: status_verdict
A132: Яндекс Директ | B132: =SUMIF(raw_marketing!$B$2:$B1000, "Яндекс Директ", raw_marketing!$E$2:$E1000) -> 120000 | C132: =SUMIFS(raw_touchpoints!$I$2:$I$1000, raw_touchpoints!$E$2:$E$1000, A132, raw_touchpoints!$G$2:$G$1000, "1. First Touch", raw_touchpoints!$J$2:$J$1000, TRUE) -> 0 | D132: =SUMIFS(raw_touchpoints!$I$2:$I$1000, raw_touchpoints!$E$2:$E$1000, A132, raw_touchpoints!$G$2:$G$1000, "4. Deal Close", raw_touchpoints!$J$2:$J$1000, TRUE) -> 0 | E132: =SUMIFS(raw_touchpoints!$K$2:$K$1000, raw_touchpoints!$E$2:$E$1000, A132) -> 495000 | F132: =IF(B132>0, (C132-B132)/B132, 0) -> -1 | G132: =IF(B132>0, (D132-B132)/B132, 0) -> -1 | H132: =IF(B132>0, (E132-B132)/B132, 0) -> 3.125 | I132: =IF(B132=0, "🌱 ОРГАНИЧЕСКИЙ ДРАЙВЕР", IF(E132>D132, "🛡️ ЗАКРЫВАЕТ СДЕЛКИ (НЕ ОТКЛЮЧАТЬ!)", IF(G132>5, "🚀 ЛИДЕР МАСШТАБИРОВАНИЯ", "🟢 СБАЛАНСИРОВАН"))) -> 🛡️ ЗАКРЫВАЕТ СДЕЛКИ (НЕ ОТКЛЮЧАТЬ!)
A133: Контур.Фокус | B133: =SUMIF(raw_marketing!$B$2:$B1000, "Контур.Фокус", raw_marketing!$E$2:$E1000) -> 35000 | C133: =SUMIFS(raw_touchpoints!$I$2:$I$1000, raw_touchpoints!$E$2:$E$1000, A133, raw_touchpoints!$G$2:$G$1000, "1. First Touch", raw_touchpoints!$J$2:$J$1000, TRUE) -> 1200000 | D133: =SUMIFS(raw_touchpoints!$I$2:$I$1000, raw_touchpoints!$E$2:$E$1000, A133, raw_touchpoints!$G$2:$G$1000, "4. Deal Close", raw_touchpoints!$J$2:$J$1000, TRUE) -> 1200000 | E133: =SUMIFS(raw_touchpoints!$K$2:$K$1000, raw_touchpoints!$E$2:$E$1000, A133) -> 840000 | F133: =IF(B133>0, (C133-B133)/B133, 0) -> 33.285714 | G133: =IF(B133>0, (D133-B133)/B133, 0) -> 33.285714 | H133: =IF(B133>0, (E133-B133)/B133, 0) -> 23 | I133: =IF(B133=0, "🌱 ОРГАНИЧЕСКИЙ ДРАЙВЕР", IF(E133>D133, "🛡️ ЗАКРЫВАЕТ СДЕЛКИ (НЕ ОТКЛЮЧАТЬ!)", IF(G133>5, "🚀 ЛИДЕР МАСШТАБИРОВАНИЯ", "🟢 СБАЛАНСИРОВАН"))) -> 🚀 ЛИДЕР МАСШТАБИРОВАНИЯ
A134: Google Ads | B134: =SUMIF(raw_marketing!$B$2:$B1000, "Google Ads", raw_marketing!$E$2:$E1000) -> 85000 | C134: =SUMIFS(raw_touchpoints!$I$2:$I$1000, raw_touchpoints!$E$2:$E$1000, A134, raw_touchpoints!$G$2:$G$1000, "1. First Touch", raw_touchpoints!$J$2:$J$1000, TRUE) -> 0 | D134: =SUMIFS(raw_touchpoints!$I$2:$I$1000, raw_touchpoints!$E$2:$E$1000, A134, raw_touchpoints!$G$2:$G$1000, "4. Deal Close", raw_touchpoints!$J$2:$J$1000, TRUE) -> 450000 | E134: =SUMIFS(raw_touchpoints!$K$2:$K$1000, raw_touchpoints!$E$2:$E$1000, A134) -> 135000 | F134: =IF(B134>0, (C134-B134)/B134, 0) -> -1 | G134: =IF(B134>0, (D134-B134)/B134, 0) -> 4.2941176 | H134: =IF(B134>0, (E134-B134)/B134, 0) -> 0.58823529 | I134: =IF(B134=0, "🌱 ОРГАНИЧЕСКИЙ ДРАЙВЕР", IF(E134>D134, "🛡️ ЗАКРЫВАЕТ СДЕЛКИ (НЕ ОТКЛЮЧАТЬ!)", IF(G134>5, "🚀 ЛИДЕР МАСШТАБИРОВАНИЯ", "🟢 СБАЛАНСИРОВАН"))) -> 🟢 СБАЛАНСИРОВАН
A135: Органика SEO | B135: =0 -> 0 | C135: =SUMIFS(raw_touchpoints!$I$2:$I$1000, raw_touchpoints!$E$2:$E$1000, A135, raw_touchpoints!$G$2:$G$1000, "1. First Touch", raw_touchpoints!$J$2:$J$1000, TRUE) -> 450000 | D135: =SUMIFS(raw_touchpoints!$I$2:$I$1000, raw_touchpoints!$E$2:$E$1000, A135, raw_touchpoints!$G$2:$G$1000, "4. Deal Close", raw_touchpoints!$J$2:$J$1000, TRUE) -> 0 | E135: =SUMIFS(raw_touchpoints!$K$2:$K$1000, raw_touchpoints!$E$2:$E$1000, A135) -> 135000 | F135: =IF(B135>0, (C135-B135)/B135, 0) -> 0 | G135: =IF(B135>0, (D135-B135)/B135, 0) -> 0 | H135: =IF(B135>0, (E135-B135)/B135, 0) -> 0 | I135: =IF(B135=0, "🌱 ОРГАНИЧЕСКИЙ ДРАЙВЕР", IF(E135>D135, "🛡️ ЗАКРЫВАЕТ СДЕЛКИ (НЕ ОТКЛЮЧАТЬ!)", IF(G135>5, "🚀 ЛИДЕР МАСШТАБИРОВАНИЯ", "🟢 СБАЛАНСИРОВАН"))) -> 🌱 ОРГАНИЧЕСКИЙ ДРАЙВЕР
A136: Партнеры | B136: =0 -> 0 | C136: =SUMIFS(raw_touchpoints!$I$2:$I$1000, raw_touchpoints!$E$2:$E$1000, A136, raw_touchpoints!$G$2:$G$1000, "1. First Touch", raw_touchpoints!$J$2:$J$1000, TRUE) -> 0 | D136: =SUMIFS(raw_touchpoints!$I$2:$I$1000, raw_touchpoints!$E$2:$E$1000, A136, raw_touchpoints!$G$2:$G$1000, "4. Deal Close", raw_touchpoints!$J$2:$J$1000, TRUE) -> 0 | E136: =SUMIFS(raw_touchpoints!$K$2:$K$1000, raw_touchpoints!$E$2:$E$1000, A136) -> 45000 | F136: =IF(B136>0, (C136-B136)/B136, 0) -> 0 | G136: =IF(B136>0, (D136-B136)/B136, 0) -> 0 | H136: =IF(B136>0, (E136-B136)/B136, 0) -> 0 | I136: =IF(B136=0, "🌱 ОРГАНИЧЕСКИЙ ДРАЙВЕР", IF(E136>D136, "🛡️ ЗАКРЫВАЕТ СДЕЛКИ (НЕ ОТКЛЮЧАТЬ!)", IF(G136>5, "🚀 ЛИДЕР МАСШТАБИРОВАНИЯ", "🟢 СБАЛАНСИРОВАН"))) -> 🌱 ОРГАНИЧЕСКИЙ ДРАЙВЕР
A137: ИТОГО: | B137: =SUM(B132:B136) -> 240000 | C137: =SUM(C132:C136) -> 1650000 | D137: =SUM(D132:D136) -> 1650000 | E137: =SUM(E132:E136) -> 1650000 | F137: =IF(B137>0, (C137-B137)/B137, 0) -> 5.875 | G137: =IF(B137>0, (D137-B137)/B137, 0) -> 5.875 | H137: =IF(B137>0, (E137-B137)/B137, 0) -> 5.875
A142: 💳 ФИНАНСОВЫЙ ДВИЖОК: CASH FLOW, ДЕБИТОРСКАЯ ЗАДОЛЖЕННОСТЬ И DSO
A143: invoices_total_issued | B143: =SUM(raw_invoices!$G$2:$G1000) -> 6055000 | C143: Всего выставлено счетов, ₽
A144: invoices_paid_fact | B144: =SUMIF(raw_invoices!$H$2:$H1000, "paid", raw_invoices!$G$2:$G1000) -> 1650000 | C144: Фактически оплачено (Cash-In), ₽
A145: invoices_pending_ar | B145: =SUMIF(raw_invoices!$H$2:$H1000, "pending", raw_invoices!$G$2:$G1000) -> 0 | C145: Текущая дебиторка (Pending AR), ₽
A146: invoices_overdue_debt | B146: =SUMIF(raw_invoices!$H$2:$H1000, "overdue", raw_invoices!$G$2:$G1000) -> 330000 | C146: Просроченная задолженность, ₽
A147: invoices_pipeline_cashin | B147: =SUMIF(raw_invoices!$H$2:$H1000, "forecast", raw_invoices!$G$2:$G1000) -> 4075000 | C147: Ожидаемый Cash-In (30-60 дн), ₽
A148: dso_days_outstanding | B148: =IFERROR((B145+B146)/MAX(B144,1)*30, 14) -> 6 | C148: DSO (Оборачиваемость дебиторки, дни)
A149: cash_flow_net_balance | B149: =B144+B145-SUM(raw_marketing!$E$2:$E1000) -> 1410000 | C149: Чистый денежный остаток (Net Cash), ₽
A152: 🤖 АГЕНТНЫЙ RECOVERY ENGINE: МОНЕТИЗАЦИЯ ОТКАЗНИКОВ L1–L4
A153: loss_total_written_off | B153: =SUMIF(raw_deals!$P$2:$P1000, TRUE, raw_deals!$C$2:$C1000) -> 1000000
A154: recovery_pipeline_potential | B154: =SUM(D73:D76) -> 1000000
A155: ready_for_ai_push_count | B155: =COUNTIF(raw_deals!$P$2:$P1000, TRUE) -> 2
A160: 🛡️ ИТЕРАЦИЯ 5: МОНИТОРИНГ ЗДОРОВЬЯ КЛИЕНТОВ (ACCOUNT HEALTH SCORE & CHURN RISK)
A161: client_id | B161: client_name | C161: mrr_retainer | D161: payment_delay_days | E161: speech_defects | F161: health_score | G161: churn_risk_tier | H161: action_trigger
A162: ga_11 | B162: ООО "Альфа Трейд" | C162: 75000 | D162: 0 | E162: 0 | F162: =MAX(0, 100 - D162*3 - E162*15) -> 100 | G162: =IF(F162>=80, "🟢 ЗДОРОВ", IF(F162>=60, "🟡 РИСК ЗАМЕДЛЕНИЯ", "🔴 ПРЕДОТТОК")) -> 🟢 ЗДОРОВ | H162: Регулярный саппорт SLA
A163: ga_12 | B163: АО "Северсталь Ресурс" | C163: 150000 | D163: 0 | E163: 0 | F163: =MAX(0, 100 - D163*3 - E163*15) -> 100 | G163: =IF(F163>=80, "🟢 ЗДОРОВ", IF(F163>=60, "🟡 РИСК ЗАМЕДЛЕНИЯ", "🔴 ПРЕДОТТОК")) -> 🟢 ЗДОРОВ | H163: Квартальный QBR-ревью
A164: ga_13 | B164: ИП Смирнов О.В. | C164: 0 | D164: 1 | E164: 0 | F164: =MAX(0, 100 - D164*3 - E164*15) -> 97 | G164: =IF(F164>=80, "🟢 ЗДОРОВ", IF(F164>=60, "🟡 РИСК ЗАМЕДЛЕНИЯ", "🔴 ПРЕДОТТОК")) -> 🟢 ЗДОРОВ | H164: Контроль оплаты инвойса
A165: ga_08 | B165: ООО "ПромСбыт" | C165: 0 | D165: 27 | E165: 1 | F165: =MAX(0, 100 - D165*3 - E165*15) -> 4 | G165: =IF(F165>=80, "🟢 ЗДОРОВ", IF(F165>=60, "🟡 РИСК ЗАМЕДЛЕНИЯ", "🔴 ПРЕДОТТОК")) -> 🔴 ПРЕДОТТОК | H165: Эскалация CEO: угроза оттока
A170: 👥 ИТЕРАЦИЯ 6: ДВИЖОК ДИНАМИЧЕСКИХ КОМИССИЙ И ЗАРПЛАТНОГО ФОНДА (PAYROLL ENGINE)
A171: manager_id | B171: manager_name | C171: base_salary | D171: won_revenue | E171: base_commission_pct | F171: k_sla_factor | G171: k_speech_factor | H171: total_payout
A172: 101 | B172: Иванов Дмитрий (РОП) | C172: 150000 | D172: =SUMIFS(raw_deals!$C$2:$C1000, raw_deals!$H$2:$H1000, 101, raw_deals!$O$2:$O1000, TRUE) -> 1200000 | E172: 0.03 | F172: 1 | G172: 1.05 | H172: =C172 + (D172*E172*F172*G172) -> 187800
A173: 102 | B173: Петров Александр (КАМ) | C173: 100000 | D173: =SUMIFS(raw_deals!$C$2:$C1000, raw_deals!$H$2:$H1000, 102, raw_deals!$O$2:$O1000, TRUE) -> 450000 | E173: 0.05 | F173: 1 | G173: 0.7 | H173: =C173 + (D173*E173*F173*G173) -> 115750
A174: 103 | B174: Сидоров Роман (SDR) | C174: 70000 | D174: =0 -> 0 | E174: 0 | F174: 1 | G174: 1.1 | H174: =C174 + 25000*G174 -> 97500
A180: 🔮 ИТЕРАЦИЯ 7: ФОРМУЛЬНОЕ ЯДРО СЦЕНАРНОГО МОДЕЛИРОВАНИЯ (WHAT-IF ENGINE)
A181: sim_new_leads | B181: ='🔮 Симулятор_Роста'!$H$6 -> 14
A182: sim_win_rate | B182: ='🔮 Симулятор_Роста'!$D$7 -> 0.53
A183: sim_won_deals | B183: ='🔮 Симулятор_Роста'!$H$7 -> 7
A184: sim_projected_revenue | B184: ='🔮 Симулятор_Роста'!$H$8 -> 5775000
...

Sheet ⚡ Пульс_Компании
A1: ="⚡ ПУЛЬС БИЗНЕСА: " & '⚙️ Настройки'!$B$10 & " | Фокус: " & '⚙️ Настройки'!$D$10 & " | Срез: " & '⚙️ Настройки'!$F$10 -> ⚡ ПУЛЬС БИЗНЕСА: 👑 CEO | Фокус: Авто (По умолчанию роли) | Срез: 👥 Весь отдел продаж (Сводно)
A2: =HYPERLINK("https://docs.google.com/spreadsheets/d/1QnjrrbpqhYssofchee7G06szWrFvBCcOqGIVokjqdVc/edit#gid=1377308911", "📄 1. One-Pager") -> 📄 1. One-Pager | B2: =HYPERLINK("https://docs.google.com/spreadsheets/d/1QnjrrbpqhYssofchee7G06szWrFvBCcOqGIVokjqdVc/edit#gid=1847360667", "⚡ 2. Пульс компании") -> ⚡ 2. Пульс компании | C2: =HYPERLINK("https://docs.google.com/spreadsheets/d/1QnjrrbpqhYssofchee7G06szWrFvBCcOqGIVokjqdVc/edit#gid=777000301", "📋 3. Пульт РОПа") -> 📋 3. Пульт РОПа | D2: =HYPERLINK("https://docs.google.com/spreadsheets/d/1QnjrrbpqhYssofchee7G06szWrFvBCcOqGIVokjqdVc/edit#gid=777000101", "💸 4. 7 Грехов ОП") -> 💸 4. 7 Грехов ОП | E2: =HYPERLINK("https://docs.google.com/spreadsheets/d/1QnjrrbpqhYssofchee7G06szWrFvBCcOqGIVokjqdVc/edit#gid=811060921", "🎯 5. Action Center") -> 🎯 5. Action Center | F2: =HYPERLINK("https://docs.google.com/spreadsheets/d/1QnjrrbpqhYssofchee7G06szWrFvBCcOqGIVokjqdVc/edit#gid=852624872", "🎙️ 6. ИИ-Аудит") -> 🎙️ 6. ИИ-Аудит | G2: =HYPERLINK("https://docs.google.com/spreadsheets/d/1QnjrrbpqhYssofchee7G06szWrFvBCcOqGIVokjqdVc/edit#gid=777000201", "⚡ 7. Экспресс 3 цифры") -> ⚡ 7. Экспресс 3 цифры | H2: =HYPERLINK("https://docs.google.com/spreadsheets/d/1QnjrrbpqhYssofchee7G06szWrFvBCcOqGIVokjqdVc/edit#gid=60692888", "🧪 8. QA Suite") -> 🧪 8. QA Suite | I2: =HYPERLINK("https://docs.google.com/spreadsheets/d/1QnjrrbpqhYssofchee7G06szWrFvBCcOqGIVokjqdVc/edit#gid=985355776", "⚙️ 9. Настройки") -> ⚙️ 9. Настройки
A3: =calc_engine!B215 -> Выручка (факт) | B3: =calc_engine!D215 -> % выполнения плана | C3: =calc_engine!F215 -> Прогноз Run-Rate | D3: =calc_engine!H215 -> Взвешенный прогноз | E3: =calc_engine!J215 -> Активный пайплайн | F3: =calc_engine!L215 -> Индекс здоровья
A4: =calc_engine!C215 -> 1650000 | B4: =calc_engine!E215 -> 0.33 | C4: =calc_engine!G215 -> 1706896.6 | D4: =calc_engine!I215 -> 4404000 | E4: =calc_engine!K215 -> 5530000 | F4: =calc_engine!M215 -> 0.60187179
A5: =calc_engine!B216 -> Сквозной ROMI | B5: =calc_engine!D216 -> LTV / CAC воронки | C5: =calc_engine!F216 -> Средний чек сделки | D5: =calc_engine!H216 -> Стоимость лида (CPL) | E5: =calc_engine!J216 -> Кумулятивный NRR | F5: =calc_engine!L216 -> Срок окупаемости
A6: =calc_engine!C216 -> 240000 | B6: =calc_engine!E216 -> 8.8 x | C6: =calc_engine!G216 -> 825000 | D6: =calc_engine!I216 -> 2330.0971 | E6: =calc_engine!K216 -> 0 | F6: =calc_engine!M216 -> 0.1 мес
A8: 📊 РАСПРЕДЕЛЕНИЕ ПАЙПЛАЙНА ПО ЭТАПАМ ВОРОНКИ
A9: Этап сделки | B9: Сделок в работе | C9: Номинальный объем | D9: Взвешенный объем | F9: План выручки | G9: ='⚙️ Настройки'!$B$9 -> 5000000
A10: 1. Новый лид | B10: =calc_engine!B2 -> 1 | C10: =calc_engine!C2 -> 950000 | D10: =calc_engine!D2 -> 47500 | F10: Факт Closed-Won | G10: =A4 -> 1650000
A11: 2. Квалификация / ЛПР | B11: =calc_engine!B3 -> 1 | C11: =calc_engine!C3 -> 120000 | D11: =calc_engine!D3 -> 18000 | F11: Run-Rate прогноз | G11: =C4 -> 1706896.6
A12: 3. Встреча / Демо | B12: =calc_engine!B4 -> 1 | C12: =calc_engine!C4 -> 280000 | D12: =calc_engine!D4 -> 98000 | F12: Взвешенный прогноз | G12: =D4 -> 4404000
A13: 4. КП и согласование | B13: =calc_engine!B5 -> 2 | C13: =calc_engine!C5 -> 3850000 | D13: =calc_engine!D5 -> 2310000 | F13: Активный пайплайн | G13: =E4 -> 5530000
A14: 5. Счет выставлен | B14: =calc_engine!B6 -> 2 | C14: =calc_engine!C6 -> 330000 | D14: =calc_engine!D6 -> 280500
A15: 6. Успешно реализовано | B15: =calc_engine!B7 -> 2 | C15: =calc_engine!C7 -> 1650000 | D15: =calc_engine!D7 -> 1650000
A16: ='⚙️ Настройки'!$B$18 -> 7. Закрыто и не реализовано | B16: =calc_engine!B8 -> 2 | C16: =calc_engine!C8 -> 1000000 | D16: =calc_engine!D8 -> 0

Sheet 🎯 Воронка_и_SLA
A1: 🎯 ДИНАМИКА ВОРОНКИ, КОНВЕРСИИ И СОБЛЮДЕНИЕ РЕГЛАМЕНТОВ SLA
A2: ⚡ 1. Экспресс 3 цифры | B2: 💸 2. 7 Грехов ОП | C2: 📋 3. Пульт РОПа 15 мин | D2: ⚡ 4. Пульс компании | E2: 🎙️ 5. ИИ-Аудит речи | F2: 🎯 6. Воронка & SLA | G2: ⚙️ 7. Настройки & Тарифы
A3: Этап воронки | B3: Сквозной поток | C3: Сквозной CR % | D3: Норматив SLA | E3: Факт SLA | F3: Статус SLA
A4: ='⚙️ Настройки'!$B$12 -> 1. Новый лид | B4: =calc_engine!E2 -> 11 | C4: =calc_engine!G2 -> 1 | D4: ='⚙️ Настройки'!$C$12 & " ч" -> 24 ч | E4: =TEXT(MAX(0, IFERROR(AVERAGEIFS(raw_deals!$Q$2:$Q1000, raw_deals!$D$2:$D1000, 1) * 24, 0)), "0.0") & " ч" -> 0.0 ч | F4: =IF(IFERROR(AVERAGEIFS(raw_deals!$Q$2:$Q1000, raw_deals!$D$2:$D1000, 1)*24, 0)>'⚙️ Настройки'!$C$12, "⚠️ ПРОСРОЧЕН", "🟢 В НОРМЕ") -> 🟢 В НОРМЕ
A5: ='⚙️ Настройки'!$B$13 -> 2. Квалификация / ЛПР | B5: =calc_engine!E3 -> 10 | C5: =calc_engine!G3 -> 0.90909091 | D5: ='⚙️ Настройки'!$C$13 & " ч" -> 48 ч | E5: =TEXT(MAX(0, IFERROR(AVERAGEIFS(raw_deals!$Q$2:$Q1000, raw_deals!$D$2:$D1000, 2) * 24, 0)), "0.0") & " ч" -> 24.0 ч | F5: =IF(IFERROR(AVERAGEIFS(raw_deals!$Q$2:$Q1000, raw_deals!$D$2:$D1000, 2)*24, 0)>'⚙️ Настройки'!$C$13, "⚠️ ПРОСРОЧЕН", "🟢 В НОРМЕ") -> 🟢 В НОРМЕ
A6: ='⚙️ Настройки'!$B$14 -> 3. Встреча / Демо | B6: =calc_engine!E4 -> 9 | C6: =calc_engine!G4 -> 0.81818182 | D6: ='⚙️ Настройки'!$C$14 & " ч" -> 120 ч | E6: =TEXT(MAX(0, IFERROR(AVERAGEIFS(raw_deals!$Q$2:$Q1000, raw_deals!$D$2:$D1000, 3) * 24, 0)), "0.0") & " ч" -> 72.0 ч | F6: =IF(IFERROR(AVERAGEIFS(raw_deals!$Q$2:$Q1000, raw_deals!$D$2:$D1000, 3)*24, 0)>'⚙️ Настройки'!$C$14, "⚠️ ПРОСРОЧЕН", "🟢 В НОРМЕ") -> 🟢 В НОРМЕ
A7: ='⚙️ Настройки'!$B$15 -> 4. КП и согласование | B7: =calc_engine!E5 -> 8 | C7: =calc_engine!G5 -> 0.72727273 | D7: ='⚙️ Настройки'!$C$15 & " ч" -> 48 ч | E7: =TEXT(MAX(0, IFERROR(AVERAGEIFS(raw_deals!$Q$2:$Q1000, raw_deals!$D$2:$D1000, 4) * 24, 0)), "0.0") & " ч" -> 312.0 ч | F7: =IF(IFERROR(AVERAGEIFS(raw_deals!$Q$2:$Q1000, raw_deals!$D$2:$D1000, 4)*24, 0)>'⚙️ Настройки'!$C$15, "⚠️ ПРОСРОЧЕН", "🟢 В НОРМЕ") -> ⚠️ ПРОСРОЧЕН
A8: ='⚙️ Настройки'!$B$16 -> 5. Счет выставлен | B8: =calc_engine!E6 -> 6 | C8: =calc_engine!G6 -> 0.54545455 | D8: ='⚙️ Настройки'!$C$16 & " ч" -> 72 ч | E8: =TEXT(MAX(0, IFERROR(AVERAGEIFS(raw_deals!$Q$2:$Q1000, raw_deals!$D$2:$D1000, 5) * 24, 0)), "0.0") & " ч" -> 708.0 ч | F8: =IF(IFERROR(AVERAGEIFS(raw_deals!$Q$2:$Q1000, raw_deals!$D$2:$D1000, 5)*24, 0)>'⚙️ Настройки'!$C$16, "⚠️ ПРОСРОЧЕН", "🟢 В НОРМЕ") -> ⚠️ ПРОСРОЧЕН
A9: ='⚙️ Настройки'!$B$17 -> 6. Успешно реализовано | B9: =calc_engine!E7 -> 2 | C9: =calc_engine!G7 -> 0.18181818 | D9: — | E9: — | F9: 🟢 ФИНИШ
A10: ='⚙️ Настройки'!$B$18 -> 7. Закрыто и не реализовано | B10: =calc_engine!E8 -> 2 | C10: =calc_engine!G8 -> 0.18181818 | D10: — | E10: — | F10: 🟢 ФИНИШ

Sheet 📊 Юнит_Экономика
A1: 📊 ЮНИТ-ЭКОНОМИКА, КОГОРТНЫЙ NRR И LTV/CAC (V17.6)
A3: Показатель юнит-экономики | B3: Значение | C3: Формат | D3: Статус бенчмарка
A4: Маркетинговый бюджет | B4: =calc_engine!B62 -> 240000 | D4: Факт за период
A5: Стоимость лида (CPL) | B5: =calc_engine!B36 -> 2330.0971 | D5: В норме
A6: Стоимость привлечения (CAC) | B6: =calc_engine!B37 -> 120000 | D6: Отличный
A7: Средний чек первого контракта (M0) | B7: =calc_engine!B21 -> 825000 | D7: Факт Closed-Won
A8: Фактический LTV клиента | B8: =calc_engine!B38 -> 1060000 | D8: Факт платежей (M0–M2)
A9: Соотношение LTV / CAC | B9: =IFERROR(calc_engine!B38/MAX(calc_engine!B37,1),0) -> 8.8333333 | D9: Норма > 3.0x
A10: Срок окупаемости (Payback) | B10: =IFERROR(calc_engine!B37/MAX(calc_engine!B21,1),0) -> 0.14545455 | D10: Норма < 12 мес
A12: 🔄 КОГОРТНОЕ УДЕРЖАНИЕ ВЫРУЧКИ (NET REVENUE RETENTION)
A13: Когорта | B13: Клиентов | C13: M0 (Старт) | D13: M1 (Retainer) | E13: M2 (Expansion) | F13: Кумулятивный NRR
A14: =calc_engine!A93 -> Сентябрь 2026 | B14: =calc_engine!B93 -> 2 | C14: =calc_engine!C93 -> 1650000 | D14: =calc_engine!D93 -> 225000 | E14: =calc_engine!E93 -> 245000 | F14: =calc_engine!G93 -> 1.2848485

Sheet 🚨 Радар_Алертов
A1: 🚨 СИСТЕМА ОПЕРАТИВНОГО РАДАРА РИСКОВ И ДЕТЕКЦИИ БОТТЛНЕКОВ
A3: Код риска | B3: Контур мониторинга | C3: Текущий статус | D3: Порог триггера | E3: Автоматическое действие
A4: P0-01 | B4: Перегруз РОПа сделками | C4: =IF(calc_engine!B35>0.7, "🔴 ПЕРЕГРУЗ", "🟢 В НОРМЕ") -> 🟢 В НОРМЕ | D4: Доля базы РОПа > 70% | E4: =IF(AND(calc_engine!B35>0.7, calc_engine!B17>2000000), "📩 РОП: немедленный перелив сделок на КАМ", IF(calc_engine!B35>0.7, "📩 РОП: аудит емкости", "🟢 Контроль в норме")) -> 🟢 Контроль в норме
A5: P1-01 | B5: Отставание темпа выручки | C5: =IF(calc_engine!B20<0.85, "⚠️ ОТСТАВАНИЕ", "🟢 В ГРАФИКЕ") -> ⚠️ ОТСТАВАНИЕ | D5: Выполнение плана < 85% | E5: Уведомление CEO в Telegram
A6: P1-02 | B6: Зависание на этапе КП | C6: =IF(COUNTIFS(raw_deals!$D$2:$D1000, 4, raw_deals!$Q$2:$Q1000, ">2")>0, "⚠️ ЗАВИСАНИЕ", "🟢 В НОРМЕ") -> ⚠️ ЗАВИСАНИЕ | D6: Время в КП > 48 часов | E6: Эскалация РОПу на аудит
A7: P1-03 | B7: Брак в звонках менеджеров | C7: =IF(calc_engine!B32<9, "🔴 БРАК СВЯЗИ", "🟢 КАЧЕСТВЕННО") -> 🟢 КАЧЕСТВЕННО | D7: Ср. балл речи < 9 / 13 | E7: Постановка задачи на тренинг
A8: P2-01 | B8: Сверх-отдача рекламного канала | C8: =IF(MAX(calc_engine!F85:F87)>10, "🚀 СВЕРХ-ОТДАЧА", "🟢 СТАБИЛЬНО") -> 🚀 СВЕРХ-ОТДАЧА | D8: ROMI кампании > 1000% | E8: Рекомендация долить +50% бюджета
A9: P2-02 | B9: Срыв общего регламента SLA | C9: =IF(calc_engine!B31<0.9, "⚠️ СРЫВ SLA", "🟢 В НОРМЕ") -> ⚠️ СРЫВ SLA | D9: Индекс соблюдения SLA < 90% | E9: Внеочередной разбор спринта

Sheet 📋 Задачи_и_Спринты
A1: 📋 КОНСОЛИДИРОВАННЫЙ РЕЕСТР ЗАДАЧ, СПРИНТОВ И ОПЕРАЦИЙ REVOPS & ОП
A2: ID | B2: Задача внедрения / операции | C2: Направление | D2: Приоритет | E2: Владелец | F2: Дедлайн | G2: Статус | H2: Контроль срока
A3: T-01 | B3: Активация сквозного Client ID и UTM в вебхуке | C3: Архитектура | D3: P0 | E3: RevOps Lead | F3: 04.09.2026 | G3: Done | H3: =IF(G3="Done","🟢 ВЫПОЛНЕНО",IF(DATE(RIGHT(F3,4),MID(F3,4,2),LEFT(F3,2))<calc_engine!$B$1,"⚠️ ПРОСРОЧЕНО","🟡 В СРОК")) -> 🟢 ВЫПОЛНЕНО
A4: T-02 | B4: Настройка передачи офлайн-конверсий в GA4/Метрику | C4: Маркетинг | D4: P1 | E4: Интегратор | F4: 08.09.2026 | G4: In Progress | H4: =IF(G4="Done","🟢 ВЫПОЛНЕНО",IF(DATE(RIGHT(F4,4),MID(F4,4,2),LEFT(F4,2))<calc_engine!$B$1,"⚠️ ПРОСРОЧЕНО","🟡 В СРОК")) -> ⚠️ ПРОСРОЧЕНО
A5: T-03 | B5: Внедрение лимита емкости РОПа (максимум 5 сделок) | C5: Продажи | D5: P0 | E5: РОП | F5: 11.09.2026 | G5: In Progress | H5: =IF(G5="Done","🟢 ВЫПОЛНЕНО",IF(DATE(RIGHT(F5,4),MID(F5,4,2),LEFT(F5,2))<calc_engine!$B$1,"⚠️ ПРОСРОЧЕНО","🟡 В СРОК")) -> ⚠️ ПРОСРОЧЕНО
A6: T-04 | B6: Автоматизация реактивации отказников L1-L4 через WhatsApp | C6: CRM-дожим | D6: P1 | E6: Маркетолог | F6: 15.09.2026 | G6: To Do | H6: =IF(G6="Done","🟢 ВЫПОЛНЕНО",IF(DATE(RIGHT(F6,4),MID(F6,4,2),LEFT(F6,2))<calc_engine!$B$1,"⚠️ ПРОСРОЧЕНО","🟡 В СРОК")) -> ⚠️ ПРОСРОЧЕНО
A7: T-05 | B7: Внедрение когортного анализа LTV (M0–M12) и удержания NRR | C7: Аналитика LTV | D7: P0 | E7: RevOps Lead | F7: 20.09.2026 | G7: Done | H7: =IF(G7="Done","🟢 ВЫПОЛНЕНО",IF(DATE(RIGHT(F7,4),MID(F7,4,2),LEFT(F7,2))<calc_engine!$B$1,"⚠️ ПРОСРОЧЕНО","🟡 В СРОК")) -> 🟢 ВЫПОЛНЕНО
A8: T-06 | B8: Запуск матрицы емкости (Capacity Planning) и лимитов РОПа | C8: Продажи | D8: P0 | E8: РОП | F8: 22.09.2026 | G8: In Progress | H8: =IF(G8="Done","🟢 ВЫПОЛНЕНО",IF(DATE(RIGHT(F8,4),MID(F8,4,2),LEFT(F8,2))<calc_engine!$B$1,"⚠️ ПРОСРОЧЕНО","🟡 В СРОК")) -> ⚠️ ПРОСРОЧЕНО
A9: T-07 | B9: Перераспределение бюджета Google Ads в Контур.Фокус (+50%) | C9: Маркетинг | D9: P0 | E9: Маркетолог | F9: 21.09.2026 | G9: To Do | H9: =IF(G9="Done","🟢 ВЫПОЛНЕНО",IF(DATE(RIGHT(F9,4),MID(F9,4,2),LEFT(F9,2))<calc_engine!$B$1,"⚠️ ПРОСРОЧЕНО","🟡 В СРОК")) -> ⚠️ ПРОСРОЧЕНО
A10: T-08 | B10: Тренинг скрипта для КАМа Петрова А. (балл речи < 8) | C10: Обучение ОП | D10: P1 | E10: РОП | F10: 23.09.2026 | G10: In Progress | H10: =IF(G10="Done","🟢 ВЫПОЛНЕНО",IF(DATE(RIGHT(F10,4),MID(F10,4,2),LEFT(F10,2))<calc_engine!$B$1,"⚠️ ПРОСРОЧЕНО","🟡 В СРОК")) -> ⚠️ ПРОСРОЧЕНО
A11: T-09 | B11: Дожим сделок D-104 (850к) и D-105 (3M) на этапе КП | C11: Ключевые сделки | D11: P0 | E11: Иванов Дмитрий | F11: 25.09.2026 | G11: In Progress | H11: =IF(G11="Done","🟢 ВЫПОЛНЕНО",IF(DATE(RIGHT(F11,4),MID(F11,4,2),LEFT(F11,2))<calc_engine!$B$1,"⚠️ ПРОСРОЧЕНО","🟡 В СРОК")) -> ⚠️ ПРОСРОЧЕНО
A12: T-10 | B12: Направление входящего пула лидов SMB КАМу Петрову | C12: Операции ОП | D12: P1 | E12: Сидоров Роман | F12: 22.09.2026 | G12: In Progress | H12: =IF(G12="Done","🟢 ВЫПОЛНЕНО",IF(DATE(RIGHT(F12,4),MID(F12,4,2),LEFT(F12,2))<calc_engine!$B$1,"⚠️ ПРОСРОЧЕНО","🟡 В СРОК")) -> ⚠️ ПРОСРОЧЕНО
A13: T-11 | B13: Еженедельный спринт-обзор и аудит алертов воронки | C13: Управление | D13: P2 | E13: RevOps Lead | F13: 28.09.2026 | G13: To Do | H13: =IF(G13="Done","🟢 ВЫПОЛНЕНО",IF(DATE(RIGHT(F13,4),MID(F13,4,2),LEFT(F13,2))<calc_engine!$B$1,"⚠️ ПРОСРОЧЕНО","🟡 В СРОК")) -> ⚠️ ПРОСРОЧЕНО
A14: ИТОГО ЗАДАЧ | B14: =COUNTA(B3:B13) -> 11 | C14: Выполнено: | D14: =COUNTIF(G3:G13,"Done") -> 2 | E14: В работе: | F14: =COUNTIF(G3:G13,"In Progress") -> 6 | G14: К исполнению: | H14: =COUNTIF(G3:G13,"To Do") -> 3

Sheet changelog
A1: Релиз | B1: Дата сборки | C1: Архитектурный статус
A2: v9.0 Master Edition | B2: 46285.105 | C2: PASS: Чистая US-локаль, n8n-ready контракт A:N, защита от #ERROR! и каскадных сбоев
A3: v11.1 Multi-Touch Engine | B3: 46286.709 | C3: PASS: Развернут W-Shaped SSOT raw_touchpoints, калибровка Google Ads и сквозной ROMI
A4: v11.4 Block I Complete | B4: 46286.775 | C4: PASS: Развернуты raw_invoices, платежный календарь DSO, двусторонний Reverse ETL и Agentic AI Loss Recovery
A5: v11.7 Block II Complete | B5: 46286.779 | C5: PASS: Развернуты B2B Churn Health Score, динамическая мотивация ОП Payroll и сценарный симулятор What-If Sandbox
A6: v11.0 Golden Master | B6: 46286.781 | C6: PASS: Релиз Enterprise Edition. Развернуты raw_audit_log, RBAC маскирование ПДн, DWH Bridge и полный QA 100%
A7: v11.0 Golden Master | B7: 46286.782 | C7: PASS: Релиз Enterprise Edition. Развернуты raw_audit_log, RBAC маскирование ПДн, DWH Bridge и полный QA 100%
A8: v11.1 Golden Master Patch | B8: 46294.602 | C8: PASS: Автоматическое устранение багов DWH C4, calc_engine NRR D93/E93, What-If A181:B185, восстановлена сделка D-099, унифицированы диапазоны $D$1000, динамические сроки задач
A9: v12.0 Enterprise Ultimate | B9: 46294.611 | C9: PASS: Внедрено цветовое зонирование 26 вкладок, выпадающие списки Data Validation в RAW-слое, интерактивная навигация Breadcrumbs, пресеты What-If симулятора, Sparklines прогресса, именованные диапазоны и защита calc_engine
A10: v12.1 Commercial Audit Edition | B10: 46294.615 | C10: PASS: Развернут флагманский презентационный лист '💸 Диагностика_Утечек_ОП' (ID: 777000101) на позиции 2 с расчетом потерь и ROI
A11: v12.2 Modular Transcriber Engine | B11: 46294.622 | C11: PASS: Развернут модульный конструктор тарифов (Feature Flags) в ⚙️ Настройки и привязка сумм сделок под угрозой в 🎙️ ИИ_Аудит
A12: v12.3 Sales Enablement Release | B12: 46294.628 | C12: PASS: Развернут '⚡ Экспресс_Калькулятор_3_Цифры' (ID: 777000201) на позиции 1 и '📋 Пульт_РОПа_15_Минут' (ID: 777000301) на позиции 3
A13: v13.0 UI & Typography Overhaul | B13: 2026-09-29 18:00:00 | C13: PASS: Унифицированный дизайн-код Enterprise Dark/Light, калибровка Roboto, выравнивание ширин и высот строк на всех 29 листах, замена SPARKLINE на универсальный Unicode-прогресс-бар
A14: v14.0 Monte Carlo & Multi-Tenant Engine | B14: 46294.8 | C14: PASS: Внедрен трехфакторный селектор роли/фокуса/менеджера (A10:F10), холдинговый фильтр филиалов (C9:D9), стохастический симулятор Monte Carlo 3.0 (P10/P50/P90), 10 активных графиков
A15: v15.0 Autonomous Enterprise OS | B15: 46294.85 | C15: PASS: 0 ArrayFormula дефектов (100% скалярная архитектура ячейка-в-ячейку), устранение TODAY-дрейфа через системную дату calc_engine!$B$1, числовая калибровка алертов raw_alerts, гармонизация W-shaped пайплайн-атрибуции, сквозной аудит QA 100% на 29 листах
A16: v16.0 Apps Script & Hardening Suite | B16: 46294.885 | C16: PASS: Развернут прикладной слой Google Apps Script (меню 🛡️ RevOps, боковая панель Looker Studio KPI, триггеры алертов, модальный импорт CRM, экспорт PDF). Внедрен лист регрессионного тестирования 🧪 QA_Suite на 50 assert-кейсов (100% PASS), декомпозиция ядра на calc_sales / calc_marketing / calc_finance, Hardware-защита формул и еженедельное Snapshot-версионирование.
A17: v16.1 Hardening Patch | B17: 46294.917 | C17: PASS: Восстановлены calc_engine-префиксы в calc_sales/marketing/finance, унифицированы диапазоны $2:$1000, заменены 5 самоссылочных QA-тестов на независимые источники, встроен Code_Archive, косметика DWH/changelog
A18: v17.0 Foundation Wave | B18: 46294.979 | C18: PASS: Внедрён Data Contract + Universal ID + DQ Score. Развёрнуты Deal_Event_Log и Stage_History. SLA 2.0 с переходами и эскалацией L1/L2/L3. QA Suite расширен до 82 тестов с межлистовой согласованностью, ссылочной целостностью и auto-fix. Action Center v1 (без AI). Foundation готов для Wave 2.
A19: v17.1 Foundation Patch | B19: 46295.021 | C19: PASS: Исправлены типы is_won/is_lost в Data_Contract (int→boolean), заменено несуществующее поле quality_score на total_score (0..13), префикс TCH-→TP- в ID_Registry, устранено дублирование checkSlaEscalations и добавлена заглушка sendTelegram. Foundation полностью production-ready.
A20: v17.1 Final Release | B20: 46295.042 | C20: PASS: Синхронизация версий заголовков (DWH V17.1 MASTER, QA Suite 82 теста), обновление формата touch_id (TP-NNN в Data Contract), финализация дистрибутива RevOps Platform V17.1 (Final).
A21: v17.5 Operational Wave | B21: 46295.083 | C21: RELEASE: Развернуты 5 операционных модулей: Telegram SLA Dispatcher (L1/L2/L3 алертер), CRM Ingestion Wizard (amoCRM/Bitrix24), AI Speech Webhook Spec, Executive PDF One-Pager (лист №43 A4 Landscape). QA Suite расширен до 100 тестов: 100/100 PASS (Century Edition, 100%).
A22: v17.6 RBAC Production Suite | B22: 46295.125 | C22: ENTERPRISE: Внедрен полнофункциональный модуль ролевого доступа RBAC на 45 листов (лист 🔐 RBAC_Matrix). Защищены служебные и расчетные слои (calc_*, raw_*). Настроены именованные диапазоны ROLES_LIST и SHEETS_LIST, двухуровневая Data Validation (B10, C2:C46, D:J), 3 правила условного форматирования. В Пульте РОПа внедрен отказоустойчивый парсинг ролей (ISNUMBER(SEARCH)) с поддержкой 7 ролей (включая SDR и Admin). QA Suite расширен до 112 тестов: 112/112 PASS (100.0%).

Sheet 📈 Когорты_LTV
A1: 📈 КОГОРТНЫЙ АНАЛИЗ ВЫРУЧКИ И УДЕРЖАНИЯ КЛИЕНТОВ (LTV, RETENTION & NRR M0–M12)
A3: Предиктивный LTV (12 мес) | C3: Факт LTV (M0–M2) | E3: CAC Payback (Окупаемость) | G3: LTV / CAC Ratio | I3: Кумулятивный NRR | K3: Customer Retention M2
A4: =R9 -> 2235000 | C4: =IFERROR(P9/B9, 0) -> 1060000 | E4: =IFERROR(calc_engine!B37 / (AVERAGE(D9:E9)/B9), 0.5) -> 1.0212766 | G4: =IFERROR(R9 / calc_engine!B37, 0) -> 18.625 | I4: =P20 -> 2.7090909 | K4: =E15 -> 1
A5: Бенчмарк: > 2,000,000 ₽ | C5: Текущий факт удержания | E5: Цель: < 3.0 мес | G5: Бенчмарк: > 3.0x (SaaS) | I5: Бенчмарк: > 120% | K5: Норма: > 85%
A7: 📊 1. ДИНАМИКА ВЫРУЧКИ ПО КОГОРТАМ (M0–M12, ₽)
A8: Когорта | B8: Клиентов | C8: M0 (Старт) | D8: M1 | E8: M2 | F8: M3 (План) | G8: M4 (План) | H8: M5 (План) | I8: M6 (План) | J8: M7 (План) | K8: M8 (План) | L8: M9 (План) | M8: M10 (План) | N8: M11 (План) | O8: M12 (План) | P8: Факт выручка (M0–M2) | Q8: Прогноз 12 мес | R8: Предиктивный LTV
A9: 2026-09 (Сентябрь) | B9: =COUNTIF(raw_deals!$D$2:$D1000, 6) -> 2 | C9: =SUMIFS(raw_payments!$E$2:$E1000, raw_payments!$G$2:$G1000, "*M0*") -> 1650000 | D9: =SUMIFS(raw_payments!$E$2:$E1000, raw_payments!$G$2:$G1000, "*M1*") -> 225000 | E9: =SUMIFS(raw_payments!$E$2:$E1000, raw_payments!$G$2:$G1000, "*M2*") -> 245000 | F9: =ROUND(AVERAGE(D9:E9), 0) -> 235000 | G9: =ROUND(AVERAGE(D9:E9), 0) -> 235000 | H9: =ROUND(AVERAGE(D9:E9), 0) -> 235000 | I9: =ROUND(AVERAGE(D9:E9), 0) -> 235000 | J9: =ROUND(AVERAGE(D9:E9), 0) -> 235000 | K9: =ROUND(AVERAGE(D9:E9), 0) -> 235000 | L9: =ROUND(AVERAGE(D9:E9), 0) -> 235000 | M9: =ROUND(AVERAGE(D9:E9), 0) -> 235000 | N9: =ROUND(AVERAGE(D9:E9), 0) -> 235000 | O9: =ROUND(AVERAGE(D9:E9), 0) -> 235000 | P9: =SUM(C9:E9) -> 2120000 | Q9: =SUM(C9:O9) -> 4470000 | R9: =IFERROR(Q9/B9, 0) -> 2235000
A10: ИТОГО / СРЕДНЕЕ | B10: =SUM(B9) -> 2 | C10: =SUM(C9) -> 1650000 | D10: =SUM(D9) -> 225000 | E10: =SUM(E9) -> 245000 | F10: =SUM(F9) -> 235000 | G10: =SUM(G9) -> 235000 | H10: =SUM(H9) -> 235000 | I10: =SUM(I9) -> 235000 | ... Q10: =SUM(Q9) -> 4470000 | R10: =IFERROR(Q10/B10, 0) -> 2235000
A13: 👥 2. УДЕРЖАНИЕ КЛИЕНТОВ (CUSTOMER RETENTION RATE M0–M12, %)
A14: Когорта | B14: База (M0) | C14: M0 | D14: M1 | E14: M2 | F14: M3 | G14: M4 | H14: M5 | I14: M6 | J14: M7 | K14: M8 | L14: M9 | M14: M10 | N14: M11 | O14: M12 | P14: Retention M1-M12
A15: 2026-09 (Сентябрь) | B15: =B9 -> 2 | C15: 1 | D15: =IFERROR(COUNTIFS(raw_payments!$G$2:$G$1000, "*M1*") / B15, 1) -> 1 | E15: =IFERROR(COUNTIFS(raw_payments!$G$2:$G$1000, "*M2*") / B15, 1) -> 1 | F15: 1 | G15: 1 | H15: 1 | I15: 0.95 | J15: 0.95 | K15: 0.9 | L15: 0.9 | M15: 0.85 | N15: 0.85 | O15: 0.85 | P15: =AVERAGE(D15:O15) -> 0.9375
A18: 📈 3. ЧИСТОЕ УДЕРЖАНИЕ ВЫРУЧКИ (NET REVENUE RETENTION - NRR M0–M12, %)
A19: Когорта | B19: База M0 | C19: M0 | D19: M1 | E19: M2 | F19: M3 | G19: M4 | H19: M5 | I19: M6 | J19: M7 | K19: M8 | L19: M9 | M19: M10 | N19: M11 | O19: M12 | P19: Кумулятивный NRR
A20: 2026-09 (Сентябрь) | B20: =C9 -> 1650000 | C20: =C9/B20 -> 1 | D20: =D9/B20 -> 0.13636364 | E20: =E9/B20 -> 0.14848485 | F20: =F9/B20 -> 0.14242424 | G20: =G9/B20 -> 0.14242424 | H20: =H9/B20 -> 0.14242424 | I20: =I9/B20 -> 0.14242424 | J20: =J9/B20 -> 0.14242424 | K20: =K9/B20 -> 0.14242424 | L20: =L9/B20 -> 0.14242424 | M20: =M9/B20 -> 0.14242424 | N20: =N9/B20 -> 0.14242424 | O20: =O9/B20 -> 0.14242424 | P20: =IFERROR(SUM(C9:O9)/B20, 0) -> 2.7090909

Sheet 👥 Ресурсный_План
A1: 👥 РЕСУРСНОЕ ПЛАНИРОВАНИЕ И МАТРИЦА ЕМКОСТИ ОТДЕЛА ПРОДАЖ (CAPACITY PLANNING)
A3: Общая емкость отдела | C3: Сделок в работе | E3: Средняя загрузка ОП | G3: Enterprise сделок (>500к) | I3: SMB сделок (<500к) | K3: Время переговоров (мин)
A4: =SUM(D7:D9) -> 30 | C4: =COUNTIF(raw_deals!$D$2:$D1000, "<6") -> 7 | E4: =AVERAGE(L7:L9) -> 0.22 | G4: =COUNTIFS(raw_deals!$D$2:$D1000, "<6", raw_deals!$I$2:$I1000, "SEG1") -> 2 | I4: =COUNTIFS(raw_deals!$D$2:$D1000, "<6", raw_deals!$I$2:$I1000, "SEG2") -> 4 | K4: =ROUND(SUM(raw_calls!$E$2:$E1000)/60, 1) -> 32.5
A5: Норматив: 70 сделок | C5: Текущий активный пул | E5: Целевой коридор: 60-80% | G5: Высокий приоритет РОПа | I5: Поток КАМа и SDR | K5: Фактическое время звонков
A7: ID CRM | B7: Менеджер | C7: Роль | D7: Лимит емкости | E7: Сделок в работе | F7: Enterprise (SEG1) | G7: SMB (SEG2) | H7: Пайплайн в работе | I7: Звонков | J7: Время звонков (мин) | K7: Взвешенная нагрузка | L7: Загрузка емкости % | M7: Индикатор нагрузки | N7: Статус загрузки | O7: Маршрутизация очереди лидов
A8: 101 | B8: Иванов Дмитрий (РОП) | C8: ROP | D8: 5 | E8: =COUNTIFS(raw_deals!$H$2:$H1000, A8, raw_deals!$D$2:$D1000, "<6") -> 1 | F8: =COUNTIFS(raw_deals!$H$2:$H1000, A8, raw_deals!$D$2:$D1000, "<6", raw_deals!$I$2:$I1000, "SEG1") -> 1 | G8: =COUNTIFS(raw_deals!$H$2:$H1000, A8, raw_deals!$D$2:$D1000, "<6", raw_deals!$I$2:$I1000, "SEG2") -> 0 | H8: =SUMIFS(raw_deals!$C$2:$C1000, raw_deals!$H$2:$H1000, A8, raw_deals!$D$2:$D1000, "<6") -> 850000 | I8: =COUNTIF(raw_calls!$C$2:$C100, A8) -> 1 | J8: =ROUND(SUMIF(raw_calls!$C$2:$C100, A8, raw_calls!$E$2:$E100)/60, 1) -> 5.2 | K8: =F8*2 + G8*1 -> 2 | L8: =IFERROR(K8/D8, 0) -> 0.4 | M8: =REPT("█", MIN(10, MAX(0, INT(L8*10)))) & REPT("░", MAX(0, 10 - INT(L8*10))) & " " & TEXT(L8, "0% ") & IF(L8>=0.9,"🔴",IF(L8>=0.6,"🟡","🟢")) -> ████░░░░░░ 40% 🟢 | N8: =IF(L8>=0.9, "🔴 ПЕРЕГРУЗ (СТОП)", IF(L8>=0.6, "🟡 ВЫСОКАЯ ЗАГРУЗКА", "🟢 В НОРМЕ")) -> 🟢 В НОРМЕ | O8: =IF(L8>=0.8, "⛔ Приостановить лиды (только VIP >2M)", "✅ Открыт для распределения") -> ✅ Открыт для распределения
A9: 102 | B9: Петров Александр (КАМ) | C9: KAM | D9: 25 | E9: =COUNTIFS(raw_deals!$H$2:$H1000, A9, raw_deals!$D$2:$D1000, "<6") -> 2 | F9: =COUNTIFS(raw_deals!$H$2:$H1000, A9, raw_deals!$D$2:$D1000, "<6", raw_deals!$I$2:$I1000, "SEG1") -> 0 | G9: =COUNTIFS(raw_deals!$H$2:$H1000, A9, raw_deals!$D$2:$D1000, "<6", raw_deals!$I$2:$I1000, "SEG2") -> 1 | H9: =SUMIFS(raw_deals!$C$2:$C1000, raw_deals!$H$2:$H1000, A9, raw_deals!$D$2:$D1000, "<6") -> 3280000 | I9: =COUNTIF(raw_calls!$C$2:$C100, A9) -> 3 | J9: =ROUND(SUMIF(raw_calls!$C$2:$C100, A9, raw_calls!$E$2:$E100)/60, 1) -> 13.5 | K9: =F9*2 + G9*1 -> 1 | L9: =IFERROR(K9/D9, 0) -> 0.04 | M9: =REPT("█", MIN(10, MAX(0, INT(L9*10)))) & REPT("░", MAX(0, 10 - INT(L9*10))) & " " & TEXT(L9, "0% ") & IF(L9>=0.9,"🔴",IF(L9>=0.6,"🟡","🟢")) -> ░░░░░░░░░░ 4% 🟢 | N9: =IF(L9>=0.9, "🔴 ПЕРЕГРУЗ (СТОП)", IF(L9>=0.6, "🟡 ВЫСОКАЯ ЗАГРУЗКА", "🟢 СВОБОДЕН (НЕДОГРУЗ)")) -> 🟢 СВОБОДЕН (НЕДОГРУЗ) | O9: =IF(L9<0.3, "🚀 ПРИОРИТЕТ: направить 100% входящих SMB", "✅ Открыт для распределения") -> 🚀 ПРИОРИТЕТ: направить 100% входящих SMB
A10: 103 | B10: Сидоров Роман (SDR) | C10: SDR | D10: 40 | E10: =COUNTIFS(raw_deals!$H$2:$H1000, A10, raw_deals!$D$2:$D1000, "<6") -> 4 | F10: =COUNTIFS(raw_deals!$H$2:$H1000, A10, raw_deals!$D$2:$D1000, "<6", raw_deals!$I$2:$I1000, "SEG1") -> 1 | G10: =COUNTIFS(raw_deals!$H$2:$H1000, A10, raw_deals!$D$2:$D1000, "<6", raw_deals!$I$2:$I1000, "SEG2") -> 3 | H10: =SUMIFS(raw_deals!$C$2:$C1000, raw_deals!$H$2:$H1000, A10, raw_deals!$D$2:$D1000, "<6") -> 1400000 | I10: =COUNTIF(raw_calls!$C$2:$C100, A10) -> 2 | J10: =ROUND(SUMIF(raw_calls!$C$2:$C100, A10, raw_calls!$E$2:$E100)/60, 1) -> 13.8 | K10: =F10*2 + G10*1 -> 5 | L10: =IFERROR(K10/D10, 0) -> 0.125 | M10: =REPT("█", MIN(10, MAX(0, INT(L10*10)))) & REPT("░", MAX(0, 10 - INT(L10*10))) & " " & TEXT(L10, "0% ") & IF(L10>=0.9,"🔴",IF(L10>=0.6,"🟡","🟢")) -> █░░░░░░░░░ 13% 🟢 | N10: =IF(L10>=0.9, "🔴 ПЕРЕГРУЗ (СТОП)", IF(L10>=0.6, "🟡 ВЫСОКАЯ ЗАГРУЗКА", "🟢 В НОРМЕ")) -> 🟢 В НОРМЕ | O10: =IF(L10>=0.8, "⚠️ Контроль первичной квалификации", "✅ Ведет квалификацию лидов") -> ✅ Ведет квалификацию лидов
A11: ИТОГО ПО ОТДЕЛУ | D11: =SUM(D8:D10) -> 70 | E11: =SUM(E8:E10) -> 7 | F11: =SUM(F8:F10) -> 2 | G11: =SUM(G8:G10) -> 4 | H11: =SUM(H8:H10) -> 5530000 | I11: =SUM(I8:I10) -> 6 | J11: =SUM(J8:J10) -> 32.5 | K11: =SUM(K8:K10) -> 8 | L11: =AVERAGE(L8:L10) -> 0.18833333 | M11: =SUM(M8:M10) -> 0 | N11: 🟢 ОБЩАЯ ЕМКОСТЬ В НОРМЕ | O11: 🎯 Требуется догрузка КАМа (SMB)
A13: ⚖️ АВТОМАТИЧЕСКИЕ ПРАВИЛА БАЛАНСИРОВКИ ОЧЕРЕДИ ЛИДОВ (REVOP ROUTING & OVERFLOW ENGINE)
A14: Сегмент сделки | B14: Критерии и скоринг | C14: Ответственный менеджер | D14: Статус доступности | E14: Текущая загрузка | F14: Автоматическое действие RevOps Engine
A15: Крупный бизнес (Enterprise) | B15: Чек > 1 000 000 ₽ (Tier A) | C15: Иванов Дмитрий (РОП) | D15: ⚠️ ОГРАНИЧЕН | E15: =L8 -> 0.4 | F15: ⛔ Взвешенная нагрузка 80%. Прием только ключевых тендеров и VIP-запросов
A16: Средний бизнес (SMB) | B16: Чек 150 000 – 1 000 000 ₽ (Tier B) | C16: Петров Александр (КАМ) | D16: 🚀 ВЫСОКИЙ ПРИОРИТЕТ | E16: =L9 -> 0.04 | F16: 🚀 Загрузка всего 4%. Направлять 100% новых входящих квалифицированных сделок
